Workbook
Name 费用种类列表: [1]费用种类列表!$A$2:$A$5211

Sheet 过机服务商重量差
A1: 运单号 | B1: 服务商单号 | C1: 渠道转单号 | D1: 销售产品 | E1: 产品组 | F1: 服务渠道 | G1: 服务渠道客服 | H1: 客户简称 | I1: 业务员 | J1: 出货实重 | K1: 出货材积重 | L1: 出货计费重 | M1: 服务商计费重 | N1: 差值
A2: QS0131-MX | B2: ICBU00000932919 | C2: 1ZG3325W0416448603 | D2: OK-FDX-DHL-TNT | E2: 非主营 | F2: OK-FDX-DHL-TNT | G2: 玉麒麟 | I2: 小飞侠 | J2: 1.87 | K2: 4.059 | L2: 3.5 | M2: 4.5 | N2: 1
A3: TL0131-NL | B3: ICBU00000932943 | C3: 1Z4W260E0409673969 | D3: OK-UPS红单 | E3: 非主营 | F3: OK-UPS红单 | G3: 玉麒麟 | I3: 小飞侠 | J3: 9.23 | K3: 4.277 | L3: 9.5 | M3: 9.5 | N3: 0
A4: FBA15G65R8GW | B4: ICBU00000932665 | C4: RCD24000759946 | D4: 澳大利亚海派-包税 | E4: 非主营 | F4: 澳大利亚海派-包税 | G4: 小旋风 | I4: 高雨晴 | J4: 105.07 | K4: 0.654 | L4: 0.7 | M4: 0.8 | N4: 0.1
A5: FBA15G65P13K | B5: ICBU00000932701 | C5: RCD24000759947 | D5: 澳大利亚海派-包税 | E5: 非主营 | F5: 澳大利亚海派-包税 | G5: 小旋风 | I5: 高雨晴 | J5: 77.91 | K5: 0.647 | L5: 0.8 | M5: 0.8 | N5: 0
A6: SP260122021 | B6: ICBU00000933108 | D6: 欧洲海派-M | E6: 非主营 | F6: 欧洲海派-M | G6: 张诚 | I6: 马淞浦 | J6: 43.64 | K6: 35.783 | L6: 44 | M6: 44 | N6: 0
A7: SP260129024 | B7: ICBU00000933109 | D7: 欧洲海派-M | E7: 非主营 | F7: 欧洲海派-M | G7: 张诚 | I7: 马淞浦 | J7: 235.02 | K7: 201.12 | L7: 236 | M7: 236 | N7: 0
A8: SP260121227 | B8: ICBU00000933107 | D8: 欧洲海派-M | E8: 非主营 | F8: 欧洲海派-M | G8: 张诚 | I8: 马淞浦 | J8: 76.54 | K8: 55.296 | L8: 77 | M8: 77 | N8: 0
A9: SP260123008 | B9: ICBU00000933118 | D9: 欧洲海派-M | E9: 非主营 | F9: 欧洲海派-M | G9: 张诚 | I9: 马淞浦 | J9: 182.35 | K9: 157.348 | L9: 183 | M9: 183 | N9: 0
A10: SP260122003 | B10: ICBU00000933106 | D10: 欧洲海派-M | E10: 非主营 | F10: 欧洲海派-M | G10: 张诚 | I10: 马淞浦 | J10: 131.67 | K10: 103.47 | L10: 132 | M10: 132 | N10: 0
A11: SP260121220 | B11: ICBU00000932842 | C11: KP | D11: 加拿大海派-JY | E11: 非主营 | F11: 加拿大海派-JY | G11: 风清扬 | I11: 马淞浦 | J11: 66.78 | K11: 51.207 | L11: 67 | M11: 67 | N11: 0
A12: SP260120060 | B12: ICBU00000932975 | C12: KP | D12: 加拿大海派-JY | E12: 非主营 | F12: 加拿大海派-JY | G12: 风清扬 | I12: 马淞浦 | J12: 271.26 | K12: 187.498 | L12: 272 | M12: 272 | N12: 0
A13: SP260122050 | B13: ICBU00000932908 | C13: KP | D13: 加拿大海派-JY | E13: 非主营 | F13: 加拿大海派-JY | G13: 风清扬 | I13: 马淞浦 | J13: 136.99 | K13: 98.223 | L13: 138 | M13: 137 | N13: -1
A14: SP260122007 | B14: ICBU00000933117 | D14: 欧洲海派-M | E14: 非主营 | F14: 欧洲海派-M | G14: 张诚 | I14: 马淞浦 | J14: 124.82 | K14: 115.412 | L14: 125 | M14: 125 | N14: 0
A15: SP260121264 | B15: ICBU00000933138 | D15: 欧洲海派-M | E15: 非主营 | F15: 欧洲海派-M | G15: 张诚 | I15: 马淞浦 | J15: 233.25 | K15: 177.097 | L15: 234 | M15: 234 | N15: 0
A16: SP260121188 | B16: ICBU00000932970 | C16: KP | D16: 加拿大海派-JY | E16: 非主营 | F16: 加拿大海派-JY | G16: 风清扬 | I16: 马淞浦 | J16: 36.3 | K16: 28.373 | L16: 37 | M16: 37 | N16: 0
A17: SP260121174 | B17: ICBU00000932897 | C17: KP | D17: 加拿大海派-JY | E17: 非主营 | F17: 加拿大海派-JY | G17: 风清扬 | I17: 马淞浦 | J17: 25.91 | K17: 22.747 | L17: 26 | M17: 26 | N17: 0
A18: SP260121195 | B18: ICBU00000933111 | D18: 欧洲海派-M | E18: 非主营 | F18: 欧洲海派-M | G18: 张诚 | I18: 马淞浦 | J18: 40.95 | K18: 27.728 | L18: 41 | M18: 41 | N18: 0
A19: SP260121223 | B19: ICBU00000933110 | D19: 欧洲海派-M | E19: 非主营 | F19: 欧洲海派-M | G19: 张诚 | I19: 马淞浦 | J19: 312.72 | K19: 224.327 | L19: 313 | M19: 313 | N19: 0
A20: SP260120043-YYZ7-16 | B20: ICBU00000932894 | C20: KP | D20: 加拿大海派-JY | E20: 非主营 | F20: 加拿大海派-JY | G20: 风清扬 | I20: 马淞浦 | J20: 269 | K20: 200.901 | L20: 270 | M20: 269 | N20: -1
A21: SP260126064-YYZ7-38 | B21: ICBU00000932826 | C21: KP | D21: 加拿大海派-JY | E21: 非主营 | F21: 加拿大海派-JY | G21: 风清扬 | I21: 马淞浦 | J21: 730.44 | K21: 652.894 | L21: 732 | M21: 731 | N21: -1
A22: SP260112003 | B22: ICBU00000933121 | D22: 欧洲海派-M | E22: 非主营 | F22: 欧洲海派-M | G22: 张诚 | I22: 马淞浦 | J22: 633.45 | K22: 431.198 | L22: 634 | M22: 634 | N22: 0
A23: HCLSA0131-6 | B23: ICBU00000932498 | C23: TPL000134937 | D23: 澳大利亚海派-含税-SC | E23: 非主营 | F23: 澳大利亚海派-含税-SC | G23: 小旋风 | I23: 刘申奥 | J23: 36.48 | K23: 22.308 | L23: 37 | M23: 43 | N23: 6
A24: SP260121154 | B24: ICBU00000933112 | D24: 欧洲海派-M | E24: 非主营 | F24: 欧洲海派-M | G24: 张诚 | I24: 马淞浦 | J24: 502.74 | K24: 499.672 | L24: 503 | M24: 503 | N24: 0
A25: YKZXX013102 | B25: ICBU00000932200 | C25: 1ZA06B016832064447 | D25: 欧洲德国清专线 | E25: 非主营 | F25: 欧洲德国清专线 | G25: 小旋风 | I25: 张小雪 | J25: 51.07 | K25: 41.317 | L25: 52 | M25: 52 | N25: 0
A26: TM260131-1CA3 | B26: ICBU00000932388 | C26: 888386607575 | D26: OK-FDX-DHL-TNT | E26: 非主营 | F26: OK-FDX-DHL-TNT | G26: 玉麒麟 | I26: 邓健群 | J26: 0.72 | K26: 0 | L26: 1 | M26: 1 | N26: 0
A27: TM260131-2FR2 | B27: ICBU00000932359 | C27: 1ZA06B016818572639 | D27: 欧洲德国清专线 | E27: 非主营 | F27: 欧洲德国清专线 | G27: 小旋风 | I27: 邓健群 | J27: 29.31 | K27: 20.758 | L27: 30 | M27: 30 | N27: 0
A28: HH233M26 | B28: ICBU00000932242 | C28: 1ZF4K3596816247057 | D28: 欧洲专线-HMC | E28: 非主营 | F28: 欧洲专线-HMC | G28: 帅时莹 | I28: 李娟-业务 | J28: 189.88 | K28: 186.461 | L28: 208 | M28: 208 | N28: 0
A29: RSC3104 | B29: ICBU00000933165 | C29: 1Z0E465J0413832648 | D29: OK-FDX-DHL-TNT | E29: 非主营 | F29: OK-FDX-DHL-TNT | G29: 玉麒麟 | I29: 汪祺 | J29: 9.8 | K29: 6.919 | L29: 10 | M29: 10 | N29: 0
A30: RSC3103 | B30: ICBU00000933199 | C30: 1Z0E465J0419105235 | D30: OK-FDX-DHL-TNT | E30: 非主营 | F30: OK-FDX-DHL-TNT | G30: 玉麒麟 | I30: 汪祺 | J30: 9.83 | K30: 7.88 | L30: 10 | M30: 10 | N30: 0
A31: RSC3102 | B31: ICBU00000933162 | C31: 1Z0E465J0419058000 | D31: OK-FDX-DHL-TNT | E31: 非主营 | F31: OK-FDX-DHL-TNT | G31: 玉麒麟 | I31: 汪祺 | J31: 5.31 | K31: 4.997 | L31: 5.5 | M31: 5.5 | N31: 0
A32: RSC3101 | B32: ICBU00000933159 | C32: 1Z0E465J0415072448 | D32: OK-FDX-DHL-TNT | E32: 非主营 | F32: OK-FDX-DHL-TNT | G32: 玉麒麟 | I32: 汪祺 | J32: 6.37 | K32: 4.191 | L32: 6.5 | M32: 6.5 | N32: 0
A33: QLWJ1781704 | B33: ICBU00000932639 | C33: 1Z0E793D0422717448 | D33: OK-UPS红单 | E33: 非主营 | F33: OK-UPS红单 | G33: 玉麒麟 | I33: 宁春阳 | J33: 50.38 | K33: 52.836 | L33: 52 | M33: 56 | N33: 4
A34: JHZW7312 | B34: ICBU00000931347 | C34: 888384610822 | D34: OK-FDX-DHL-TNT | E34: 非主营 | F34: OK-FDX-DHL-TNT | G34: 玉麒麟 | I34: 宋海周 | J34: 28.04 | K34: 18.262 | L34: 29 | M34: 29 | N34: 0
A35: SH0131-2 | B35: ICBU00000932684 | C35: 1ZHF38642014756797 | D35: 加拿大准时达海派UPS | E35: 非主营 | F35: 加拿大准时达海派UPS | G35: 风清扬 | I35: 小飞侠 | J35: 16.97 | K35: 22.182 | L35: 27 | M35: 23 | N35: -4
A36: JPS20260131002 | B36: ICBU00000932924 | C36: CR431657742DE | D36: HST-UPS 6000 | E36: 非主营 | F36: HST-UPS 6000 | G36: 无崖子 | I36: 柴燕玲 | J36: 7.45 | K36: 9.281 | L36: 7.5 | M36: 9.5 | N36: 2
... A49: LM-056 | B49: ICBU00000932113 | C49: 1Z0R6D926806701789 | D49: 欧洲卡航含税(快递派) | E49: 非主营 | F49: 欧洲卡航含税(快递派） | G49: 007 | I49: 张小雪 | J49: 53.99 | K49: 53.065 | L49: 55 | M49: 54 | N49: -1
A50: YKZXX0131 | B50: ICBU00000932135 | D50: 义乌联邦IE-包税 | E50: 非主营 | F50: 义乌联邦IE-包税 | G50: 无崖子 | I50: 张小雪 | J50: 48.64 | K50: 113.528 | L50: 118 | M50: 122 | N50: 4
A51: HJ25613101 | B51: ICBU00000932738 | C51: 888401830517 | D51: JRGJ-专线 | E51: 非主营 | F51: JRGJ-专线 | G51: 帅时莹 | I51: 李凤 | J51: 69.65 | K51: 72.481 | L51: 82 | M51: 73 | N51: -9
A52: 29G6T9 | B52: ICBU00000933001 | C52: CR431656565DE | D52: HST-UPS 6000 | E52: 非主营 | F52: HST-UPS 6000 | G52: 无崖子 | I52: 李可 | J52: 12.39 | K52: 9.758 | L52: 12.5 | M52: 13 | N52: 0.5
A53: UES260100104 | B53: ICBU00000933078 | C53: KP | D53: 美转加快提卡派(HEDE) | E53: 非主营 | F53: 美转加快提卡派(HEDE) | G53: 风清扬 | I53: 张小雪 | J53: 1592.96 | K53: 1176.319 | L53: 1571 | M53: 2573 | N53: 1002
A54: DS260131-90015 | B54: ICBU00000931627 | C54: 888393849785 | D54: 义乌联邦FICP-包税 | E54: 非主营 | F54: 义乌联邦FICP-包税 | G54: 无崖子 | I54: 臧明 | J54: 0.24 | K54: 0 | L54: 0.5 | M54: 0.5 | N54: 0
A55: NS0131 | B55: ICBU00000932227 | C55: 888386680111 | D55: OK-FDX-DHL-TNT | E55: 非主营 | F55: OK-FDX-DHL-TNT | G55: 玉麒麟 | I55: 付乐航 | J55: 0.1 | K55: 0 | L55: 0.5 | M55: 0.5 | N55: 0
A56: D20260131-1 | B56: ICBU00000932917 | C56: 398309170150 | D56: FEDEX速快美国包税6000 | E56: 非主营 | F56: FEDEX速快美国包税6000 | G56: 无崖子 | I56: 施建祥 | J56: 0.06 | K56: 0 | L56: 0.5 | M56: 0.5 | N56: 0
A57: MWR26131-1 | B57: ICBU00000932936 | C57: 1Z4W260E0402266135 | D57: OK-UPS红单 | E57: 非主营 | F57: OK-UPS红单 | G57: 玉麒麟 | I57: 徐建 | J57: 5.87 | K57: 7.157 | L57: 7 | M57: 7.5 | N57: 0.5
A58: YQ131CZ-1 | B58: ICBU00000932663 | C58: 1Z0R6D926809022365 | D58: 欧洲卡航含税(快递派) | E58: 非主营 | F58: 欧洲卡航含税(快递派） | G58: 007 | I58: 张俊合 | J58: 34.11 | K58: 13.86 | L58: 35 | M58: 35 | N58: 0
A59: PTYL-131T | B59: ICBU00000932552 | C59: 1Z4W260E0409162127 | D59: OK-FDX-DHL-TNT | E59: 非主营 | F59: OK-FDX-DHL-TNT | G59: 玉麒麟 | I59: 汪礼平 | J59: 3.01 | K59: 0.878 | L59: 3.5 | M59: 3.5 | N59: 0
A60: HY260131-NL-9 | B60: ICBU00000931782 | C60: 1ZF4K3596803870460 | D60: 欧洲专线-HMC | E60: 非主营 | F60: 欧洲专线-HMC | G60: 帅时莹 | I60: 朱杰 | J60: 127.81 | K60: 53.97 | L60: 131 | M60: 131 | N60: 0
A61: 5ME9963WS | B61: ICBU00000932078 | C61: 1Z0E620D0435857753 | D61: OK-FDX-DHL-TNT | E61: 非主营 | F61: OK-FDX-DHL-TNT | G61: 玉麒麟 | I61: 王岩岩 | J61: 6.27 | K61: 6.863 | L61: 7 | M61: 7 | N61: 0
A62: BSMY20260131-2 | B62: ICBU00000932971 | C62: 1Z0R6D896822740883 | D62: 欧洲快船-JT | E62: 非主营 | F62: 欧洲快船-JT | G62: 风清扬 | I62: 叶伟明 | J62: 26.29 | K62: 13.629 | L62: 39 | M62: 39 | N62: 0
... A80: TX260131-WJ17 | B80: ICBU00000932864 | C80: 1ZF4K3596809766885 | D80: 欧洲专线-HMC | E80: 非主营 | F80: 欧洲专线-HMC | G80: 帅时莹 | I80: 余雨婕 | J80: 117.59 | K80: 79.825 | L80: 131 | M80: 131 | N80: 0
A81: TB013101 | B81: ICBU00000932219 | C81: 1Z0JH5420330751666 | D81: 美国WP | E81: 非主营 | F81: 美国WP | I81: 张小雪 | J81: 1500 | K81: 480 | L81: 1500 | M81: 1500 | N81: 0
A82: FBA1973TX06Q | B82: ICBU00000932857 | C82: 1Z4W260E0411601880 | D82: OK-UPS红单 | E82: 非主营 | F82: OK-UPS红单 | G82: 玉麒麟 | I82: 李得胜 | J82: 14.98 | K82: 14.321 | L82: 15 | M82: 15 | N82: 0
A83: TX260131-LY11 | B83: ICBU00000932888 | C83: AMQ6873695 | D83: 澳大利亚空派-香港飞-SC | E83: 非主营 | F83: 澳大利亚空派-香港飞-SC | G83: 小旋风 | I83: 余雨婕 | J83: 1.42 | K83: 1.922 | L83: 2 | M83: 22 | N83: 20
A84: HCLSA0131-1 | B84: ICBU00000932298 | C84: 15504530823180 | D84: 英国海派包税（快递派） | E84: 非主营 | F84: 英国海派包税（快递派） | G84: 007 | I84: 刘申奥 | J84: 147.65 | K84: 296.148 | L84: 291 | M84: 315 | N84: 24
A85: HCLSA0131-2 | B85: ICBU00000932390 | C85: 15504530853878 | D85: 英国空派-普货-经济-含税-KY | E85: 非主营 | F85: 英国空派-普货-经济-含税-KY | G85: 风清扬 | I85: 刘申奥 | J85: 6.98 | K85: 16.555 | L85: 21 | M85: 26 | N85: 5
A86: YM2613102 | B86: ICBU00000932802 | C86: 888401809040 | D86: JRGJ-专线 | E86: 非主营 | F86: JRGJ-专线 | G86: 帅时莹 | I86: 李凤 | J86: 230.64 | K86: 146.331 | L86: 231 | M86: 231 | N86: 0
A87: 26EYEJ058 | B87: ICBU00000926830 | C87: KP | D87: 欧洲快船-JT | E87: 非主营 | F87: 欧洲快船-JT | G87: 风清扬 | I87: 周志宇 | J87: 290 | K87: 368.16 | L87: 369 | M87: 369 | N87: 0
A88: LKS-PO8302-51 | B88: ICBU00000932022 | C88: KP | D88: 加拿大海派-JY | E88: 非主营 | F88: 加拿大海派-JY | G88: 风清扬 | I88: 马淞浦 | J88: 552.4 | K88: 473.426 | L88: 553 | M88: 553 | N88: 0
A89: FL-260130A | B89: ICBU00000928728 | D89: 美国WP | E89: 非主营 | F89: 美国WP | I89: 陈炎 | J89: 2884.5 | K89: 1045.844 | L89: 2885 | M89: 2885 | N89: 0
A90: HL26131-1 | B90: ICBU00000932189 | C90: 1ZHF05572014691146 | D90: 加拿大空派-大陆飞-UPS派送/6000 | E90: 非主营 | F90: 加拿大空派-大陆飞-UPS派送/6000 | G90: 风清扬 | I90: 丁佳伟 | J90: 17.27 | K90: 21.28 | L90: 21 | M90: 22 | N90: 1
A91: GB0131-DE | B91: ICBU00000931328 | C91: 888382928543 | D91: 上海FEDEX-P价IP | E91: 非主营 | F91: 上海FEDEX-P价IP | G91: 无崖子 | I91: 陈颖 | J91: 0.95 | K91: 1.253 | L91: 1.5 | M91: 1.5 | N91: 0
A92: FBA15LDBQTGT | B92: ICBU00000930712 | C92: 1Z0R6D926808645944 | D92: 欧洲卡航含税(快递派) | E92: 非主营 | F92: 欧洲卡航含税(快递派） | G92: 007 | I92: 小飞侠 | J92: 45.13 | K92: 60.31 | L92: 57 | M92: 61 | N92: 4
A93: GB0131-US01 | B93: ICBU00000931243 | C93: 398309225951 | D93: FEDEX速快美国包税6000 | E93: 非主营 | F93: FEDEX速快美国包税6000 | G93: 无崖子 | I93: 陈颖 | J93: 2.54 | K93: 2.028 | L93: 3 | M93: 3 | N93: 0
A94: WLXB-3GB-1 | B94: ICBU00000929599 | C94: 888384608580 | D94: OK-FDX-DHL-TNT | E94: 非主营 | F94: OK-FDX-DHL-TNT | G94: 玉麒麟 | I94: 邓健群 | J94: 59.33 | K94: 69.886 | L94: 70 | M94: 70 | N94: 0
A95: WLXB-3GB-2 | B95: ICBU00000929600 | C95: 888386159189 | D95: OK-FDX-DHL-TNT | E95: 非主营 | F95: OK-FDX-DHL-TNT | G95: 玉麒麟 | I95: 邓健群 | J95: 59.39 | K95: 68.156 | L95: 69 | M95: 69 | N95: 0
A96: CH20260131-1 | B96: ICBU00000932648 | C96: KP | D96: 英国卡航-卡派-含税-KY | E96: 非主营 | F96: 英国卡航-卡派-含税-KY | G96: 风清扬 | I96: 张德士 | J96: 214.5 | K96: 427.862 | L96: 423 | M96: 428 | N96: 5
A97: JYZ26013101 | B97: ICBU00000931973 | C97: 1ZX30Y730490393478 | D97: 义乌UPS红单直发包税/5000 | E97: 非主营 | F97: 义乌UPS红单直发包税/5000 | G97: 无崖子 | I97: 张小雪 | J97: 60.56 | K97: 19.618 | L97: 62 | M97: 64 | N97: 2
A98: JYZ26013102 | B98: ICBU00000931978 | C98: 1ZX30Y730498888581 | D98: 义乌UPS红单直发包税/5000 | E98: 非主营 | F98: 义乌UPS红单直发包税/5000 | G98: 无崖子 | I98: 张小雪 | J98: 54.28 | K98: 16.499 | L98: 55 | M98: 55 | N98: 0
A99: JLL260131A | B99: ICBU00000932055 | C99: MKP4534281830 | D99: 澳大利亚空派-大陆飞-SC | E99: 非主营 | F99: 澳大利亚空派-大陆飞-SC | G99: 小旋风 | I99: 陈炎 | J99: 428.48 | K99: 436.599 | L99: 429.5 | M99: 437 | N99: 7.5
A100: JLL260131B | B100: ICBU00000932080 | C100: TPL600032612 | D100: 澳大利亚空派-大陆飞-SC | E100: 非主营 | F100: 澳大利亚空派-大陆飞-SC | G100: 小旋风 | I100: 陈炎 | J100: 27.41 | K100: 30.288 | L100: 30 | M100: 31 | N100: 1
A101: JLL260131C | B101: ICBU00000932083 | C101: 888385218542 | D101: OK-FDX-DHL-TNT | E101: 非主营 | F101: OK-FDX-DHL-TNT | G101: 玉麒麟 | I101: 陈炎 | J101: 9.14 | K101: 11.88 | L101: 12 | M101: 12 | N101: 0
... A113: ZJTX2025803 | B113: ICBU00000930190 | C113: 888386075311 | D113: OK-FDX-DHL-TNT | E113: 非主营 | F113: OK-FDX-DHL-TNT | G113: 玉麒麟 | I113: 陈玉琴 | J113: 0.45 | K113: 0 | L113: 0.5 | M113: 0.5 | N113: 0
A114: CZQ260130 | B114: ICBU00000932382 | D114: OK-FDX-DHL-TNT | E114: 非主营 | F114: OK-FDX-DHL-TNT | G114: 玉麒麟 | I114: 蒋龙波 | J114: 0.08 | K114: 0 | L114: 0.5 | M114: 0.5 | N114: 0
A115: FREDA707102 | B115: ICBU00000932392 | C115: 1Z0R6D926803614290 | D115: 欧洲海派含税(快递派) | E115: 非主营 | F115: 欧洲海派含税(快递派） | G115: 007 | I115: 高雨晴 | J115: 22.21 | K115: 26.216 | L115: 26 | M115: 27 | N115: 1
A116: LUNA9305523 | B116: ICBU00000931320 | C116: 1Z0R6D896806053549 | D116: 欧洲快船-JT | E116: 非主营 | F116: 欧洲快船-JT | G116: 风清扬 | I116: 何林霞 | J116: 286.04 | K116: 287.696 | L116: 326 | M116: 326 | N116: 0
A117: RF-1147 | B117: ICBU00000929704 | C117: 1Z0R6D926839601567 | D117: 欧洲海派含税(快递派) | E117: 非主营 | F117: 欧洲海派含税(快递派） | G117: 007 | I117: 王拥 | J117: 2989.26 | K117: 3497.429 | L117: 3374 | M117: 3498 | N117: 124
A118: FG260108020 | B118: ICBU00000931596 | C118: AMQ6873655 | D118: 澳大利亚空派-经济线-SC | E118: 非主营 | F118: 澳大利亚空派-经济线-SC | G118: 小旋风 | I118: 李凤 | J118: 21.65 | K118: 16.246 | L118: 22 | M118: 22 | N118: 0
A119: RC261302 | B119: ICBU00000932130 | C119: SA780165875 | D119: 阿联酋专线-YT | E119: 非主营 | F119: 阿联酋专线-YT | G119: 帅时莹 | I119: 李凤 | J119: 59.99 | K119: 32.905 | L119: 60 | M119: 60 | N119: 0
A120: SQ260108002 | B120: ICBU00000931902 | C120: 500745742652 | D120: OK-UPS蓝单 | E120: 非主营 | F120: OK-UPS蓝单 | G120: 玉麒麟 | I120: 李凤 | J120: 93.76 | K120: 99.404 | L120: 96 | M120: 102 | N120: 6
A121: FL-2601310E | B121: ICBU00000932337 | D121: 美国WP | E121: 非主营 | F121: 美国WP | I121: 陈炎 | J121: 3700.78 | K121: 2441.763 | L121: 3701 | M121: 3701 | N121: 0
A122: HS457-77 | B122: ICBU00000932148 | C122: SA-WJ24626 | D122: 沙特海派 | E122: 非主营 | F122: 沙特海派 | G122: 小旋风 | I122: 左宗伟 | J122: 385.7 | K122: 430.317 | L122: 431 | M122: 431 | N122: 0
A123: RF-7704 | B123: ICBU00000932373 | C123: 1Z0R6D926832267101 | D123: 欧洲海派含税(快递派) | E123: 非主营 | F123: 欧洲海派含税(快递派） | G123: 007 | I123: 王拥 | J123: 849.57 | K123: 251.497 | L123: 865 | M123: 857 | N123: -8
A124: YINHAI2544 | B124: ICBU00000932088 | C124: MY4751 | D124: 沙特空派 | E124: 非主营 | F124: 沙特空派 | G124: 小旋风 | I124: 左宗伟 | J124: 142.72 | K124: 159.809 | L124: 150 | M124: 160 | N124: 10
A125: LR260130 | B125: ICBU00000930956 | C125: MKP24000759952 | D125: 私人地址海派双清含税（AU-S-02） | E125: 非主营 | F125: 私人地址海派双清含税（AU-S-02） | G125: 小旋风 | I125: 孙源圻 | J125: 851.34 | K125: 1312.709 | L125: 1313 | M125: 1313 | N125: 0
A126: FCO0018 | B126: ICBU00000931738 | C126: 398309492050 | D126: YF-联邦包税小包 | E126: 非主营 | F126: YF-联邦包税小包 | G126: 帅时莹 | I126: 李可 | J126: 0.76 | K126: 0 | L126: 1 | M126: 1 | N126: 0
A127: LEKE29318 | B127: ICBU00000932197 | C127: 398310485636 | D127: OK-FDX-DHL-TNT | E127: 非主营 | F127: OK-FDX-DHL-TNT | G127: 玉麒麟 | I127: 宋海周 | J127: 0.55 | K127: 0.95 | L127: 1 | M127: 1 | N127: 0
A128: BLS01307200 | B128: ICBU00000932157 | C128: 1Z80F20X0423193076 | D128: FedEx-通用渠道 | E128: 非主营 | F128: FedEx-通用渠道 | G128: 无崖子 | I128: 高雨晴 | J128: 0.79 | K128: 0.867 | L128: 1 | M128: 1.5 | N128: 0.5
A129: SHANELGORIAL26131-1 | B129: ICBU00000931993 | C129: 1Z0E620D0405399626 | D129: OK-FDX-DHL-TNT | E129: 非主营 | F129: OK-FDX-DHL-TNT | G129: 玉麒麟 | I129: 丁佳伟 | J129: 0.41 | K129: 0.739 | L129: 1 | M129: 1 | N129: 0
A130: FBA19751BCG3 | B130: ICBU00000932097 | C130: KP | D130: 加拿大海派-JY | E130: 非主营 | F130: 加拿大海派-JY | G130: 风清扬 | I130: 陈兵 | J130: 307.31 | K130: 265.858 | L130: 308 | M130: 308 | N130: 0
A131: CN260131-US-46806 | B131: ICBU00000931286 | C131: 398309523280 | D131: YF-联邦包税小包 | E131: 非主营 | F131: YF-联邦包税小包 | G131: 帅时莹 | I131: 朱杰 | J131: 1.98 | K131: 2.567 | L131: 2.5 | M131: 3 | N131: 0.5
A132: CN260131-US-52552 | B132: ICBU00000931289 | C132: 398309602860 | D132: YF-联邦包税小包 | E132: 非主营 | F132: YF-联邦包税小包 | G132: 帅时莹 | I132: 朱杰 | J132: 1.83 | K132: 2.567 | L132: 2.5 | M132: 3 | N132: 0.5
A133: CN260131-US-33778 | B133: ICBU00000931285 | C133: 398309593703 | D133: YF-联邦包税小包 | E133: 非主营 | F133: YF-联邦包税小包 | G133: 帅时莹 | I133: 朱杰 | J133: 2.5 | K133: 2.678 | L133: 3 | M133: 3 | N133: 0
... A154: JT0131-1 | B154: ICBU00000932046 | C154: 1Z0E793D6704433474 | D154: MSHQ-UPS | E154: 非主营 | F154: MSHQ-UPS | G154: 帅时莹 | I154: 王涛 | J154: 5.07 | K154: 11.178 | L154: 10 | M154: 12 | N154: 2
A155: YKZXX013101 | B155: ICBU00000931779 | D155: 义乌联邦IE-包税 | E155: 非主营 | F155: 义乌联邦IE-包税 | G155: 无崖子 | I155: 张小雪 | J155: 51.35 | K155: 55.493 | L155: 56 | M155: 56 | N155: 0
A156: HZHF0037 | B156: ICBU00000925854 | C156: 1ZHF34022038229695 | D156: 加拿大海派-JY | E156: 非主营 | F156: 加拿大海派-JY | G156: 风清扬 | I156: 叶伟明 | J156: 71.14 | K156: 58.448 | L156: 72 | M156: 72 | N156: 0
A157: CX-128879 | B157: ICBU00000931980 | C157: 1Z33W2600493890928 | D157: OK-FDX-DHL-TNT | E157: 非主营 | F157: OK-FDX-DHL-TNT | G157: 玉麒麟 | I157: 江伟成 | J157: 2.99 | K157: 3.584 | L157: 3.5 | M157: 4.5 | N157: 1
A158: 260130GT-LISA3 | B158: ICBU00000928563 | C158: 15504530331795 | D158: 英国空运普货DPD派 | E158: 非主营 | F158: 英国空运普货DPD派 | G158: 小旋风 | I158: 黄小丽 | J158: 18.16 | K158: 48.195 | L158: 33 | M158: 66 | N158: 33
A159: QY26-0131ER01 | B159: ICBU00000931932 | C159: 500745745216 | D159: OK-UPS蓝单 | E159: 非主营 | F159: OK-UPS蓝单 | G159: 玉麒麟 | I159: 王志军 | J159: 15.25 | K159: 13.874 | L159: 15.5 | M159: 16 | N159: 0.5
A160: AQ26131-2 | B160: ICBU00000931871 | C160: 1ZX30Y730491475360 | D160: 义乌UPS红单直发包税/6000 | E160: 非主营 | F160: 义乌UPS红单直发包税/6000 | G160: 无崖子 | I160: 丁佳伟 | J160: 22.05 | K160: 24.798 | L160: 30 | M160: 26 | N160: -4
...

Sheet 业务数据统计
A1: 期间 | B1: 渠道客服 | C1: 渠道 | D1: 出货计费重 | E1: 业务占用提成金额 | F1: 是否计算提成 | G1: 客户单号 | H1: 服务商单号 | I1: 渠道转单号 | J1: 销售产品 | K1: 应收运费单价 | L1: 产品组 | M1: 结算员 | N1: 目的国家 | O1: 邮编 | P1: FBA仓库代码 | Q1: 客户 | R1: 客户类型 | S1: 业务员 | T1: 业务员部门 | U1: 前线客服 | V1: 申报总价值 | W1: 货物类型 | X1: 操作状态 | Y1: 中转状态 | Z1: 退件状态 | AA1: 件数 | AB1: 收货实重 | AC1: 收货计费重 | AD1: 收货比重 | AE1: 服务商计费重 | AF1: 应收 | AG1: 实收 | AH1: 应收单价 | AI1: 应付 | AJ1: 实付 | AK1: 毛利 | AL1: 业务员成本 | AM1: 业务员成本单价 | AN1: 业务员毛利 | AO1: 产品部毛利 | AP1: 核销时间 | AQ1: 应收是否锁定 | AR1: 应付是否锁定 | AS1: 结算服务商 | AT1: 业务服务商 | AU1: 服务渠道 | AV1: 收货机构 | AW1: 到货时间 | AX1: 到货总单 | AY1: 出货时间 | AZ1: 出货总单 | BA1: 附加服务 | BB1: 航空主单号 | BC1: 中文品名 | BD1: 自定义备注
A2: =MID(AW2,1,7) -> 2026-01 | B2: =_xlfn.XLOOKUP(G2,过机服务商重量差!A:A,过机服务商重量差!G:G) -> 玉麒麟 | C2: =IF(OR(AO2<0,L2="FBA海运"),"","渠道") -> 渠道 | D2: =ROUND(IF(AND(AO2>=0,Y2="正常走货"),_xlfn.XLOOKUP(G2,过机服务商重量差!A:A,过机服务商重量差!L:L),"0"),2) -> 3.5 | E2: =ROUND(IF(B2="吴敏洁(小旋风)",$D2/提成!$D$4*提成!$E$4,$D2/提成!$D$3*提成!$E$3),2) -> 0.04 | F2: {=IFERROR(LOOKUP(1,0/((B2=名单!B:B)*(VALUE(AW2)>=名单!E:E)*(VALUE(AW2)<=名单!G:G)*(Y2="正常走货")),名单!H:H),"否")} -> 否 | G2: QS0131-MX | H2: 1ZG3325W0416448603 | J2: OK-FDX-DHL-TNT | L2: 非主营 | S2: 小飞侠 | T2: 营销五部 | Y2: 正常走货 | AO2: 118.16 | AW2: 2026-01-31 22:46:57
A3: =MID(AW3,1,7) -> 2026-01 | B3: =_xlfn.XLOOKUP(G3,过机服务商重量差!A:A,过机服务商重量差!G:G) -> 玉麒麟 | C3: =IF(OR(AO3<0,L3="FBA海运"),"","渠道") -> 渠道 | D3: =ROUND(IF(AND(AO3>=0,Y3="正常走货"),_xlfn.XLOOKUP(G3,过机服务商重量差!A:A,过机服务商重量差!L:L),"0"),2) -> 9.5 | E3: =ROUND(IF(B3="小旋风",$D3/提成!$D$4*提成!$E$4,$D3/提成!$D$3*提成!$E$3),2) -> 0.1 | F3: =IFERROR(LOOKUP(1,0/((B3=名单!B:B)*(VALUE(AW3)>=名单!E:E)*(VALUE(AW3)<=名单!G:G)*(Y3="正常走货")),名单!H:H),"否") -> 否 | G3: TL0131-NL | H3: 1Z4W260E0409673969 | J3: OK-UPS红单 | L3: 非主营 | S3: 小飞侠 | T3: 营销五部 | Y3: 正常走货 | AO3: 132.4 | AW3: 2026-01-31 22:46:36
A4: =MID(AW4,1,7) -> 2026-01 | B4: =_xlfn.XLOOKUP(G4,过机服务商重量差!A:A,过机服务商重量差!G:G) -> 小旋风 | C4: =IF(OR(AO4<0,L4="FBA海运"),"","渠道") -> 渠道 | D4: =ROUND(IF(AND(AO4>=0,Y4="正常走货"),_xlfn.XLOOKUP(G4,过机服务商重量差!A:A,过机服务商重量差!L:L),"0"),2) -> 0.7 | E4: =ROUND(IF(B4="小旋风",$D4/提成!$D$4*提成!$E$4,$D4/提成!$D$3*提成!$E$3),2) -> 0.01 | F4: =IFERROR(LOOKUP(1,0/((B4=名单!B:B)*(VALUE(AW4)>=名单!E:E)*(VALUE(AW4)<=名单!G:G)*(Y4="正常走货")),名单!H:H),"否") -> 是 | G4: FBA15G65R8GW | H4: RCD24000759946 | J4: 澳大利亚海派-包税 | L4: 非主营 | S4: 高雨晴 | T4: 营销二部 | Y4: 正常走货 | AO4: 420 | AW4: 2026-01-31 22:45:45
A5: =MID(AW5,1,7) -> 2026-01 | B5: =_xlfn.XLOOKUP(G5,过机服务商重量差!A:A,过机服务商重量差!G:G) -> 小旋风 | C5: =IF(OR(AO5<0,L5="FBA海运"),"","渠道") -> 渠道 | D5: =ROUND(IF(AND(AO5>=0,Y5="正常走货"),_xlfn.XLOOKUP(G5,过机服务商重量差!A:A,过机服务商重量差!L:L),"0"),2) -> 0.8 | E5: =ROUND(IF(B5="小旋风",$D5/提成!$D$4*提成!$E$4,$D5/提成!$D$3*提成!$E$3),2) -> 0.01 | F5: =IFERROR(LOOKUP(1,0/((B5=名单!B:B)*(VALUE(AW5)>=名单!E:E)*(VALUE(AW5)<=名单!G:G)*(Y5="正常走货")),名单!H:H),"否") -> 是 | G5: FBA15G65P13K | H5: RCD24000759947 | J5: 澳大利亚海派-包税 | L5: 非主营 | S5: 高雨晴 | T5: 营销二部 | Y5: 正常走货 | AO5: 800 | AW5: 2026-01-31 22:45:28
A6: =MID(AW6,1,7) -> 2026-01 | B6: =_xlfn.XLOOKUP(G6,过机服务商重量差!A:A,过机服务商重量差!G:G) -> 张诚 | C6: =IF(OR(AO6<0,L6="FBA海运"),"","渠道") -> 渠道 | D6: =ROUND(IF(AND(AO6>=0,Y6="正常走货"),_xlfn.XLOOKUP(G6,过机服务商重量差!A:A,过机服务商重量差!L:L),"0"),2) -> 44 | E6: =ROUND(IF(B6="小旋风",$D6/提成!$D$4*提成!$E$4,$D6/提成!$D$3*提成!$E$3),2) -> 0.44 | F6: =IFERROR(LOOKUP(1,0/((B6=名单!B:B)*(VALUE(AW6)>=名单!E:E)*(VALUE(AW6)<=名单!G:G)*(Y6="正常走货")),名单!H:H),"否") -> 否 | G6: SP260122021 | J6: 欧洲海卡包税-MM | L6: 非主营 | S6: 马淞浦 | T6: 营销一部 | Y6: 正常走货 | AO6: 400 | AW6: 2026-01-31 22:43:03
A7: =MID(AW7,1,7) -> 2026-01 | B7: =_xlfn.XLOOKUP(G7,过机服务商重量差!A:A,过机服务商重量差!G:G) -> 张诚 | C7: =IF(OR(AO7<0,L7="FBA海运"),"","渠道") -> 渠道 | D7: =ROUND(IF(AND(AO7>=0,Y7="正常走货"),_xlfn.XLOOKUP(G7,过机服务商重量差!A:A,过机服务商重量差!L:L),"0"),2) -> 236 | E7: =ROUND(IF(B7="小旋风",$D7/提成!$D$4*提成!$E$4,$D7/提成!$D$3*提成!$E$3),2) -> 2.36 | F7: =IFERROR(LOOKUP(1,0/((B7=名单!B:B)*(VALUE(AW7)>=名单!E:E)*(VALUE(AW7)<=名单!G:G)*(Y7="正常走货")),名单!H:H),"否") -> 否 | G7: SP260129024 | J7: 欧洲海卡包税-MM | L7: 非主营 | S7: 马淞浦 | T7: 营销一部 | Y7: 正常走货 | AO7: 2832 | AW7: 2026-01-31 22:42:39
A8: =MID(AW8,1,7) -> 2026-01 | B8: =_xlfn.XLOOKUP(G8,过机服务商重量差!A:A,过机服务商重量差!G:G) -> 张诚 | C8: =IF(OR(AO8<0,L8="FBA海运"),"","渠道") -> 渠道 | D8: =ROUND(IF(AND(AO8>=0,Y8="正常走货"),_xlfn.XLOOKUP(G8,过机服务商重量差!A:A,过机服务商重量差!L:L),"0"),2) -> 77 | E8: =ROUND(IF(B8="小旋风",$D8/提成!$D$4*提成!$E$4,$D8/提成!$D$3*提成!$E$3),2) -> 0.77 | F8: =IFERROR(LOOKUP(1,0/((B8=名单!B:B)*(VALUE(AW8)>=名单!E:E)*(VALUE(AW8)<=名单!G:G)*(Y8="正常走货")),名单!H:H),"否") -> 否 | G8: SP260121227 | J8: 欧洲海卡包税-MM | L8: 非主营 | S8: 马淞浦 | T8: 营销一部 | Y8: 正常走货 | AO8: 924 | AW8: 2026-01-31 22:42:32
A9: =MID(AW9,1,7) -> 2026-01 | B9: =_xlfn.XLOOKUP(G9,过机服务商重量差!A:A,过机服务商重量差!G:G) -> 张诚 | C9: =IF(OR(AO9<0,L9="FBA海运"),"","渠道") -> 渠道 | D9: =ROUND(IF(AND(AO9>=0,Y9="正常走货"),_xlfn.XLOOKUP(G9,过机服务商重量差!A:A,过机服务商重量差!L:L),"0"),2) -> 183 | E9: =ROUND(IF(B9="小旋风",$D9/提成!$D$4*提成!$E$4,$D9/提成!$D$3*提成!$E$3),2) -> 1.83 | F9: =IFERROR(LOOKUP(1,0/((B9=名单!B:B)*(VALUE(AW9)>=名单!E:E)*(VALUE(AW9)<=名单!G:G)*(Y9="正常走货")),名单!H:H),"否") -> 否 | G9: SP260123008 | J9: 欧洲海卡包税-MM | L9: 非主营 | S9: 马淞浦 | T9: 营销一部 | Y9: 正常走货 | AO9: 2196 | AW9: 2026-01-31 22:40:53
A10: =MID(AW10,1,7) -> 2026-01 | B10: =_xlfn.XLOOKUP(G10,过机服务商重量差!A:A,过机服务商重量差!G:G) -> 张诚 | C10: =IF(OR(AO10<0,L10="FBA海运"),"","渠道") -> 渠道 | D10: =ROUND(IF(AND(AO10>=0,Y10="正常走货"),_xlfn.XLOOKUP(G10,过机服务商重量差!A:A,过机服务商重量差!L:L),"0"),2) -> 132 | E10: =ROUND(IF(B10="小旋风",$D10/提成!$D$4*提成!$E$4,$D10/提成!$D$3*提成!$E$3),2) -> 1.32 | F10: =IFERROR(LOOKUP(1,0/((B10=名单!B:B)*(VALUE(AW10)>=名单!E:E)*(VALUE(AW10)<=名单!G:G)*(Y10="正常走货")),名单!H:H),"否") -> 否 | G10: SP260122003 | J10: 欧洲海卡包税-MM | L10: 非主营 | S10: 马淞浦 | T10: 营销一部 | Y10: 正常走货 | AO10: 1584 | AW10: 2026-01-31 22:39:00
A11: =MID(AW11,1,7) -> 2026-01 | B11: =_xlfn.XLOOKUP(G11,过机服务商重量差!A:A,过机服务商重量差!G:G) -> 风清扬 | C11: =IF(OR(AO11<0,L11="FBA海运"),"","渠道") | D11: =ROUND(IF(AND(AO11>=0,Y11="正常走货"),_xlfn.XLOOKUP(G11,过机服务商重量差!A:A,过机服务商重量差!L:L),"0"),2) -> 0 | E11: =ROUND(IF(B11="小旋风",$D11/提成!$D$4*提成!$E$4,$D11/提成!$D$3*提成!$E$3),2) -> 0 | F11: =IFERROR(LOOKUP(1,0/((B11=名单!B:B)*(VALUE(AW11)>=名单!E:E)*(VALUE(AW11)<=名单!G:G)*(Y11="正常走货")),名单!H:H),"否") -> 是 | G11: SP260121220 | H11: KP | J11: 加拿大海派-JY | L11: 非主营 | S11: 马淞浦 | T11: 营销一部 | Y11: 正常走货 | AO11: -99.5 | AW11: 2026-01-31 22:37:31
A12: =MID(AW12,1,7) -> 2026-01 | B12: =_xlfn.XLOOKUP(G12,过机服务商重量差!A:A,过机服务商重量差!G:G) -> 风清扬 | C12: =IF(OR(AO12<0,L12="FBA海运"),"","渠道") -> 渠道 | D12: =ROUND(IF(AND(AO12>=0,Y12="正常走货"),_xlfn.XLOOKUP(G12,过机服务商重量差!A:A,过机服务商重量差!L:L),"0"),2) -> 272 | E12: =ROUND(IF(B12="小旋风",$D12/提成!$D$4*提成!$E$4,$D12/提成!$D$3*提成!$E$3),2) -> 2.72 | F12: =IFERROR(LOOKUP(1,0/((B12=名单!B:B)*(VALUE(AW12)>=名单!E:E)*(VALUE(AW12)<=名单!G:G)*(Y12="正常走货")),名单!H:H),"否") -> 是 | G12: SP260120060 | H12: KP | J12: 加拿大海派-JY | L12: 非主营 | S12: 马淞浦 | T12: 营销一部 | Y12: 正常走货 | AO12: 126.4 | AW12: 2026-01-31 22:37:02
A13: =MID(AW13,1,7) -> 2026-01 | B13: =_xlfn.XLOOKUP(G13,过机服务商重量差!A:A,过机服务商重量差!G:G) -> 风清扬 | C13: =IF(OR(AO13<0,L13="FBA海运"),"","渠道") -> 渠道 | D13: =ROUND(IF(AND(AO13>=0,Y13="正常走货"),_xlfn.XLOOKUP(G13,过机服务商重量差!A:A,过机服务商重量差!L:L),"0"),2) -> 138 | E13: =ROUND(IF(B13="小旋风",$D13/提成!$D$4*提成!$E$4,$D13/提成!$D$3*提成!$E$3),2) -> 1.38 | F13: =IFERROR(LOOKUP(1,0/((B13=名单!B:B)*(VALUE(AW13)>=名单!E:E)*(VALUE(AW13)<=名单!G:G)*(Y13="正常走货")),名单!H:H),"否") -> 是 | G13: SP260122050 | H13: KP | J13: 加拿大海派-JY | L13: 非主营 | S13: 马淞浦 | T13: 营销一部 | Y13: 正常走货 | AO13: 139.3 | AW13: 2026-01-31 22:36:32
A14: =MID(AW14,1,7) -> 2026-01 | B14: =_xlfn.XLOOKUP(G14,过机服务商重量差!A:A,过机服务商重量差!G:G) -> 张诚 | C14: =IF(OR(AO14<0,L14="FBA海运"),"","渠道") -> 渠道 | D14: =ROUND(IF(AND(AO14>=0,Y14="正常走货"),_xlfn.XLOOKUP(G14,过机服务商重量差!A:A,过机服务商重量差!L:L),"0"),2) -> 125 | E14: =ROUND(IF(B14="小旋风",$D14/提成!$D$4*提成!$E$4,$D14/提成!$D$3*提成!$E$3),2) -> 1.25 | F14: =IFERROR(LOOKUP(1,0/((B14=名单!B:B)*(VALUE(AW14)>=名单!E:E)*(VALUE(AW14)<=名单!G:G)*(Y14="正常走货")),名单!H:H),"否") -> 否 | G14: SP260122007 | J14: 欧洲海卡包税-MM | L14: 非主营 | S14: 马淞浦 | T14: 营销一部 | Y14: 正常走货 | AO14: 1562.5 | AW14: 2026-01-31 22:31:06
A15: =MID(AW15,1,7) -> 2026-01 | B15: =_xlfn.XLOOKUP(G15,过机服务商重量差!A:A,过机服务商重量差!G:G) -> 张诚 | C15: =IF(OR(AO15<0,L15="FBA海运"),"","渠道") -> 渠道 | D15: =ROUND(IF(AND(AO15>=0,Y15="正常走货"),_xlfn.XLOOKUP(G15,过机服务商重量差!A:A,过机服务商重量差!L:L),"0"),2) -> 234 | E15: =ROUND(IF(B15="小旋风",$D15/提成!$D$4*提成!$E$4,$D15/提成!$D$3*提成!$E$3),2) -> 2.34 | F15: {=IFERROR(LOOKUP(1,0/((B15=名单!B:B)*(VALUE(AW15)>=名单!E:E)*(VALUE(AW15)<=名单!G:G)*(Y15="正常走货")),名单!H:H),"否")} -> 否 | G15: SP260121264 | J15: 欧洲海卡包税-MM | L15: 非主营 | S15: 马淞浦 | T15: 营销一部 | Y15: 正常走货 | AO15: 2925 | AW15: 2026-01-31 22:26:23
A16: =MID(AW16,1,7) -> 2026-01 | B16: =_xlfn.XLOOKUP(G16,过机服务商重量差!A:A,过机服务商重量差!G:G) -> 风清扬 | C16: =IF(OR(AO16<0,L16="FBA海运"),"","渠道") -> 渠道 | D16: =ROUND(IF(AND(AO16>=0,Y16="正常走货"),_xlfn.XLOOKUP(G16,过机服务商重量差!A:A,过机服务商重量差!L:L),"0"),2) -> 37 | E16: =ROUND(IF(B16="小旋风",$D16/提成!$D$4*提成!$E$4,$D16/提成!$D$3*提成!$E$3),2) -> 0.37 | F16: =IFERROR(LOOKUP(1,0/((B16=名单!B:B)*(VALUE(AW16)>=名单!E:E)*(VALUE(AW16)<=名单!G:G)*(Y16="正常走货")),名单!H:H),"否") -> 是 | G16: SP260121188 | H16: KP | J16: 加拿大海派-JY | L16: 非主营 | S16: 马淞浦 | T16: 营销一部 | Y16: 正常走货 | AO16: 29.9 | AW16: 2026-01-31 22:24:58
A17: =MID(AW17,1,7) -> 2026-01 | B17: =_xlfn.XLOOKUP(G17,过机服务商重量差!A:A,过机服务商重量差!G:G) -> 风清扬 | C17: =IF(OR(AO17<0,L17="FBA海运"),"","渠道") -> 渠道 | D17: =ROUND(IF(AND(AO17>=0,Y17="正常走货"),_xlfn.XLOOKUP(G17,过机服务商重量差!A:A,过机服务商重量差!L:L),"0"),2) -> 26 | E17: =ROUND(IF(B17="小旋风",$D17/提成!$D$4*提成!$E$4,$D17/提成!$D$3*提成!$E$3),2) -> 0.26 | F17: =IFERROR(LOOKUP(1,0/((B17=名单!B:B)*(VALUE(AW17)>=名单!E:E)*(VALUE(AW17)<=名单!G:G)*(Y17="正常走货")),名单!H:H),"否") -> 是 | G17: SP260121174 | H17: KP | J17: 加拿大海派-JY | L17: 非主营 | S17: 马淞浦 | T17: 营销一部 | Y17: 正常走货 | AO17: 173.4 | AW17: 2026-01-31 22:24:21
A18: =MID(AW18,1,7) -> 2026-01 | B18: =_xlfn.XLOOKUP(G18,过机服务商重量差!A:A,过机服务商重量差!G:G) -> 张诚 | C18: =IF(OR(AO18<0,L18="FBA海运"),"","渠道") -> 渠道 | D18: =ROUND(IF(AND(AO18>=0,Y18="正常走货"),_xlfn.XLOOKUP(G18,过机服务商重量差!A:A,过机服务商重量差!L:L),"0"),2) -> 41 | E18: =ROUND(IF(B18="小旋风",$D18/提成!$D$4*提成!$E$4,$D18/提成!$D$3*提成!$E$3),2) -> 0.41 | F18: =IFERROR(LOOKUP(1,0/((B18=名单!B:B)*(VALUE(AW18)>=名单!E:E)*(VALUE(AW18)<=名单!G:G)*(Y18="正常走货")),名单!H:H),"否") -> 否 | G18: SP260121195 | J18: 欧洲海卡包税-MM | L18: 非主营 | S18: 马淞浦 | T18: 营销一部 | Y18: 正常走货 | AO18: 594 | AW18: 2026-01-31 22:24:04
A19: =MID(AW19,1,7) -> 2026-01 | B19: =_xlfn.XLOOKUP(G19,过机服务商重量差!A:A,过机服务商重量差!G:G) -> 张诚 | C19: =IF(OR(AO19<0,L19="FBA海运"),"","渠道") -> 渠道 | D19: =ROUND(IF(AND(AO19>=0,Y19="正常走货"),_xlfn.XLOOKUP(G19,过机服务商重量差!A:A,过机服务商重量差!L:L),"0"),2) -> 313 | E19: =ROUND(IF(B19="小旋风",$D19/提成!$D$4*提成!$E$4,$D19/提成!$D$3*提成!$E$3),2) -> 3.13 | F19: =IFERROR(LOOKUP(1,0/((B19=名单!B:B)*(VALUE(AW19)>=名单!E:E)*(VALUE(AW19)<=名单!G:G)*(Y19="正常走货")),名单!H:H),"否") -> 否 | G19: SP260121223 | J19: 欧洲海卡包税-MM | L19: 非主营 | S19: 马淞浦 | T19: 营销一部 | Y19: 正常走货 | AO19: 4225.5 | AW19: 2026-01-31 22:20:47
A20: =MID(AW20,1,7) -> 2026-01 | B20: =_xlfn.XLOOKUP(G20,过机服务商重量差!A:A,过机服务商重量差!G:G) -> 风清扬 | C20: =IF(OR(AO20<0,L20="FBA海运"),"","渠道") | D20: =ROUND(IF(AND(AO20>=0,Y20="正常走货"),_xlfn.XLOOKUP(G20,过机服务商重量差!A:A,过机服务商重量差!L:L),"0"),2) -> 0 | E20: =ROUND(IF(B20="小旋风",$D20/提成!$D$4*提成!$E$4,$D20/提成!$D$3*提成!$E$3),2) -> 0 | F20: =IFERROR(LOOKUP(1,0/((B20=名单!B:B)*(VALUE(AW20)>=名单!E:E)*(VALUE(AW20)<=名单!G:G)*(Y20="正常走货")),名单!H:H),"否") -> 是 | G20: SP260120043-YYZ7-16 | H20: KP | J20: 加拿大海派-JY | L20: 非主营 | S20: 马淞浦 | T20: 营销一部 | Y20: 正常走货 | AO20: -1287.4 | AW20: 2026-01-31 22:18:11
A21: =MID(AW21,1,7) -> 2026-01 | B21: =_xlfn.XLOOKUP(G21,过机服务商重量差!A:A,过机服务商重量差!G:G) -> 风清扬 | C21: =IF(OR(AO21<0,L21="FBA海运"),"","渠道") | D21: =ROUND(IF(AND(AO21>=0,Y21="正常走货"),_xlfn.XLOOKUP(G21,过机服务商重量差!A:A,过机服务商重量差!L:L),"0"),2) -> 0 | E21: =ROUND(IF(B21="小旋风",$D21/提成!$D$4*提成!$E$4,$D21/提成!$D$3*提成!$E$3),2) -> 0 | F21: =IFERROR(LOOKUP(1,0/((B21=名单!B:B)*(VALUE(AW21)>=名单!E:E)*(VALUE(AW21)<=名单!G:G)*(Y21="正常走货")),名单!H:H),"否") -> 是 | G21: SP260126064-YYZ7-38 | H21: KP | J21: 加拿大海派-JY | L21: 非主营 | S21: 马淞浦 | T21: 营销一部 | Y21: 正常走货 | AO21: -2935.6 | AW21: 2026-01-31 22:17:08
A22: =MID(AW22,1,7) -> 2026-01 | B22: =_xlfn.XLOOKUP(G22,过机服务商重量差!A:A,过机服务商重量差!G:G) -> 张诚 | C22: =IF(OR(AO22<0,L22="FBA海运"),"","渠道") -> 渠道 | D22: =ROUND(IF(AND(AO22>=0,Y22="正常走货"),_xlfn.XLOOKUP(G22,过机服务商重量差!A:A,过机服务商重量差!L:L),"0"),2) -> 634 | E22: =ROUND(IF(B22="小旋风",$D22/提成!$D$4*提成!$E$4,$D22/提成!$D$3*提成!$E$3),2) -> 6.34 | F22: =IFERROR(LOOKUP(1,0/((B22=名单!B:B)*(VALUE(AW22)>=名单!E:E)*(VALUE(AW22)<=名单!G:G)*(Y22="正常走货")),名单!H:H),"否") -> 否 | G22: SP260112003 | J22: 欧洲海卡包税-MM | L22: 非主营 | S22: 马淞浦 | T22: 营销一部 | Y22: 正常走货 | AO22: 7975.8 | AW22: 2026-01-31 22:12:25
A23: =MID(AW23,1,7) -> 2026-01 | B23: =_xlfn.XLOOKUP(G23,过机服务商重量差!A:A,过机服务商重量差!G:G) -> 小旋风 | C23: =IF(OR(AO23<0,L23="FBA海运"),"","渠道") -> 渠道 | D23: =ROUND(IF(AND(AO23>=0,Y23="正常走货"),_xlfn.XLOOKUP(G23,过机服务商重量差!A:A,过机服务商重量差!L:L),"0"),2) -> 37 | E23: =ROUND(IF(B23="小旋风",$D23/提成!$D$4*提成!$E$4,$D23/提成!$D$3*提成!$E$3),2) -> 0.37 | F23: =IFERROR(LOOKUP(1,0/((B23=名单!B:B)*(VALUE(AW23)>=名单!E:E)*(VALUE(AW23)<=名单!G:G)*(Y23="正常走货")),名单!H:H),"否") -> 是 | G23: HCLSA0131-6 | H23: TPL000134937 | J23: 澳大利亚海派-含税-SC | L23: 非主营 | S23: 刘申奥 | T23: 营销五部 | Y23: 正常走货 | AO23: 195.9 | AW23: 2026-01-31 22:08:59
A24: =MID(AW24,1,7) -> 2026-01 | B24: =_xlfn.XLOOKUP(G24,过机服务商重量差!A:A,过机服务商重量差!G:G) -> 张诚 | C24: =IF(OR(AO24<0,L24="FBA海运"),"","渠道") -> 渠道 | D24: =ROUND(IF(AND(AO24>=0,Y24="正常走货"),_xlfn.XLOOKUP(G24,过机服务商重量差!A:A,过机服务商重量差!L:L),"0"),2) -> 503 | E24: =ROUND(IF(B24="小旋风",$D24/提成!$D$4*提成!$E$4,$D24/提成!$D$3*提成!$E$3),2) -> 5.03 | F24: =IFERROR(LOOKUP(1,0/((B24=名单!B:B)*(VALUE(AW24)>=名单!E:E)*(VALUE(AW24)<=名单!G:G)*(Y24="正常走货")),名单!H:H),"否") -> 否 | G24: SP260121154 | J24: 欧洲海卡包税-MM | L24: 非主营 | S24: 马淞浦 | T24: 营销一部 | Y24: 正常走货 | AO24: 6287.5 | AW24: 2026-01-31 22:01:04
A25: =MID(AW25,1,7) -> 2026-01 | B25: =_xlfn.XLOOKUP(G25,过机服务商重量差!A:A,过机服务商重量差!G:G) -> 小旋风 | C25: =IF(OR(AO25<0,L25="FBA海运"),"","渠道") -> 渠道 | D25: =ROUND(IF(AND(AO25>=0,Y25="正常走货"),_xlfn.XLOOKUP(G25,过机服务商重量差!A:A,过机服务商重量差!L:L),"0"),2) -> 52 | E25: =ROUND(IF(B25="小旋风",$D25/提成!$D$4*提成!$E$4,$D25/提成!$D$3*提成!$E$3),2) -> 0.52 | F25: =IFERROR(LOOKUP(1,0/((B25=名单!B:B)*(VALUE(AW25)>=名单!E:E)*(VALUE(AW25)<=名单!G:G)*(Y25="正常走货")),名单!H:H),"否") -> 是 | G25: YKZXX013102 | H25: 1ZA06B016832064447 | J25: 欧洲德国清专线 | L25: 非主营 | S25: 张小雪 | T25: 营销五部 | Y25: 正常走货 | AO25: 2794 | AW25: 2026-01-31 21:13:41
A26: =MID(AW26,1,7) -> 2026-01 | B26: =_xlfn.XLOOKUP(G26,过机服务商重量差!A:A,过机服务商重量差!G:G) -> 玉麒麟 | C26: =IF(OR(AO26<0,L26="FBA海运"),"","渠道") -> 渠道 | D26: =ROUND(IF(AND(AO26>=0,Y26="正常走货"),_xlfn.XLOOKUP(G26,过机服务商重量差!A:A,过机服务商重量差!L:L),"0"),2) -> 1 | E26: =ROUND(IF(B26="小旋风",$D26/提成!$D$4*提成!$E$4,$D26/提成!$D$3*提成!$E$3),2) -> 0.01 | F26: =IFERROR(LOOKUP(1,0/((B26=名单!B:B)*(VALUE(AW26)>=名单!E:E)*(VALUE(AW26)<=名单!G:G)*(Y26="正常走货")),名单!H:H),"否") -> 否 | G26: TM260131-1CA3 | H26: 888386607575 | J26: OK-FDX-DHL-TNT | L26: 非主营 | S26: 邓健群 | T26: 营销三部 | Y26: 正常走货 | AO26: 17.92 | AW26: 2026-01-31 21:02:14
A27: =MID(AW27,1,7) -> 2026-01 | B27: =_xlfn.XLOOKUP(G27,过机服务商重量差!A:A,过机服务商重量差!G:G) -> 小旋风 | C27: =IF(OR(AO27<0,L27="FBA海运"),"","渠道") -> 渠道 | D27: =ROUND(IF(AND(AO27>=0,Y27="正常走货"),_xlfn.XLOOKUP(G27,过机服务商重量差!A:A,过机服务商重量差!L:L),"0"),2) -> 30 | E27: =ROUND(IF(B27="小旋风",$D27/提成!$D$4*提成!$E$4,$D27/提成!$D$3*提成!$E$3),2) -> 0.3 | F27: =IFERROR(LOOKUP(1,0/((B27=名单!B:B)*(VALUE(AW27)>=名单!E:E)*(VALUE(AW27)<=名单!G:G)*(Y27="正常走货")),名单!H:H),"否") -> 是 | G27: TM260131-2FR2 | H27: 1ZA06B016818572639 | J27: 欧洲德国清专线 | L27: 非主营 | S27: 邓健群 | T27: 营销三部 | Y27: 正常走货 | AO27: 1500 | AW27: 2026-01-31 21:00:55
A28: =MID(AW28,1,7) -> 2026-01 | B28: =_xlfn.XLOOKUP(G28,过机服务商重量差!A:A,过机服务商重量差!G:G) -> 帅时莹 | C28: =IF(OR(AO28<0,L28="FBA海运"),"","渠道") -> 渠道 | D28: =ROUND(IF(AND(AO28>=0,Y28="正常走货"),_xlfn.XLOOKUP(G28,过机服务商重量差!A:A,过机服务商重量差!L:L),"0"),2) -> 208 | E28: =ROUND(IF(B28="小旋风",$D28/提成!$D$4*提成!$E$4,$D28/提成!$D$3*提成!$E$3),2) -> 2.08 | F28: {=IFERROR(LOOKUP(1,0/((B28=名单!B:B)*(VALUE(AW28)>=名单!E:E)*(VALUE(AW28)<=名单!G:G)*(Y28="正常走货")),名单!H:H),"否")} -> 否 | G28: HH233M26 | H28: 1ZF4K3596816247057 | J28: 欧洲专线-HMC | L28: 非主营 | S28: 李娟-业务 | T28: 营销四部 | Y28: 正常走货 | AO28: 2700 | AW28: 2026-01-31 20:59:02
A29: =MID(AW29,1,7) -> 2026-01 | B29: =_xlfn.XLOOKUP(G29,过机服务商重量差!A:A,过机服务商重量差!G:G) -> 玉麒麟 | C29: =IF(OR(AO29<0,L29="FBA海运"),"","渠道") -> 渠道 | D29: =ROUND(IF(AND(AO29>=0,Y29="正常走货"),_xlfn.XLOOKUP(G29,过机服务商重量差!A:A,过机服务商重量差!L:L),"0"),2) -> 10 | E29: =ROUND(IF(B29="小旋风",$D29/提成!$D$4*提成!$E$4,$D29/提成!$D$3*提成!$E$3),2) -> 0.1 | F29: =IFERROR(LOOKUP(1,0/((B29=名单!B:B)*(VALUE(AW29)>=名单!E:E)*(VALUE(AW29)<=名单!G:G)*(Y29="正常走货")),名单!H:H),"否") -> 否 | G29: RSC3104 | H29: 1Z0E465J0413832648 | J29: OK-FDX-DHL-TNT | L29: 非主营 | S29: 汪祺 | T29: 营销二部 | Y29: 正常走货 | AO29: 101.6 | AW29: 2026-01-31 20:56:27
A30: =MID(AW30,1,7) -> 2026-01 | B30: =_xlfn.XLOOKUP(G30,过机服务商重量差!A:A,过机服务商重量差!G:G) -> 玉麒麟 | C30: =IF(OR(AO30<0,L30="FBA海运"),"","渠道") -> 渠道 | D30: =ROUND(IF(AND(AO30>=0,Y30="正常走货"),_xlfn.XLOOKUP(G30,过机服务商重量差!A:A,过机服务商重量差!L:L),"0"),2) -> 10 | E30: =ROUND(IF(B30="小旋风",$D30/提成!$D$4*提成!$E$4,$D30/提成!$D$3*提成!$E$3),2) -> 0.1 | F30: =IFERROR(LOOKUP(1,0/((B30=名单!B:B)*(VALUE(AW30)>=名单!E:E)*(VALUE(AW30)<=名单!G:G)*(Y30="正常走货")),名单!H:H),"否") -> 否 | G30: RSC3103 | H30: 1Z0E465J0419105235 | J30: OK-FDX-DHL-TNT | L30: 非主营 | S30: 汪祺 | T30: 营销二部 | Y30: 正常走货 | AO30: 101.6 | AW30: 2026-01-31 20:56:22
A31: =MID(AW31,1,7) -> 2026-01 | B31: =_xlfn.XLOOKUP(G31,过机服务商重量差!A:A,过机服务商重量差!G:G) -> 玉麒麟 | C31: =IF(OR(AO31<0,L31="FBA海运"),"","渠道") -> 渠道 | D31: =ROUND(IF(AND(AO31>=0,Y31="正常走货"),_xlfn.XLOOKUP(G31,过机服务商重量差!A:A,过机服务商重量差!L:L),"0"),2) -> 5.5 | E31: =ROUND(IF(B31="小旋风",$D31/提成!$D$4*提成!$E$4,$D31/提成!$D$3*提成!$E$3),2) -> 0.06 | F31: =IFERROR(LOOKUP(1,0/((B31=名单!B:B)*(VALUE(AW31)>=名单!E:E)*(VALUE(AW31)<=名单!G:G)*(Y31="正常走货")),名单!H:H),"否") -> 否 | G31: RSC3102 | H31: 1Z0E465J0419058000 | J31: OK-FDX-DHL-TNT | L31: 非主营 | S31: 汪祺 | T31: 营销二部 | Y31: 正常走货 | AO31: 101.6 | AW31: 2026-01-31 20:56:04
A32: =MID(AW32,1,7) -> 2026-01 | B32: =_xlfn.XLOOKUP(G32,过机服务商重量差!A:A,过机服务商重量差!G:G) -> 玉麒麟 | C32: =IF(OR(AO32<0,L32="FBA海运"),"","渠道") -> 渠道 | D32: =ROUND(IF(AND(AO32>=0,Y32="正常走货"),_xlfn.XLOOKUP(G32,过机服务商重量差!A:A,过机服务商重量差!L:L),"0"),2) -> 6.5 | E32: =ROUND(IF(B32="小旋风",$D32/提成!$D$4*提成!$E$4,$D32/提成!$D$3*提成!$E$3),2) -> 0.07 | F32: =IFERROR(LOOKUP(1,0/((B32=名单!B:B)*(VALUE(AW32)>=名单!E:E)*(VALUE(AW32)<=名单!G:G)*(Y32="正常走货")),名单!H:H),"否") -> 否 | G32: RSC3101 | H32: 1Z0E465J0415072448 | J32: OK-FDX-DHL-TNT | L32: 非主营 | S32: 汪祺 | T32: 营销二部 | Y32: 正常走货 | AO32: 101.6 | AW32: 2026-01-31 20:55:58
A33: =MID(AW33,1,7) -> 2026-01 | B33: =_xlfn.XLOOKUP(G33,过机服务商重量差!A:A,过机服务商重量差!G:G) -> 玉麒麟 | C33: =IF(OR(AO33<0,L33="FBA海运"),"","渠道") -> 渠道 | D33: =ROUND(IF(AND(AO33>=0,Y33="正常走货"),_xlfn.XLOOKUP(G33,过机服务商重量差!A:A,过机服务商重量差!L:L),"0"),2) -> 52 | E33: =ROUND(IF(B33="小旋风",$D33/提成!$D$4*提成!$E$4,$D33/提成!$D$3*提成!$E$3),2) -> 0.52 | F33: =IFERROR(LOOKUP(1,0/((B33=名单!B:B)*(VALUE(AW33)>=名单!E:E)*(VALUE(AW33)<=名单!G:G)*(Y33="正常走货")),名单!H:H),"否") -> 否 | G33: QLWJ1781704 | H33: 1Z0E793D0422717448 | J33: OK-UPS红单 | L33: 非主营 | S33: 宁春阳 | T33: 营销二部 | Y33: 正常走货 | AO33: 421.1 | AW33: 2026-01-31 20:53:03
A34: =MID(AW34,1,7) -> 2026-01 | B34: =_xlfn.XLOOKUP(G34,过机服务商重量差!A:A,过机服务商重量差!G:G) -> 玉麒麟 | C34: =IF(OR(AO34<0,L34="FBA海运"),"","渠道") -> 渠道 | D34: =ROUND(IF(AND(AO34>=0,Y34="正常走货"),_xlfn.XLOOKUP(G34,过机服务商重量差!A:A,过机服务商重量差!L:L),"0"),2) -> 29 | E34: =ROUND(IF(B34="小旋风",$D34/提成!$D$4*提成!$E$4,$D34/提成!$D$3*提成!$E$3),2) -> 0.29 | F34: =IFERROR(LOOKUP(1,0/((B34=名单!B:B)*(VALUE(AW34)>=名单!E:E)*(VALUE(AW34)<=名单!G:G)*(Y34="正常走货")),名单!H:H),"否") -> 否 | G34: JHZW7312 | H34: 888384610822 | J34: OK-FDX-DHL-TNT | L34: 非主营 | S34: 宋海周 | T34: 营销二部 | Y34: 正常走货 | AO34: 101.64 | AW34: 2026-01-31 20:46:55
A35: =MID(AW35,1,7) -> 2026-01 | B35: =_xlfn.XLOOKUP(G35,过机服务商重量差!A:A,过机服务商重量差!G:G) -> 风清扬 | C35: =IF(OR(AO35<0,L35="FBA海运"),"","渠道") -> 渠道 | D35: =ROUND(IF(AND(AO35>=0,Y35="正常走货"),_xlfn.XLOOKUP(G35,过机服务商重量差!A:A,过机服务商重量差!L:L),"0"),2) -> 27 | E35: =ROUND(IF(B35="小旋风",$D35/提成!$D$4*提成!$E$4,$D35/提成!$D$3*提成!$E$3),2) -> 0.27 | F35: =IFERROR(LOOKUP(1,0/((B35=名单!B:B)*(VALUE(AW35)>=名单!E:E)*(VALUE(AW35)<=名单!G:G)*(Y35="正常走货")),名单!H:H),"否") -> 是 | G35: SH0131-2 | H35: 1ZHF38642014756797 | J35: 加拿大准时达海派UPS | L35: 非主营 | S35: 小飞侠 | T35: 营销五部 | Y35: 正常走货 | AO35: 377 | AW35: 2026-01-31 20:43:24
A36: =MID(AW36,1,7) -> 2026-01 | B36: =_xlfn.XLOOKUP(G36,过机服务商重量差!A:A,过机服务商重量差!G:G) -> 无崖子 | C36: =IF(OR(AO36<0,L36="FBA海运"),"","渠道") -> 渠道 | D36: =ROUND(IF(AND(AO36>=0,Y36="正常走货"),_xlfn.XLOOKUP(G36,过机服务商重量差!A:A,过机服务商重量差!L:L),"0"),2) -> 7.5 | E36: =ROUND(IF(B36="小旋风",$D36/提成!$D$4*提成!$E$4,$D36/提成!$D$3*提成!$E$3),2) -> 0.08 | F36: =IFERROR(LOOKUP(1,0/((B36=名单!B:B)*(VALUE(AW36)>=名单!E:E)*(VALUE(AW36)<=名单!G:G)*(Y36="正常走货")),名单!H:H),"否") -> 否 | G36: JPS20260131002 | H36: CR431657742DE | J36: HST-UPS 6000 | L36: 非主营 | S36: 柴燕玲 | T36: 四部KA客服 | Y36: 正常走货 | AO36: 225 | AW36: 2026-01-31 20:41:12
A37: =MID(AW37,1,7) -> 2026-01 | B37: =_xlfn.XLOOKUP(G37,过机服务商重量差!A:A,过机服务商重量差!G:G) -> 无崖子 | C37: =IF(OR(AO37<0,L37="FBA海运"),"","渠道") -> 渠道 | D37: =ROUND(IF(AND(AO37>=0,Y37="正常走货"),_xlfn.XLOOKUP(G37,过机服务商重量差!A:A,过机服务商重量差!L:L),"0"),2) -> 6 | E37: =ROUND(IF(B37="小旋风",$D37/提成!$D$4*提成!$E$4,$D37/提成!$D$3*提成!$E$3),2) -> 0.06 | F37: =IFERROR(LOOKUP(1,0/((B37=名单!B:B)*(VALUE(AW37)>=名单!E:E)*(VALUE(AW37)<=名单!G:G)*(Y37="正常走货")),名单!H:H),"否") -> 否 | G37: JPS20260131001 | H37: CR431657314DE | J37: HST-UPS 6000 | L37: 非主营 | S37: 柴燕玲 | T37: 四部KA客服 | Y37: 正常走货 | AO37: 229.36 | AW37: 2026-01-31 20:41:04
A38: =MID(AW38,1,7) -> 2026-01 | B38: =_xlfn.XLOOKUP(G38,过机服务商重量差!A:A,过机服务商重量差!G:G) -> 玉麒麟 | C38: =IF(OR(AO38<0,L38="FBA海运"),"","渠道") -> 渠道 | D38: =ROUND(IF(AND(AO38>=0,Y38="正常走货"),_xlfn.XLOOKUP(G38,过机服务商重量差!A:A,过机服务商重量差!L:L),"0"),2) -> 25 | E38: =ROUND(IF(B38="小旋风",$D38/提成!$D$4*提成!$E$4,$D38/提成!$D$3*提成!$E$3),2) -> 0.25 | F38: =IFERROR(LOOKUP(1,0/((B38=名单!B:B)*(VALUE(AW38)>=名单!E:E)*(VALUE(AW38)<=名单!G:G)*(Y38="正常走货")),名单!H:H),"否") -> 否 | G38: PBI3-FBA19757N66N | H38: 1Z0E465J0407453337 | J38: OK-FDX-DHL-TNT | L38: 非主营 | S38: 李娟-业务 | T38: 营销四部 | Y38: 正常走货 | AO38: 329.1 | AW38: 2026-01-31 20:40:50
A39: =MID(AW39,1,7) -> 2026-01 | B39: =_xlfn.XLOOKUP(G39,过机服务商重量差!A:A,过机服务商重量差!G:G) -> 帅时莹 | C39: =IF(OR(AO39<0,L39="FBA海运"),"","渠道") -> 渠道 | D39: =ROUND(IF(AND(AO39>=0,Y39="正常走货"),_xlfn.XLOOKUP(G39,过机服务商重量差!A:A,过机服务商重量差!L:L),"0"),2) -> 3.5 | E39: =ROUND(IF(B39="小旋风",$D39/提成!$D$4*提成!$E$4,$D39/提成!$D$3*提成!$E$3),2) -> 0.04 | F39: =IFERROR(LOOKUP(1,0/((B39=名单!B:B)*(VALUE(AW39)>=名单!E:E)*(VALUE(AW39)<=名单!G:G)*(Y39="正常走货")),名单!H:H),"否") -> 否 | G39: 95T6963 | H39: 1ZG3333D0406480200 | J39: MSHQ-UPS | L39: 非主营 | S39: 李娟-业务 | T39: 营销四部 | Y39: 正常走货 | AO39: 139.1 | AW39: 2026-01-31 20:40:36
A40: =MID(AW40,1,7) -> 2026-01 | B40: =_xlfn.XLOOKUP(G40,过机服务商重量差!A:A,过机服务商重量差!G:G) -> 风清扬 | C40: =IF(OR(AO40<0,L40="FBA海运"),"","渠道") -> 渠道 | D40: =ROUND(IF(AND(AO40>=0,Y40="正常走货"),_xlfn.XLOOKUP(G40,过机服务商重量差!A:A,过机服务商重量差!L:L),"0"),2) -> 142 | E40: =ROUND(IF(B40="小旋风",$D40/提成!$D$4*提成!$E$4,$D40/提成!$D$3*提成!$E$3),2) -> 1.42 | F40: =IFERROR(LOOKUP(1,0/((B40=名单!B:B)*(VALUE(AW40)>=名单!E:E)*(VALUE(AW40)<=名单!G:G)*(Y40="正常走货")),名单!H:H),"否") -> 是 | G40: 24543733501033648 | H40: 881072500 | J40: 东南亚专线 | L40: 非主营 | S40: 丁佳伟 | T40: 营销三部 | Y40: 正常走货 | AO40: 1361 | AW40: 2026-01-31 20:40:27
... A49: =MID(AW49,1,7) -> 2026-01 | B49: =_xlfn.XLOOKUP(G49,过机服务商重量差!A:A,过机服务商重量差!G:G) -> 007 | C49: =IF(OR(AO49<0,L49="FBA海运"),"","渠道") -> 渠道 | D49: =ROUND(IF(AND(AO49>=0,Y49="正常走货"),_xlfn.XLOOKUP(G49,过机服务商重量差!A:A,过机服务商重量差!L:L),"0"),2) -> 55 | E49: =ROUND(IF(B49="小旋风",$D49/提成!$D$4*提成!$E$4,$D49/提成!$D$3*提成!$E$3),2) -> 0.55 | F49: =IFERROR(LOOKUP(1,0/((B49=名单!B:B)*(VALUE(AW49)>=名单!E:E)*(VALUE(AW49)<=名单!G:G)*(Y49="正常走货")),名单!H:H),"否") -> 否 | G49: LM-056 | H49: 1Z0R6D926806701789 | J49: 欧洲卡航含税(快递派) | L49: 非主营 | S49: 张小雪 | T49: 营销五部 | Y49: 正常走货 | AO49: 770 | AW49: 2026-01-31 20:26:38
A50: =MID(AW50,1,7) -> 2026-01 | B50: =_xlfn.XLOOKUP(G50,过机服务商重量差!A:A,过机服务商重量差!G:G) -> 无崖子 | C50: =IF(OR(AO50<0,L50="FBA海运"),"","渠道") -> 渠道 | D50: =ROUND(IF(AND(AO50>=0,Y50="正常走货"),_xlfn.XLOOKUP(G50,过机服务商重量差!A:A,过机服务商重量差!L:L),"0"),2) -> 0 | E50: =ROUND(IF(B50="小旋风",$D50/提成!$D$4*提成!$E$4,$D50/提成!$D$3*提成!$E$3),2) -> 0 | F50: =IFERROR(LOOKUP(1,0/((B50=名单!B:B)*(VALUE(AW50)>=名单!E:E)*(VALUE(AW50)<=名单!G:G)*(Y50="正常走货")),名单!H:H),"否") -> 否 | G50: YKZXX0131 | J50: 义乌联邦IE-包税 | L50: 非主营 | S50: 张小雪 | T50: 营销五部 | Y50: 已退件 | AO50: 0 | AW50: 2026-01-31 20:17:55
A51: =MID(AW51,1,7) -> 2026-01 | B51: =_xlfn.XLOOKUP(G51,过机服务商重量差!A:A,过机服务商重量差!G:G) -> 帅时莹 | C51: =IF(OR(AO51<0,L51="FBA海运"),"","渠道") -> 渠道 | D51: =ROUND(IF(AND(AO51>=0,Y51="正常走货"),_xlfn.XLOOKUP(G51,过机服务商重量差!A:A,过机服务商重量差!L:L),"0"),2) -> 82 | E51: =ROUND(IF(B51="小旋风",$D51/提成!$D$4*提成!$E$4,$D51/提成!$D$3*提成!$E$3),2) -> 0.82 | F51: =IFERROR(LOOKUP(1,0/((B51=名单!B:B)*(VALUE(AW51)>=名单!E:E)*(VALUE(AW51)<=名单!G:G)*(Y51="正常走货")),名单!H:H),"否") -> 否 | G51: HJ25613101 | H51: 888401830517 | J51: JRGJ-专线 | L51: 非主营 | S51: 李凤 | T51: 营销四部 | Y51: 正常走货 | AO51: 284 | AW51: 2026-01-31 20:11:57
A52: =MID(AW52,1,7) -> 2026-01 | B52: =_xlfn.XLOOKUP(G52,过机服务商重量差!A:A,过机服务商重量差!G:G) -> 无崖子 | C52: =IF(OR(AO52<0,L52="FBA海运"),"","渠道") -> 渠道 | D52: =ROUND(IF(AND(AO52>=0,Y52="正常走货"),_xlfn.XLOOKUP(G52,过机服务商重量差!A:A,过机服务商重量差!L:L),"0"),2) -> 12.5 | E52: =ROUND(IF(B52="小旋风",$D52/提成!$D$4*提成!$E$4,$D52/提成!$D$3*提成!$E$3),2) -> 0.13 | F52: =IFERROR(LOOKUP(1,0/((B52=名单!B:B)*(VALUE(AW52)>=名单!E:E)*(VALUE(AW52)<=名单!G:G)*(Y52="正常走货")),名单!H:H),"否") -> 否 | G52: 29G6T9 | H52: CR431656565DE | J52: HST-UPS 6000 | L52: 非主营 | S52: 李可 | T52: 营销四部 | Y52: 正常走货 | AO52: 176.56 | AW52: 2026-01-31 20:06:50
A53: =MID(AW53,1,7) -> 2026-01 | B53: =_xlfn.XLOOKUP(G53,过机服务商重量差!A:A,过机服务商重量差!G:G) -> 风清扬 | C53: =IF(OR(AO53<0,L53="FBA海运"),"","渠道") -> 渠道 | D53: =ROUND(IF(AND(AO53>=0,Y53="正常走货"),_xlfn.XLOOKUP(G53,过机服务商重量差!A:A,过机服务商重量差!L:L),"0"),2) -> 1571 | E53: =ROUND(IF(B53="小旋风",$D53/提成!$D$4*提成!$E$4,$D53/提成!$D$3*提成!$E$3),2) -> 15.71 | F53: =IFERROR(LOOKUP(1,0/((B53=名单!B:B)*(VALUE(AW53)>=名单!E:E)*(VALUE(AW53)<=名单!G:G)*(Y53="正常走货")),名单!H:H),"否") -> 是 | G53: UES260100104 | H53: KP | J53: 美转加快提卡派(HEDE) | L53: 非主营 | S53: 张小雪 | T53: 营销五部 | Y53: 正常走货 | AO53: 25028 | AW53: 2026-01-31 20:02:23
A54: =MID(AW54,1,7) -> 2026-01 | B54: =_xlfn.XLOOKUP(G54,过机服务商重量差!A:A,过机服务商重量差!G:G) -> 无崖子 | C54: =IF(OR(AO54<0,L54="FBA海运"),"","渠道") -> 渠道 | D54: =ROUND(IF(AND(AO54>=0,Y54="正常走货"),_xlfn.XLOOKUP(G54,过机服务商重量差!A:A,过机服务商重量差!L:L),"0"),2) -> 0.5 | E54: =ROUND(IF(B54="小旋风",$D54/提成!$D$4*提成!$E$4,$D54/提成!$D$3*提成!$E$3),2) -> 0.01 | F54: =IFERROR(LOOKUP(1,0/((B54=名单!B:B)*(VALUE(AW54)>=名单!E:E)*(VALUE(AW54)<=名单!G:G)*(Y54="正常走货")),名单!H:H),"否") -> 否 | G54: DS260131-90015 | H54: 888393849785 | J54: 义乌联邦FICP-包税 | L54: 非主营 | S54: 臧明 | T54: 北苑总经办 | Y54: 正常走货 | AO54: 0 | AW54: 2026-01-31 19:55:43
A55: =MID(AW55,1,7) -> 2026-01 | B55: =_xlfn.XLOOKUP(G55,过机服务商重量差!A:A,过机服务商重量差!G:G) -> 玉麒麟 | C55: =IF(OR(AO55<0,L55="FBA海运"),"","渠道") -> 渠道 | D55: =ROUND(IF(AND(AO55>=0,Y55="正常走货"),_xlfn.XLOOKUP(G55,过机服务商重量差!A:A,过机服务商重量差!L:L),"0"),2) -> 0.5 | E55: =ROUND(IF(B55="小旋风",$D55/提成!$D$4*提成!$E$4,$D55/提成!$D$3*提成!$E$3),2) -> 0.01 | F55: =IFERROR(LOOKUP(1,0/((B55=名单!B:B)*(VALUE(AW55)>=名单!E:E)*(VALUE(AW55)<=名单!G:G)*(Y55="正常走货")),名单!H:H),"否") -> 否 | G55: NS0131 | H55: 888386680111 | J55: OK-FDX-DHL-TNT | L55: 非主营 | S55: 付乐航 | T55: 营销五部 | Y55: 正常走货 | AO55: 69.81 | AW55: 2026-01-31 19:55:35
A56: =MID(AW56,1,7) -> 2026-01 | B56: =_xlfn.XLOOKUP(G56,过机服务商重量差!A:A,过机服务商重量差!G:G) -> 无崖子 | C56: =IF(OR(AO56<0,L56="FBA海运"),"","渠道") -> 渠道 | D56: =ROUND(IF(AND(AO56>=0,Y56="正常走货"),_xlfn.XLOOKUP(G56,过机服务商重量差!A:A,过机服务商重量差!L:L),"0"),2) -> 0.5 | E56: =ROUND(IF(B56="小旋风",$D56/提成!$D$4*提成!$E$4,$D56/提成!$D$3*提成!$E$3),2) -> 0.01 | F56: =IFERROR(LOOKUP(1,0/((B56=名单!B:B)*(VALUE(AW56)>=名单!E:E)*(VALUE(AW56)<=名单!G:G)*(Y56="正常走货")),名单!H:H),"否") -> 否 | G56: D20260131-1 | H56: 398309170150 | J56: FEDEX速快美国包税6000 | L56: 非主营 | S56: 施建祥 | T56: 营销三部 | Y56: 正常走货 | AO56: 0 | AW56: 2026-01-31 19:55:30
A57: =MID(AW57,1,7) -> 2026-01 | B57: =_xlfn.XLOOKUP(G57,过机服务商重量差!A:A,过机服务商重量差!G:G) -> 玉麒麟 | C57: =IF(OR(AO57<0,L57="FBA海运"),"","渠道") -> 渠道 | D57: =ROUND(IF(AND(AO57>=0,Y57="正常走货"),_xlfn.XLOOKUP(G57,过机服务商重量差!A:A,过机服务商重量差!L:L),"0"),2) -> 7 | E57: =ROUND(IF(B57="小旋风",$D57/提成!$D$4*提成!$E$4,$D57/提成!$D$3*提成!$E$3),2) -> 0.07 | F57: =IFERROR(LOOKUP(1,0/((B57=名单!B:B)*(VALUE(AW57)>=名单!E:E)*(VALUE(AW57)<=名单!G:G)*(Y57="正常走货")),名单!H:H),"否") -> 否 | G57: MWR26131-1 | H57: 1Z4W260E0402266135 | J57: OK-UPS红单 | L57: 非主营 | S57: 徐建 | T57: 营销三部 | Y57: 正常走货 | AO57: 43.3 | AW57: 2026-01-31 19:54:51
A58: =MID(AW58,1,7) -> 2026-01 | B58: =_xlfn.XLOOKUP(G58,过机服务商重量差!A:A,过机服务商重量差!G:G) -> 007 | C58: =IF(OR(AO58<0,L58="FBA海运"),"","渠道") -> 渠道 | D58: =ROUND(IF(AND(AO58>=0,Y58="正常走货"),_xlfn.XLOOKUP(G58,过机服务商重量差!A:A,过机服务商重量差!L:L),"0"),2) -> 35 | E58: =ROUND(IF(B58="小旋风",$D58/提成!$D$4*提成!$E$4,$D58/提成!$D$3*提成!$E$3),2) -> 0.35 | F58: =IFERROR(LOOKUP(1,0/((B58=名单!B:B)*(VALUE(AW58)>=名单!E:E)*(VALUE(AW58)<=名单!G:G)*(Y58="正常走货")),名单!H:H),"否") -> 否 | G58: YQ131CZ-1 | H58: 1Z0R6D926809022365 | J58: 欧洲卡航含税(快递派) | L58: 非主营 | S58: 张俊合 | T58: 营销五部 | Y58: 正常走货 | AO58: 490 | AW58: 2026-01-31 19:47:27
A59: =MID(AW59,1,7) -> 2026-01 | B59: =_xlfn.XLOOKUP(G59,过机服务商重量差!A:A,过机服务商重量差!G:G) -> 玉麒麟 | C59: =IF(OR(AO59<0,L59="FBA海运"),"","渠道") -> 渠道 | D59: =ROUND(IF(AND(AO59>=0,Y59="正常走货"),_xlfn.XLOOKUP(G59,过机服务商重量差!A:A,过机服务商重量差!L:L),"0"),2) -> 3.5 | E59: =ROUND(IF(B59="小旋风",$D59/提成!$D$4*提成!$E$4,$D59/提成!$D$3*提成!$E$3),2) -> 0.04 | F59: =IFERROR(LOOKUP(1,0/((B59=名单!B:B)*(VALUE(AW59)>=名单!E:E)*(VALUE(AW59)<=名单!G:G)*(Y59="正常走货")),名单!H:H),"否") -> 否 | G59: PTYL-131T | H59: 1Z4W260E0409162127 | J59: OK-FDX-DHL-TNT | L59: 非主营 | S59: 汪礼平 | T59: 营销一部 | Y59: 正常走货 | AO59: 62.5 | AW59: 2026-01-31 19:47:08
A60: =MID(AW60,1,7) -> 2026-01 | B60: =_xlfn.XLOOKUP(G60,过机服务商重量差!A:A,过机服务商重量差!G:G) -> 帅时莹 | C60: =IF(OR(AO60<0,L60="FBA海运"),"","渠道") -> 渠道 | D60: =ROUND(IF(AND(AO60>=0,Y60="正常走货"),_xlfn.XLOOKUP(G60,过机服务商重量差!A:A,过机服务商重量差!L:L),"0"),2) -> 131 | E60: =ROUND(IF(B60="小旋风",$D60/提成!$D$4*提成!$E$4,$D60/提成!$D$3*提成!$E$3),2) -> 1.31 | F60: =IFERROR(LOOKUP(1,0/((B60=名单!B:B)*(VALUE(AW60)>=名单!E:E)*(VALUE(AW60)<=名单!G:G)*(Y60="正常走货")),名单!H:H),"否") -> 否 | G60: HY260131-NL-9 | H60: 1ZF4K3596803870460 | J60: 欧洲专线-HMC | L60: 非主营 | S60: 朱杰 | T60: 营销四部 | Y60: 正常走货 | AO60: 1650 | AW60: 2026-01-31 19:46:55
A61: =MID(AW61,1,7) -> 2026-01 | B61: =_xlfn.XLOOKUP(G61,过机服务商重量差!A:A,过机服务商重量差!G:G) -> 玉麒麟 | C61: =IF(OR(AO61<0,L61="FBA海运"),"","渠道") -> 渠道 | D61: =ROUND(IF(AND(AO61>=0,Y61="正常走货"),_xlfn.XLOOKUP(G61,过机服务商重量差!A:A,过机服务商重量差!L:L),"0"),2) -> 7 | E61: =ROUND(IF(B61="小旋风",$D61/提成!$D$4*提成!$E$4,$D61/提成!$D$3*提成!$E$3),2) -> 0.07 | F61: =IFERROR(LOOKUP(1,0/((B61=名单!B:B)*(VALUE(AW61)>=名单!E:E)*(VALUE(AW61)<=名单!G:G)*(Y61="正常走货")),名单!H:H),"否") -> 否 | G61: 5ME9963WS | H61: 1Z0E620D0435857753 | J61: OK-FDX-DHL-TNT | L61: 非主营 | S61: 王岩岩 | T61: 营销四部 | Y61: 正常走货 | AO61: 61.63 | AW61: 2026-01-31 19:43:27
A62: =MID(AW62,1,7) -> 2026-01 | B62: =_xlfn.XLOOKUP(G62,过机服务商重量差!A:A,过机服务商重量差!G:G) -> 风清扬 | C62: =IF(OR(AO62<0,L62="FBA海运"),"","渠道") -> 渠道 | D62: =ROUND(IF(AND(AO62>=0,Y62="正常走货"),_xlfn.XLOOKUP(G62,过机服务商重量差!A:A,过机服务商重量差!L:L),"0"),2) -> 39 | E62: =ROUND(IF(B62="小旋风",$D62/提成!$D$4*提成!$E$4,$D62/提成!$D$3*提成!$E$3),2) -> 0.39 | F62: =IFERROR(LOOKUP(1,0/((B62=名单!B:B)*(VALUE(AW62)>=名单!E:E)*(VALUE(AW62)<=名单!G:G)*(Y62="正常走货")),名单!H:H),"否") -> 是 | G62: BSMY20260131-2 | H62: 1Z0R6D896822740883 | J62: 欧洲快船-JT | L62: 非主营 | S62: 叶伟明 | T62: 营销一部 | Y62: 正常走货 | AO62: 273.9 | AW62: 2026-01-31 19:40:56
... A88: =MID(AW88,1,7) -> 2026-01 | B88: =_xlfn.XLOOKUP(G88,过机服务商重量差!A:A,过机服务商重量差!G:G) -> 风清扬 | C88: =IF(OR(AO88<0,L88="FBA海运"),"","渠道") | D88: =ROUND(IF(AND(AO88>=0,Y88="正常走货"),_xlfn.XLOOKUP(G88,过机服务商重量差!A:A,过机服务商重量差!L:L),"0"),2) -> 0 | E88: =ROUND(IF(B88="小旋风",$D88/提成!$D$4*提成!$E$4,$D88/提成!$D$3*提成!$E$3),2) -> 0 | F88: =IFERROR(LOOKUP(1,0/((B88=名单!B:B)*(VALUE(AW88)>=名单!E:E)*(VALUE(AW88)<=名单!G:G)*(Y88="正常走货")),名单!H:H),"否") -> 是 | G88: LKS-PO8302-51 | H88: KP | J88: 加拿大海派-JY | L88: 非主营 | S88: 马淞浦 | T88: 营销一部 | Y88: 正常走货 | AO88: -1637.8 | AW88: 2026-01-31 18:24:31
A89: =MID(AW89,1,7) -> 2026-01 | B89: =_xlfn.XLOOKUP(G89,过机服务商重量差!A:A,过机服务商重量差!G:G) | C89: =IF(OR(AO89<0,L89="FBA海运"),"","渠道") -> 渠道 | D89: =ROUND(IF(AND(AO89>=0,Y89="正常走货"),_xlfn.XLOOKUP(G89,过机服务商重量差!A:A,过机服务商重量差!L:L),"0"),2) -> 2885 | E89: =ROUND(IF(B89="小旋风",$D89/提成!$D$4*提成!$E$4,$D89/提成!$D$3*提成!$E$3),2) -> 28.85 | F89: =IFERROR(LOOKUP(1,0/((B89=名单!B:B)*(VALUE(AW89)>=名单!E:E)*(VALUE(AW89)<=名单!G:G)*(Y89="正常走货")),名单!H:H),"否") -> 否 | G89: FL-260130A | J89: 美国WP | L89: 非主营 | S89: 陈炎 | T89: 营销二部 | Y89: 正常走货 | AO89: 8631 | AW89: 2026-01-31 18:22:36
A90: =MID(AW90,1,7) -> 2026-01 | B90: =_xlfn.XLOOKUP(G90,过机服务商重量差!A:A,过机服务商重量差!G:G) -> 风清扬 | C90: =IF(OR(AO90<0,L90="FBA海运"),"","渠道") -> 渠道 | D90: =ROUND(IF(AND(AO90>=0,Y90="正常走货"),_xlfn.XLOOKUP(G90,过机服务商重量差!A:A,过机服务商重量差!L:L),"0"),2) -> 21 | E90: =ROUND(IF(B90="小旋风",$D90/提成!$D$4*提成!$E$4,$D90/提成!$D$3*提成!$E$3),2) -> 0.21 | F90: =IFERROR(LOOKUP(1,0/((B90=名单!B:B)*(VALUE(AW90)>=名单!E:E)*(VALUE(AW90)<=名单!G:G)*(Y90="正常走货")),名单!H:H),"否") -> 是 | G90: HL26131-1 | H90: 1ZHF05572014691146 | J90: 加拿大空派-大陆飞-UPS派送/6000 | L90: 非主营 | S90: 丁佳伟 | T90: 营销三部 | Y90: 正常走货 | AO90: 0 | AW90: 2026-01-31 18:17:30
A91: =MID(AW91,1,7) -> 2026-01 | B91: =_xlfn.XLOOKUP(G91,过机服务商重量差!A:A,过机服务商重量差!G:G) -> 无崖子 | C91: =IF(OR(AO91<0,L91="FBA海运"),"","渠道") | D91: =ROUND(IF(AND(AO91>=0,Y91="正常走货"),_xlfn.XLOOKUP(G91,过机服务商重量差!A:A,过机服务商重量差!L:L),"0"),2) -> 0 | E91: =ROUND(IF(B91="小旋风",$D91/提成!$D$4*提成!$E$4,$D91/提成!$D$3*提成!$E$3),2) -> 0 | F91: =IFERROR(LOOKUP(1,0/((B91=名单!B:B)*(VALUE(AW91)>=名单!E:E)*(VALUE(AW91)<=名单!G:G)*(Y91="正常走货")),名单!H:H),"否") -> 否 | G91: GB0131-DE | H91: 888382928543 | J91: 上海FEDEX-P价IP | L91: 非主营 | S91: 陈颖 | T91: 营销五部 | Y91: 正常走货 | AO91: -1.06 | AW91: 2026-01-31 18:17:22
A92: =MID(AW92,1,7) -> 2026-01 | B92: =_xlfn.XLOOKUP(G92,过机服务商重量差!A:A,过机服务商重量差!G:G) -> 007 | C92: =IF(OR(AO92<0,L92="FBA海运"),"","渠道") -> 渠道 | D92: =ROUND(IF(AND(AO92>=0,Y92="正常走货"),_xlfn.XLOOKUP(G92,过机服务商重量差!A:A,过机服务商重量差!L:L),"0"),2) -> 57 | E92: =ROUND(IF(B92="小旋风",$D92/提成!$D$4*提成!$E$4,$D92/提成!$D$3*提成!$E$3),2) -> 0.57 | F92: =IFERROR(LOOKUP(1,0/((B92=名单!B:B)*(VALUE(AW92)>=名单!E:E)*(VALUE(AW92)<=名单!G:G)*(Y92="正常走货")),名单!H:H),"否") -> 否 | G92: FBA15LDBQTGT | H92: 1Z0R6D926808645944 | J92: 欧洲卡航含税(快递派) | L92: 非主营 | S92: 小飞侠 | T92: 营销五部 | Y92: 正常走货 | AO92: 655.5 | AW92: 2026-01-31 18:17:16
A93: =MID(AW93,1,7) -> 2026-01 | B93: =_xlfn.XLOOKUP(G93,过机服务商重量差!A:A,过机服务商重量差!G:G) -> 无崖子 | C93: =IF(OR(AO93<0,L93="FBA海运"),"","渠道") -> 渠道 | D93: =ROUND(IF(AND(AO93>=0,Y93="正常走货"),_xlfn.XLOOKUP(G93,过机服务商重量差!A:A,过机服务商重量差!L:L),"0"),2) -> 3 | E93: =ROUND(IF(B93="小旋风",$D93/提成!$D$4*提成!$E$4,$D93/提成!$D$3*提成!$E$3),2) -> 0.03 | F93: =IFERROR(LOOKUP(1,0/((B93=名单!B:B)*(VALUE(AW93)>=名单!E:E)*(VALUE(AW93)<=名单!G:G)*(Y93="正常走货")),名单!H:H),"否") -> 否 | G93: GB0131-US01 | H93: 398309225951 | J93: FEDEX速快美国包税6000 | L93: 非主营 | S93: 陈颖 | T93: 营销五部 | Y93: 正常走货 | AO93: 0 | AW93: 2026-01-31 18:16:44
A94: =MID(AW94,1,7) -> 2026-01 | B94: =_xlfn.XLOOKUP(G94,过机服务商重量差!A:A,过机服务商重量差!G:G) -> 玉麒麟 | C94: =IF(OR(AO94<0,L94="FBA海运"),"","渠道") -> 渠道 | D94: =ROUND(IF(AND(AO94>=0,Y94="正常走货"),_xlfn.XLOOKUP(G94,过机服务商重量差!A:A,过机服务商重量差!L:L),"0"),2) -> 70 | E94: =ROUND(IF(B94="小旋风",$D94/提成!$D$4*提成!$E$4,$D94/提成!$D$3*提成!$E$3),2) -> 0.7 | F94: =IFERROR(LOOKUP(1,0/((B94=名单!B:B)*(VALUE(AW94)>=名单!E:E)*(VALUE(AW94)<=名单!G:G)*(Y94="正常走货")),名单!H:H),"否") -> 否 | G94: WLXB-3GB-1 | H94: 888384608580 | J94: OK-FDX-DHL-TNT | L94: 非主营 | S94: 邓健群 | T94: 营销三部 | Y94: 正常走货 | AO94: 710.58 | AW94: 2026-01-31 18:16:27
A95: =MID(AW95,1,7) -> 2026-01 | B95: =_xlfn.XLOOKUP(G95,过机服务商重量差!A:A,过机服务商重量差!G:G) -> 玉麒麟 | C95: =IF(OR(AO95<0,L95="FBA海运"),"","渠道") -> 渠道 | D95: =ROUND(IF(AND(AO95>=0,Y95="正常走货"),_xlfn.XLOOKUP(G95,过机服务商重量差!A:A,过机服务商重量差!L:L),"0"),2) -> 69 | E95: =ROUND(IF(B95="小旋风",$D95/提成!$D$4*提成!$E$4,$D95/提成!$D$3*提成!$E$3),2) -> 0.69 | F95: =IFERROR(LOOKUP(1,0/((B95=名单!B:B)*(VALUE(AW95)>=名单!E:E)*(VALUE(AW95)<=名单!G:G)*(Y95="正常走货")),名单!H:H),"否") -> 否 | G95: WLXB-3GB-2 | H95: 888386159189 | J95: OK-FDX-DHL-TNT | L95: 非主营 | S95: 邓健群 | T95: 营销三部 | Y95: 正常走货 | AO95: 805.17 | AW95: 2026-01-31 18:16:03
A96: =MID(AW96,1,7) -> 2026-01 | B96: =_xlfn.XLOOKUP(G96,过机服务商重量差!A:A,过机服务商重量差!G:G) -> 风清扬 | C96: =IF(OR(AO96<0,L96="FBA海运"),"","渠道") -> 渠道 | D96: =ROUND(IF(AND(AO96>=0,Y96="正常走货"),_xlfn.XLOOKUP(G96,过机服务商重量差!A:A,过机服务商重量差!L:L),"0"),2) -> 423 | E96: =ROUND(IF(B96="小旋风",$D96/提成!$D$4*提成!$E$4,$D96/提成!$D$3*提成!$E$3),2) -> 4.23 | F96: =IFERROR(LOOKUP(1,0/((B96=名单!B:B)*(VALUE(AW96)>=名单!E:E)*(VALUE(AW96)<=名单!G:G)*(Y96="正常走货")),名单!H:H),"否") -> 是 | G96: CH20260131-1 | H96: KP | J96: 英国卡航-卡派-含税-KY | L96: 非主营 | S96: 张德士 | T96: 营销一部 | Y96: 正常走货 | AO96: 100 | AW96: 2026-01-31 18:14:49
A97: =MID(AW97,1,7) -> 2026-01 | B97: =_xlfn.XLOOKUP(G97,过机服务商重量差!A:A,过机服务商重量差!G:G) -> 无崖子 | C97: =IF(OR(AO97<0,L97="FBA海运"),"","渠道") -> 渠道 | D97: =ROUND(IF(AND(AO97>=0,Y97="正常走货"),_xlfn.XLOOKUP(G97,过机服务商重量差!A:A,过机服务商重量差!L:L),"0"),2) -> 62 | E97: =ROUND(IF(B97="小旋风",$D97/提成!$D$4*提成!$E$4,$D97/提成!$D$3*提成!$E$3),2) -> 0.62 | F97: =IFERROR(LOOKUP(1,0/((B97=名单!B:B)*(VALUE(AW97)>=名单!E:E)*(VALUE(AW97)<=名单!G:G)*(Y97="正常走货")),名单!H:H),"否") -> 否 | G97: JYZ26013101 | H97: 1ZX30Y730490393478 | J97: 义乌UPS红单直发包税/5000 | L97: 非主营 | S97: 张小雪 | T97: 营销五部 | Y97: 正常走货 | AO97: 31.4 | AW97: 2026-01-31 18:09:43
A98: =MID(AW98,1,7) -> 2026-01 | B98: =_xlfn.XLOOKUP(G98,过机服务商重量差!A:A,过机服务商重量差!G:G) -> 无崖子 | C98: =IF(OR(AO98<0,L98="FBA海运"),"","渠道") -> 渠道 | D98: =ROUND(IF(AND(AO98>=0,Y98="正常走货"),_xlfn.XLOOKUP(G98,过机服务商重量差!A:A,过机服务商重量差!L:L),"0"),2) -> 55 | E98: =ROUND(IF(B98="小旋风",$D98/提成!$D$4*提成!$E$4,$D98/提成!$D$3*提成!$E$3),2) -> 0.55 | F98: =IFERROR(LOOKUP(1,0/((B98=名单!B:B)*(VALUE(AW98)>=名单!E:E)*(VALUE(AW98)<=名单!G:G)*(Y98="正常走货")),名单!H:H),"否") -> 否 | G98: JYZ26013102 | H98: 1ZX30Y730498888581 | J98: 义乌UPS红单直发包税/5000 | L98: 非主营 | S98: 张小雪 | T98: 营销五部 | Y98: 正常走货 | AO98: 27.9 | AW98: 2026-01-31 18:05:23
A99: =MID(AW99,1,7) -> 2026-01 | B99: =_xlfn.XLOOKUP(G99,过机服务商重量差!A:A,过机服务商重量差!G:G) -> 小旋风 | C99: =IF(OR(AO99<0,L99="FBA海运"),"","渠道") -> 渠道 | D99: =ROUND(IF(AND(AO99>=0,Y99="正常走货"),_xlfn.XLOOKUP(G99,过机服务商重量差!A:A,过机服务商重量差!L:L),"0"),2) -> 429.5 | E99: =ROUND(IF(B99="小旋风",$D99/提成!$D$4*提成!$E$4,$D99/提成!$D$3*提成!$E$3),2) -> 4.29 | F99: =IFERROR(LOOKUP(1,0/((B99=名单!B:B)*(VALUE(AW99)>=名单!E:E)*(VALUE(AW99)<=名单!G:G)*(Y99="正常走货")),名单!H:H),"否") -> 是 | G99: JLL260131A | H99: MKP4534281830 | J99: 澳大利亚空派-大陆飞-SC | L99: 非主营 | S99: 陈炎 | T99: 营销二部 | Y99: 正常走货 | AO99: 2700.03 | AW99: 2026-01-31 17:59:41
A100: =MID(AW100,1,7) -> 2026-01 | B100: =_xlfn.XLOOKUP(G100,过机服务商重量差!A:A,过机服务商重量差!G:G) -> 小旋风 | C100: =IF(OR(AO100<0,L100="FBA海运"),"","渠道") -> 渠道 | D100: =ROUND(IF(AND(AO100>=0,Y100="正常走货"),_xlfn.XLOOKUP(G100,过机服务商重量差!A:A,过机服务商重量差!L:L),"0"),2) -> 30 | E100: =ROUND(IF(B100="小旋风",$D100/提成!$D$4*提成!$E$4,$D100/提成!$D$3*提成!$E$3),2) -> 0.3 | F100: =IFERROR(LOOKUP(1,0/((B100=名单!B:B)*(VALUE(AW100)>=名单!E:E)*(VALUE(AW100)<=名单!G:G)*(Y100="正常走货")),名单!H:H),"否") -> 是 | G100: JLL260131B | H100: TPL600032612 | J100: 澳大利亚空派-大陆飞-SC | L100: 非主营 | S100: 陈炎 | T100: 营销二部 | Y100: 正常走货 | AO100: 163 | AW100: 2026-01-31 17:59:29
A101: =MID(AW101,1,7) -> 2026-01 | B101: =_xlfn.XLOOKUP(G101,过机服务商重量差!A:A,过机服务商重量差!G:G) -> 玉麒麟 | C101: =IF(OR(AO101<0,L101="FBA海运"),"","渠道") -> 渠道 | D101: =ROUND(IF(AND(AO101>=0,Y101="正常走货"),_xlfn.XLOOKUP(G101,过机服务商重量差!A:A,过机服务商重量差!L:L),"0"),2) -> 12 | E101: =ROUND(IF(B101="小旋风",$D101/提成!$D$4*提成!$E$4,$D101/提成!$D$3*提成!$E$3),2) -> 0.12 | F101: =IFERROR(LOOKUP(1,0/((B101=名单!B:B)*(VALUE(AW101)>=名单!E:E)*(VALUE(AW101)<=名单!G:G)*(Y101="正常走货")),名单!H:H),"否") -> 否 | G101: JLL260131C | H101: 888385218542 | J101: OK-FDX-DHL-TNT | L101: 非主营 | S101: 陈炎 | T101: 营销二部 | Y101: 正常走货 | AO101: 89 | AW101: 2026-01-31 17:59:12
... A113: =MID(AW113,1,7) -> 2026-01 | B113: =_xlfn.XLOOKUP(G113,过机服务商重量差!A:A,过机服务商重量差!G:G) -> 玉麒麟 | C113: =IF(OR(AO113<0,L113="FBA海运"),"","渠道") -> 渠道 | D113: =ROUND(IF(AND(AO113>=0,Y113="正常走货"),_xlfn.XLOOKUP(G113,过机服务商重量差!A:A,过机服务商重量差!L:L),"0"),2) -> 0.5 | E113: =ROUND(IF(B113="小旋风",$D113/提成!$D$4*提成!$E$4,$D113/提成!$D$3*提成!$E$3),2) -> 0.01 | F113: =IFERROR(LOOKUP(1,0/((B113=名单!B:B)*(VALUE(AW113)>=名单!E:E)*(VALUE(AW113)<=名单!G:G)*(Y113="正常走货")),名单!H:H),"否") -> 否 | G113: ZJTX2025803 | H113: 888386075311 | J113: OK-FDX-DHL-TNT | L113: 非主营 | S113: 陈玉琴 | T113: 营销五部 | Y113: 正常走货 | AO113: 71.02 | AW113: 2026-01-31 16:55:46
A114: =MID(AW114,1,7) -> 2026-01 | B114: =_xlfn.XLOOKUP(G114,过机服务商重量差!A:A,过机服务商重量差!G:G) -> 玉麒麟 | C114: =IF(OR(AO114<0,L114="FBA海运"),"","渠道") -> 渠道 | D114: =ROUND(IF(AND(AO114>=0,Y114="正常走货"),_xlfn.XLOOKUP(G114,过机服务商重量差!A:A,过机服务商重量差!L:L),"0"),2) -> 0.5 | E114: =ROUND(IF(B114="小旋风",$D114/提成!$D$4*提成!$E$4,$D114/提成!$D$3*提成!$E$3),2) -> 0.01 | F114: =IFERROR(LOOKUP(1,0/((B114=名单!B:B)*(VALUE(AW114)>=名单!E:E)*(VALUE(AW114)<=名单!G:G)*(Y114="正常走货")),名单!H:H),"否") -> 否 | G114: CZQ260130 | J114: OK-FDX-DHL-TNT | L114: 非主营 | S114: 蒋龙波 | T114: 营销三部 | Y114: 正常走货 | AO114: 23.5 | AW114: 2026-01-31 16:55:40
A115: =MID(AW115,1,7) -> 2026-01 | B115: =_xlfn.XLOOKUP(G115,过机服务商重量差!A:A,过机服务商重量差!G:G) -> 007 | C115: =IF(OR(AO115<0,L115="FBA海运"),"","渠道") -> 渠道 | D115: =ROUND(IF(AND(AO115>=0,Y115="正常走货"),_xlfn.XLOOKUP(G115,过机服务商重量差!A:A,过机服务商重量差!L:L),"0"),2) -> 26 | E115: =ROUND(IF(B115="小旋风",$D115/提成!$D$4*提成!$E$4,$D115/提成!$D$3*提成!$E$3),2) -> 0.26 | F115: =IFERROR(LOOKUP(1,0/((B115=名单!B:B)*(VALUE(AW115)>=名单!E:E)*(VALUE(AW115)<=名单!G:G)*(Y115="正常走货")),名单!H:H),"否") -> 否 | G115: FREDA707102 | H115: 1Z0R6D926803614290 | J115: 欧洲海派含税(快递派) | L115: 非主营 | S115: 高雨晴 | T115: 营销二部 | Y115: 正常走货 | AO115: 223.6 | AW115: 2026-01-31 16:55:24
A116: =MID(AW116,1,7) -> 2026-01 | B116: =_xlfn.XLOOKUP(G116,过机服务商重量差!A:A,过机服务商重量差!G:G) -> 风清扬 | C116: =IF(OR(AO116<0,L116="FBA海运"),"","渠道") -> 渠道 | D116: =ROUND(IF(AND(AO116>=0,Y116="正常走货"),_xlfn.XLOOKUP(G116,过机服务商重量差!A:A,过机服务商重量差!L:L),"0"),2) -> 326 | E116: =ROUND(IF(B116="小旋风",$D116/提成!$D$4*提成!$E$4,$D116/提成!$D$3*提成!$E$3),2) -> 3.26 | F116: =IFERROR(LOOKUP(1,0/((B116=名单!B:B)*(VALUE(AW116)>=名单!E:E)*(VALUE(AW116)<=名单!G:G)*(Y116="正常走货")),名单!H:H),"否") -> 是 | G116: LUNA9305523 | H116: 1Z0R6D896806053549 | J116: 欧洲快船-JT | L116: 非主营 | S116: 何林霞 | T116: 营销二部 | Y116: 正常走货 | AO116: 2871 | AW116: 2026-01-31 16:54:57
A117: =MID(AW117,1,7) -> 2026-01 | B117: =_xlfn.XLOOKUP(G117,过机服务商重量差!A:A,过机服务商重量差!G:G) -> 007 | C117: =IF(OR(AO117<0,L117="FBA海运"),"","渠道") -> 渠道 | D117: =ROUND(IF(AND(AO117>=0,Y117="正常走货"),_xlfn.XLOOKUP(G117,过机服务商重量差!A:A,过机服务商重量差!L:L),"0"),2) -> 3374 | E117: =ROUND(IF(B117="小旋风",$D117/提成!$D$4*提成!$E$4,$D117/提成!$D$3*提成!$E$3),2) -> 33.74 | F117: =IFERROR(LOOKUP(1,0/((B117=名单!B:B)*(VALUE(AW117)>=名单!E:E)*(VALUE(AW117)<=名单!G:G)*(Y117="正常走货")),名单!H:H),"否") -> 否 | G117: RF-1147 | H117: 1Z0R6D926839601567 | J117: 欧洲海派含税(快递派) | L117: 非主营 | S117: 王拥 | T117: 营销二部 | Y117: 正常走货 | AO117: 29016.4 | AW117: 2026-01-31 16:53:00
A118: =MID(AW118,1,7) -> 2026-01 | B118: =_xlfn.XLOOKUP(G118,过机服务商重量差!A:A,过机服务商重量差!G:G) -> 小旋风 | C118: =IF(OR(AO118<0,L118="FBA海运"),"","渠道") -> 渠道 | D118: =ROUND(IF(AND(AO118>=0,Y118="正常走货"),_xlfn.XLOOKUP(G118,过机服务商重量差!A:A,过机服务商重量差!L:L),"0"),2) -> 22 | E118: =ROUND(IF(B118="小旋风",$D118/提成!$D$4*提成!$E$4,$D118/提成!$D$3*提成!$E$3),2) -> 0.22 | F118: =IFERROR(LOOKUP(1,0/((B118=名单!B:B)*(VALUE(AW118)>=名单!E:E)*(VALUE(AW118)<=名单!G:G)*(Y118="正常走货")),名单!H:H),"否") -> 是 | G118: FG260108020 | H118: AMQ6873655 | J118: 澳大利亚空派-经济线-SC | L118: 非主营 | S118: 李凤 | T118: 营销四部 | Y118: 正常走货 | AO118: 110 | AW118: 2026-01-31 16:51:26
A119: =MID(AW119,1,7) -> 2026-01 | B119: =_xlfn.XLOOKUP(G119,过机服务商重量差!A:A,过机服务商重量差!G:G) -> 帅时莹 | C119: =IF(OR(AO119<0,L119="FBA海运"),"","渠道") -> 渠道 | D119: =ROUND(IF(AND(AO119>=0,Y119="正常走货"),_xlfn.XLOOKUP(G119,过机服务商重量差!A:A,过机服务商重量差!L:L),"0"),2) -> 60 | E119: =ROUND(IF(B119="小旋风",$D119/提成!$D$4*提成!$E$4,$D119/提成!$D$3*提成!$E$3),2) -> 0.6 | F119: =IFERROR(LOOKUP(1,0/((B119=名单!B:B)*(VALUE(AW119)>=名单!E:E)*(VALUE(AW119)<=名单!G:G)*(Y119="正常走货")),名单!H:H),"否") -> 否 | G119: RC261302 | H119: SA780165875 | J119: 阿联酋专线-YT | L119: 非主营 | S119: 李凤 | T119: 营销四部 | Y119: 正常走货 | AO119: 210 | AW119: 2026-01-31 16:47:46
A120: =MID(AW120,1,7) -> 2026-01 | B120: =_xlfn.XLOOKUP(G120,过机服务商重量差!A:A,过机服务商重量差!G:G) -> 玉麒麟 | C120: =IF(OR(AO120<0,L120="FBA海运"),"","渠道") -> 渠道 | D120: =ROUND(IF(AND(AO120>=0,Y120="正常走货"),_xlfn.XLOOKUP(G120,过机服务商重量差!A:A,过机服务商重量差!L:L),"0"),2) -> 96 | E120: =ROUND(IF(B120="小旋风",$D120/提成!$D$4*提成!$E$4,$D120/提成!$D$3*提成!$E$3),2) -> 0.96 | F120: =IFERROR(LOOKUP(1,0/((B120=名单!B:B)*(VALUE(AW120)>=名单!E:E)*(VALUE(AW120)<=名单!G:G)*(Y120="正常走货")),名单!H:H),"否") -> 否 | G120: SQ260108002 | H120: 500745742652 | J120: OK-UPS蓝单 | L120: 非主营 | S120: 李凤 | T120: 营销四部 | Y120: 正常走货 | AO120: 1779 | AW120: 2026-01-31 16:46:22
A121: =MID(AW121,1,7) -> 2026-01 | B121: =_xlfn.XLOOKUP(G121,过机服务商重量差!A:A,过机服务商重量差!G:G) | C121: =IF(OR(AO121<0,L121="FBA海运"),"","渠道") -> 渠道 | D121: =ROUND(IF(AND(AO121>=0,Y121="正常走货"),_xlfn.XLOOKUP(G121,过机服务商重量差!A:A,过机服务商重量差!L:L),"0"),2) -> 3701 | E121: =ROUND(IF(B121="小旋风",$D121/提成!$D$4*提成!$E$4,$D121/提成!$D$3*提成!$E$3),2) -> 37.01 | F121: =IFERROR(LOOKUP(1,0/((B121=名单!B:B)*(VALUE(AW121)>=名单!E:E)*(VALUE(AW121)<=名单!G:G)*(Y121="正常走货")),名单!H:H),"否") -> 否 | G121: FL-2601310E | J121: 美国WP | L121: 非主营 | S121: 陈炎 | T121: 营销二部 | Y121: 正常走货 | AO121: 3709 | AW121: 2026-01-31 16:43:29
A122: =MID(AW122,1,7) -> 2026-01 | B122: =_xlfn.XLOOKUP(G122,过机服务商重量差!A:A,过机服务商重量差!G:G) -> 小旋风 | C122: =IF(OR(AO122<0,L122="FBA海运"),"","渠道") -> 渠道 | D122: =ROUND(IF(AND(AO122>=0,Y122="正常走货"),_xlfn.XLOOKUP(G122,过机服务商重量差!A:A,过机服务商重量差!L:L),"0"),2) -> 431 | E122: =ROUND(IF(B122="小旋风",$D122/提成!$D$4*提成!$E$4,$D122/提成!$D$3*提成!$E$3),2) -> 4.31 | F122: =IFERROR(LOOKUP(1,0/((B122=名单!B:B)*(VALUE(AW122)>=名单!E:E)*(VALUE(AW122)<=名单!G:G)*(Y122="正常走货")),名单!H:H),"否") -> 是 | G122: HS457-77 | H122: SA-WJ24626 | J122: 沙特海派 | L122: 非主营 | S122: 左宗伟 | T122: 营销四部 | Y122: 正常走货 | AO122: 3670 | AW122: 2026-01-31 16:42:07
A123: =MID(AW123,1,7) -> 2026-01 | B123: =_xlfn.XLOOKUP(G123,过机服务商重量差!A:A,过机服务商重量差!G:G) -> 007 | C123: =IF(OR(AO123<0,L123="FBA海运"),"","渠道") -> 渠道 | D123: =ROUND(IF(AND(AO123>=0,Y123="正常走货"),_xlfn.XLOOKUP(G123,过机服务商重量差!A:A,过机服务商重量差!L:L),"0"),2) -> 865 | E123: =ROUND(IF(B123="小旋风",$D123/提成!$D$4*提成!$E$4,$D123/提成!$D$3*提成!$E$3),2) -> 8.65 | F123: =IFERROR(LOOKUP(1,0/((B123=名单!B:B)*(VALUE(AW123)>=名单!E:E)*(VALUE(AW123)<=名单!G:G)*(Y123="正常走货")),名单!H:H),"否") -> 否 | G123: RF-7704 | H123: 1Z0R6D926832267101 | J123: 欧洲海派含税(快递派) | L123: 非主营 | S123: 王拥 | T123: 营销二部 | Y123: 正常走货 | AO123: 7439 | AW123: 2026-01-31 16:37:12
A124: =MID(AW124,1,7) -> 2026-01 | B124: =_xlfn.XLOOKUP(G124,过机服务商重量差!A:A,过机服务商重量差!G:G) -> 小旋风 | C124: =IF(OR(AO124<0,L124="FBA海运"),"","渠道") -> 渠道 | D124: =ROUND(IF(AND(AO124>=0,Y124="正常走货"),_xlfn.XLOOKUP(G124,过机服务商重量差!A:A,过机服务商重量差!L:L),"0"),2) -> 150 | E124: =ROUND(IF(B124="小旋风",$D124/提成!$D$4*提成!$E$4,$D124/提成!$D$3*提成!$E$3),2) -> 1.5 | F124: =IFERROR(LOOKUP(1,0/((B124=名单!B:B)*(VALUE(AW124)>=名单!E:E)*(VALUE(AW124)<=名单!G:G)*(Y124="正常走货")),名单!H:H),"否") -> 是 | G124: YINHAI2544 | H124: MY4751 | J124: 沙特空派 | L124: 非主营 | S124: 左宗伟 | T124: 营销四部 | Y124: 正常走货 | AO124: 830 | AW124: 2026-01-31 16:34:06
A125: =MID(AW125,1,7) -> 2026-01 | B125: =_xlfn.XLOOKUP(G125,过机服务商重量差!A:A,过机服务商重量差!G:G) -> 小旋风 | C125: =IF(OR(AO125<0,L125="FBA海运"),"","渠道") -> 渠道 | D125: =ROUND(IF(AND(AO125>=0,Y125="正常走货"),_xlfn.XLOOKUP(G125,过机服务商重量差!A:A,过机服务商重量差!L:L),"0"),2) -> 1313 | E125: =ROUND(IF(B125="小旋风",$D125/提成!$D$4*提成!$E$4,$D125/提成!$D$3*提成!$E$3),2) -> 13.13 | F125: =IFERROR(LOOKUP(1,0/((B125=名单!B:B)*(VALUE(AW125)>=名单!E:E)*(VALUE(AW125)<=名单!G:G)*(Y125="正常走货")),名单!H:H),"否") -> 是 | G125: LR260130 | H125: MKP24000759952 | J125: 私人地址海派双清含税（AU-S-02） | L125: 非主营 | S125: 孙源圻 | T125: 营销三部 | Y125: 正常走货 | AO125: 8140.6 | AW125: 2026-01-31 16:32:23
A126: =MID(AW126,1,7) -> 2026-01 | B126: =_xlfn.XLOOKUP(G126,过机服务商重量差!A:A,过机服务商重量差!G:G) -> 帅时莹 | C126: =IF(OR(AO126<0,L126="FBA海运"),"","渠道") -> 渠道 | D126: =ROUND(IF(AND(AO126>=0,Y126="正常走货"),_xlfn.XLOOKUP(G126,过机服务商重量差!A:A,过机服务商重量差!L:L),"0"),2) -> 1 | E126: =ROUND(IF(B126="小旋风",$D126/提成!$D$4*提成!$E$4,$D126/提成!$D$3*提成!$E$3),2) -> 0.01 | F126: =IFERROR(LOOKUP(1,0/((B126=名单!B:B)*(VALUE(AW126)>=名单!E:E)*(VALUE(AW126)<=名单!G:G)*(Y126="正常走货")),名单!H:H),"否") -> 否 | G126: FCO0018 | H126: 398309492050 | J126: YF-联邦包税小包 | L126: 非主营 | S126: 李可 | T126: 营销四部 | Y126: 正常走货 | AO126: 102 | AW126: 2026-01-31 16:31:06
A127: =MID(AW127,1,7) -> 2026-01 | B127: =_xlfn.XLOOKUP(G127,过机服务商重量差!A:A,过机服务商重量差!G:G) -> 玉麒麟 | C127: =IF(OR(AO127<0,L127="FBA海运"),"","渠道") -> 渠道 | D127: =ROUND(IF(AND(AO127>=0,Y127="正常走货"),_xlfn.XLOOKUP(G127,过机服务商重量差!A:A,过机服务商重量差!L:L),"0"),2) -> 1 | E127: =ROUND(IF(B127="小旋风",$D127/提成!$D$4*提成!$E$4,$D127/提成!$D$3*提成!$E$3),2) -> 0.01 | F127: =IFERROR(LOOKUP(1,0/((B127=名单!B:B)*(VALUE(AW127)>=名单!E:E)*(VALUE(AW127)<=名单!G:G)*(Y127="正常走货")),名单!H:H),"否") -> 否 | G127: LEKE29318 | H127: 398310485636 | J127: OK-FDX-DHL-TNT | L127: 非主营 | S127: 宋海周 | T127: 营销二部 | Y127: 正常走货 | AO127: 44.6 | AW127: 2026-01-31 16:30:52
A128: =MID(AW128,1,7) -> 2026-01 | B128: =_xlfn.XLOOKUP(G128,过机服务商重量差!A:A,过机服务商重量差!G:G) -> 无崖子 | C128: =IF(OR(AO128<0,L128="FBA海运"),"","渠道") -> 渠道 | D128: =ROUND(IF(AND(AO128>=0,Y128="正常走货"),_xlfn.XLOOKUP(G128,过机服务商重量差!A:A,过机服务商重量差!L:L),"0"),2) -> 1 | E128: =ROUND(IF(B128="小旋风",$D128/提成!$D$4*提成!$E$4,$D128/提成!$D$3*提成!$E$3),2) -> 0.01 | F128: =IFERROR(LOOKUP(1,0/((B128=名单!B:B)*(VALUE(AW128)>=名单!E:E)*(VALUE(AW128)<=名单!G:G)*(Y128="正常走货")),名单!H:H),"否") -> 否 | G128: BLS01307200 | H128: 1Z80F20X0423193076 | J128: FedEx-通用渠道 | L128: 非主营 | S128: 高雨晴 | T128: 营销二部 | Y128: 正常走货 | AO128: 133.67 | AW128: 2026-01-31 16:30:47
A129: =MID(AW129,1,7) -> 2026-01 | B129: =_xlfn.XLOOKUP(G129,过机服务商重量差!A:A,过机服务商重量差!G:G) -> 玉麒麟 | C129: =IF(OR(AO129<0,L129="FBA海运"),"","渠道") -> 渠道 | D129: =ROUND(IF(AND(AO129>=0,Y129="正常走货"),_xlfn.XLOOKUP(G129,过机服务商重量差!A:A,过机服务商重量差!L:L),"0"),2) -> 1 | E129: =ROUND(IF(B129="小旋风",$D129/提成!$D$4*提成!$E$4,$D129/提成!$D$3*提成!$E$3),2) -> 0.01 | F129: =IFERROR(LOOKUP(1,0/((B129=名单!B:B)*(VALUE(AW129)>=名单!E:E)*(VALUE(AW129)<=名单!G:G)*(Y129="正常走货")),名单!H:H),"否") -> 否 | G129: SHANELGORIAL26131-1 | H129: 1Z0E620D0405399626 | J129: OK-FDX-DHL-TNT | L129: 非主营 | S129: 丁佳伟 | T129: 营销三部 | Y129: 正常走货 | AO129: 78.93 | AW129: 2026-01-31 16:25:09
A130: =MID(AW130,1,7) -> 2026-01 | B130: =_xlfn.XLOOKUP(G130,过机服务商重量差!A:A,过机服务商重量差!G:G) -> 风清扬 | C130: =IF(OR(AO130<0,L130="FBA海运"),"","渠道") -> 渠道 | D130: =ROUND(IF(AND(AO130>=0,Y130="正常走货"),_xlfn.XLOOKUP(G130,过机服务商重量差!A:A,过机服务商重量差!L:L),"0"),2) -> 308 | E130: =ROUND(IF(B130="小旋风",$D130/提成!$D$4*提成!$E$4,$D130/提成!$D$3*提成!$E$3),2) -> 3.08 | F130: =IFERROR(LOOKUP(1,0/((B130=名单!B:B)*(VALUE(AW130)>=名单!E:E)*(VALUE(AW130)<=名单!G:G)*(Y130="正常走货")),名单!H:H),"否") -> 是 | G130: FBA19751BCG3 | H130: KP | J130: 加拿大海派-JY | L130: 非主营 | S130: 陈兵 | T130: 营销一部 | Y130: 正常走货 | AO130: 1047.2 | AW130: 2026-01-31 16:15:10
A131: =MID(AW131,1,7) -> 2026-01 | B131: =_xlfn.XLOOKUP(G131,过机服务商重量差!A:A,过机服务商重量差!G:G) -> 帅时莹 | C131: =IF(OR(AO131<0,L131="FBA海运"),"","渠道") -> 渠道 | D131: =ROUND(IF(AND(AO131>=0,Y131="正常走货"),_xlfn.XLOOKUP(G131,过机服务商重量差!A:A,过机服务商重量差!L:L),"0"),2) -> 2.5 | E131: =ROUND(IF(B131="小旋风",$D131/提成!$D$4*提成!$E$4,$D131/提成!$D$3*提成!$E$3),2) -> 0.03 | F131: =IFERROR(LOOKUP(1,0/((B131=名单!B:B)*(VALUE(AW131)>=名单!E:E)*(VALUE(AW131)<=名单!G:G)*(Y131="正常走货")),名单!H:H),"否") -> 否 | G131: CN260131-US-46806 | H131: 398309523280 | J131: YF-联邦包税小包 | L131: 非主营 | S131: 朱杰 | T131: 营销四部 | Y131: 正常走货 | AO131: 76 | AW131: 2026-01-31 16:06:49
A132: =MID(AW132,1,7) -> 2026-01 | B132: =_xlfn.XLOOKUP(G132,过机服务商重量差!A:A,过机服务商重量差!G:G) -> 帅时莹 | C132: =IF(OR(AO132<0,L132="FBA海运"),"","渠道") -> 渠道 | D132: =ROUND(IF(AND(AO132>=0,Y132="正常走货"),_xlfn.XLOOKUP(G132,过机服务商重量差!A:A,过机服务商重量差!L:L),"0"),2) -> 2.5 | E132: =ROUND(IF(B132="小旋风",$D132/提成!$D$4*提成!$E$4,$D132/提成!$D$3*提成!$E$3),2) -> 0.03 | F132: =IFERROR(LOOKUP(1,0/((B132=名单!B:B)*(VALUE(AW132)>=名单!E:E)*(VALUE(AW132)<=名单!G:G)*(Y132="正常走货")),名单!H:H),"否") -> 否 | G132: CN260131-US-52552 | H132: 398309602860 | J132: YF-联邦包税小包 | L132: 非主营 | S132: 朱杰 | T132: 营销四部 | Y132: 正常走货 | AO132: 76 | AW132: 2026-01-31 16:06:40
A133: =MID(AW133,1,7) -> 2026-01 | B133: =_xlfn.XLOOKUP(G133,过机服务商重量差!A:A,过机服务商重量差!G:G) -> 帅时莹 | C133: =IF(OR(AO133<0,L133="FBA海运"),"","渠道") -> 渠道 | D133: =ROUND(IF(AND(AO133>=0,Y133="正常走货"),_xlfn.XLOOKUP(G133,过机服务商重量差!A:A,过机服务商重量差!L:L),"0"),2) -> 3 | E133: =ROUND(IF(B133="小旋风",$D133/提成!$D$4*提成!$E$4,$D133/提成!$D$3*提成!$E$3),2) -> 0.03 | F133: =IFERROR(LOOKUP(1,0/((B133=名单!B:B)*(VALUE(AW133)>=名单!E:E)*(VALUE(AW133)<=名单!G:G)*(Y133="正常走货")),名单!H:H),"否") -> 否 | G133: CN260131-US-33778 | H133: 398309593703 | J133: YF-联邦包税小包 | L133: 非主营 | S133: 朱杰 | T133: 营销四部 | Y133: 正常走货 | AO133: 46 | AW133: 2026-01-31 16:06:34
... A154: =MID(AW154,1,7) -> 2026-01 | B154: =_xlfn.XLOOKUP(G154,过机服务商重量差!A:A,过机服务商重量差!G:G) -> 帅时莹 | C154: =IF(OR(AO154<0,L154="FBA海运"),"","渠道") -> 渠道 | D154: =ROUND(IF(AND(AO154>=0,Y154="正常走货"),_xlfn.XLOOKUP(G154,过机服务商重量差!A:A,过机服务商重量差!L:L),"0"),2) -> 10 | E154: =ROUND(IF(B154="小旋风",$D154/提成!$D$4*提成!$E$4,$D154/提成!$D$3*提成!$E$3),2) -> 0.1 | F154: =IFERROR(LOOKUP(1,0/((B154=名单!B:B)*(VALUE(AW154)>=名单!E:E)*(VALUE(AW154)<=名单!G:G)*(Y154="正常走货")),名单!H:H),"否") -> 否 | G154: JT0131-1 | H154: 1Z0E793D6704433474 | J154: MSHQ-UPS | L154: 非主营 | S154: 王涛 | T154: 营销四部 | Y154: 正常走货 | AO154: 86.35 | AW154: 2026-01-31 15:33:10
A155: =MID(AW155,1,7) -> 2026-01 | B155: =_xlfn.XLOOKUP(G155,过机服务商重量差!A:A,过机服务商重量差!G:G) -> 无崖子 | C155: =IF(OR(AO155<0,L155="FBA海运"),"","渠道") -> 渠道 | D155: =ROUND(IF(AND(AO155>=0,Y155="正常走货"),_xlfn.XLOOKUP(G155,过机服务商重量差!A:A,过机服务商重量差!L:L),"0"),2) -> 0 | E155: =ROUND(IF(B155="小旋风",$D155/提成!$D$4*提成!$E$4,$D155/提成!$D$3*提成!$E$3),2) -> 0 | F155: =IFERROR(LOOKUP(1,0/((B155=名单!B:B)*(VALUE(AW155)>=名单!E:E)*(VALUE(AW155)<=名单!G:G)*(Y155="正常走货")),名单!H:H),"否") -> 否 | G155: YKZXX013101 | J155: 义乌联邦IE-包税 | L155: 非主营 | S155: 张小雪 | T155: 营销五部 | Y155: 已退件 | AO155: 0 | AW155: 2026-01-31 15:33:00
A156: =MID(AW156,1,7) -> 2026-01 | B156: =_xlfn.XLOOKUP(G156,过机服务商重量差!A:A,过机服务商重量差!G:G) -> 风清扬 | C156: =IF(OR(AO156<0,L156="FBA海运"),"","渠道") -> 渠道 | D156: =ROUND(IF(AND(AO156>=0,Y156="正常走货"),_xlfn.XLOOKUP(G156,过机服务商重量差!A:A,过机服务商重量差!L:L),"0"),2) -> 72 | E156: =ROUND(IF(B156="小旋风",$D156/提成!$D$4*提成!$E$4,$D156/提成!$D$3*提成!$E$3),2) -> 0.72 | F156: =IFERROR(LOOKUP(1,0/((B156=名单!B:B)*(VALUE(AW156)>=名单!E:E)*(VALUE(AW156)<=名单!G:G)*(Y156="正常走货")),名单!H:H),"否") -> 是 | G156: HZHF0037 | H156: 1ZHF34022038229695 | J156: 加拿大海派-JY | L156: 非主营 | S156: 叶伟明 | T156: 营销一部 | Y156: 正常走货 | AO156: 36 | AW156: 2026-01-31 15:32:33
A157: =MID(AW157,1,7) -> 2026-01 | B157: =_xlfn.XLOOKUP(G157,过机服务商重量差!A:A,过机服务商重量差!G:G) -> 玉麒麟 | C157: =IF(OR(AO157<0,L157="FBA海运"),"","渠道") -> 渠道 | D157: =ROUND(IF(AND(AO157>=0,Y157="正常走货"),_xlfn.XLOOKUP(G157,过机服务商重量差!A:A,过机服务商重量差!L:L),"0"),2) -> 3.5 | E157: =ROUND(IF(B157="小旋风",$D157/提成!$D$4*提成!$E$4,$D157/提成!$D$3*提成!$E$3),2) -> 0.04 | F157: =IFERROR(LOOKUP(1,0/((B157=名单!B:B)*(VALUE(AW157)>=名单!E:E)*(VALUE(AW157)<=名单!G:G)*(Y157="正常走货")),名单!H:H),"否") -> 否 | G157: CX-128879 | H157: 1Z33W2600493890928 | J157: OK-FDX-DHL-TNT | L157: 非主营 | S157: 江伟成 | T157: 营销二部 | Y157: 正常走货 | AO157: 90.8 | AW157: 2026-01-31 15:21:50
A158: =MID(AW158,1,7) -> 2026-01 | B158: =_xlfn.XLOOKUP(G158,过机服务商重量差!A:A,过机服务商重量差!G:G) -> 小旋风 | C158: =IF(OR(AO158<0,L158="FBA海运"),"","渠道") -> 渠道 | D158: =ROUND(IF(AND(AO158>=0,Y158="正常走货"),_xlfn.XLOOKUP(G158,过机服务商重量差!A:A,过机服务商重量差!L:L),"0"),2) -> 33 | E158: =ROUND(IF(B158="小旋风",$D158/提成!$D$4*提成!$E$4,$D158/提成!$D$3*提成!$E$3),2) -> 0.33 | F158: =IFERROR(LOOKUP(1,0/((B158=名单!B:B)*(VALUE(AW158)>=名单!E:E)*(VALUE(AW158)<=名单!G:G)*(Y158="正常走货")),名单!H:H),"否") -> 是 | G158: 260130GT-LISA3 | H158: 15504530331795 | J158: 英国空运普货DPD派 | L158: 非主营 | S158: 黄小丽 | T158: 营销四部 | Y158: 正常走货 | AO158: 2009 | AW158: 2026-01-31 15:13:43
A159: =MID(AW159,1,7) -> 2026-01 | B159: =_xlfn.XLOOKUP(G159,过机服务商重量差!A:A,过机服务商重量差!G:G) -> 玉麒麟 | C159: =IF(OR(AO159<0,L159="FBA海运"),"","渠道") -> 渠道 | D159: =ROUND(IF(AND(AO159>=0,Y159="正常走货"),_xlfn.XLOOKUP(G159,过机服务商重量差!A:A,过机服务商重量差!L:L),"0"),2) -> 15.5 | E159: =ROUND(IF(B159="小旋风",$D159/提成!$D$4*提成!$E$4,$D159/提成!$D$3*提成!$E$3),2) -> 0.16 | F159: =IFERROR(LOOKUP(1,0/((B159=名单!B:B)*(VALUE(AW159)>=名单!E:E)*(VALUE(AW159)<=名单!G:G)*(Y159="正常走货")),名单!H:H),"否") -> 否 | G159: QY26-0131ER01 | H159: 500745745216 | J159: OK-UPS蓝单 | L159: 非主营 | S159: 王志军 | T159: 营销四部 | Y159: 正常走货 | AO159: 106 | AW159: 2026-01-31 15:09:39
A160: =MID(AW160,1,7) -> 2026-01 | B160: =_xlfn.XLOOKUP(G160,过机服务商重量差!A:A,过机服务商重量差!G:G) -> 无崖子 | C160: =IF(OR(AO160<0,L160="FBA海运"),"","渠道") -> 渠道 | D160: =ROUND(IF(AND(AO160>=0,Y160="正常走货"),_xlfn.XLOOKUP(G160,过机服务商重量差!A:A,过机服务商重量差!L:L),"0"),2) -> 30 | E160: =ROUND(IF(B160="小旋风",$D160/提成!$D$4*提成!$E$4,$D160/提成!$D$3*提成!$E$3),2) -> 0.3 | F160: =IFERROR(LOOKUP(1,0/((B160=名单!B:B)*(VALUE(AW160)>=名单!E:E)*(VALUE(AW160)<=名单!G:G)*(Y160="正常走货")),名单!H:H),"否") -> 否 | G160: AQ26131-2 | H160: 1ZX30Y730491475360 | J160: 义乌UPS红单直发包税/6000 | L160: 非主营 | S160: 丁佳伟 | T160: 营销三部 | Y160: 正常走货 | AO160: 0.4 | AW160: 2026-01-31 14:59:26
A161: =MID(AW161,1,7) -> 2026-01 | B161: =_xlfn.XLOOKUP(G161,过机服务商重量差!A:A,过机服务商重量差!G:G) -> 玉麒麟 | C161: =IF(OR(AO161<0,L161="FBA海运"),"","渠道") -> 渠道 | D161: =ROUND(IF(AND(AO161>=0,Y161="正常走货"),_xlfn.XLOOKUP(G161,过机服务商重量差!A:A,过机服务商重量差!L:L),"0"),2) -> 34 | E161: =ROUND(IF(B161="小旋风",$D161/提成!$D$4*提成!$E$4,$D161/提成!$D$3*提成!$E$3),2) -> 0.34 | F161: =IFERROR(LOOKUP(1,0/((B161=名单!B:B)*(VALUE(AW161)>=名单!E:E)*(VALUE(AW161)<=名单!G:G)*(Y161="正常走货")),名单!H:H),"否") -> 否 | G161: BJC260131-2JP | H161: 1Z762E4V0419177464 | J161: OK-FDX-DHL-TNT | L161: 非主营 | S161: 张博 | T161: 营销三部 | Y161: 正常走货 | AO161: 199.6 | AW161: 2026-01-31 14:57:58
A162: =MID(AW162,1,7) -> 2026-01 | B162: =_xlfn.XLOOKUP(G162,过机服务商重量差!A:A,过机服务商重量差!G:G) -> 帅时莹 | C162: =IF(OR(AO162<0,L162="FBA海运"),"","渠道") -> 渠道 | D162: =ROUND(IF(AND(AO162>=0,Y162="正常走货"),_xlfn.XLOOKUP(G162,过机服务商重量差!A:A,过机服务商重量差!L:L),"0"),2) -> 32 | E162: =ROUND(IF(B162="小旋风",$D162/提成!$D$4*提成!$E$4,$D162/提成!$D$3*提成!$E$3),2) -> 0.32 | F162: =IFERROR(LOOKUP(1,0/((B162=名单!B:B)*(VALUE(AW162)>=名单!E:E)*(VALUE(AW162)<=名单!G:G)*(Y162="正常走货")),名单!H:H),"否") -> 否 | G162: LG26-0131RT01 | H162: 1Z0E793D0410608794 | J162: MSHQ-UPS | L162: 非主营 | S162: 王志军 | T162: 营销四部 | Y162: 正常走货 | AO162: 313.99 | AW162: 2026-01-31 14:54:05
A163: =MID(AW163,1,7) -> 2026-01 | B163: =_xlfn.XLOOKUP(G163,过机服务商重量差!A:A,过机服务商重量差!G:G) -> 玉麒麟 | C163: =IF(OR(AO163<0,L163="FBA海运"),"","渠道") -> 渠道 | D163: =ROUND(IF(AND(AO163>=0,Y163="正常走货"),_xlfn.XLOOKUP(G163,过机服务商重量差!A:A,过机服务商重量差!L:L),"0"),2) -> 6.5 | E163: =ROUND(IF(B163="小旋风",$D163/提成!$D$4*提成!$E$4,$D163/提成!$D$3*提成!$E$3),2) -> 0.07 | F163: =IFERROR(LOOKUP(1,0/((B163=名单!B:B)*(VALUE(AW163)>=名单!E:E)*(VALUE(AW163)<=名单!G:G)*(Y163="正常走货")),名单!H:H),"否") -> 否 | G163: 3KOLEDH98 | H163: 1Z4W260E0409563686 | J163: OK-FDX-DHL-TNT | L163: 非主营 | S163: 王岩岩 | T163: 营销四部 | Y163: 正常走货 | AO163: 226.4 | AW163: 2026-01-31 14:52:51
A164: =MID(AW164,1,7) -> 2026-01 | B164: =_xlfn.XLOOKUP(G164,过机服务商重量差!A:A,过机服务商重量差!G:G) -> 无崖子 | C164: =IF(OR(AO164<0,L164="FBA海运"),"","渠道") -> 渠道 | D164: =ROUND(IF(AND(AO164>=0,Y164="正常走货"),_xlfn.XLOOKUP(G164,过机服务商重量差!A:A,过机服务商重量差!L:L),"0"),2) -> 13.5 | E164: =ROUND(IF(B164="小旋风",$D164/提成!$D$4*提成!$E$4,$D164/提成!$D$3*提成!$E$3),2) -> 0.14 | F164: =IFERROR(LOOKUP(1,0/((B164=名单!B:B)*(VALUE(AW164)>=名单!E:E)*(VALUE(AW164)<=名单!G:G)*(Y164="正常走货")),名单!H:H),"否") -> 否 | G164: 260130HJ-JC1 | H164: 1Z0E64G86718962126 | J164: HST-UPS 6000 | L164: 非主营 | S164: 黄小丽 | T164: 营销四部 | Y164: 正常走货 | AO164: 186.21 | AW164: 2026-01-31 14:51:55
...

Sheet 名单
B1: 客服系统名 | C1: 姓名 | D1: 入职时间 | E1: 提成计算开始日期 | F1: 结束日期（手填） | G1: 结束日期 | H1: 是否计算提成
B2: 无崖子 | C2: 陈巧玲 | E2: 45078 | F2: 45716 | G2: =IF(F2="",TODAY(),F2) -> 45716 | H2: 否
B3: 霹雳火-快递客服(杨帆) | C3: 杨帆 | E3: 45123 | F3: 45276 | G3: =IF(F3="",TODAY(),F3) -> 45276 | H3: 否
B4: 风清扬 | C4: 陈晓密 | E4: 45748 | G4: =IF(F4="",TODAY(),F4) -> 46091 | H4: 是
B5: 小旋风 | C5: 吴敏洁 | E5: 45748 | G5: =IF(F5="",TODAY(),F5) -> 46091 | H5: 是

Sheet 提成标准
N2: 渠道 | O2: 中转状态 | Q2: 大于等于 | R2: 小于 | S2: 取数 | T2: 单位 | U2: 提成系数（元） | V2: 截止到2023.12.14（其中杨帆的是到离职日16日）
B3: 中转状态 | F3: 取数 | G3: 单位 | H3: 提成系数（元） | I3: 2025.4.1开始 | N3: 快递 | O3: 正常走货 | P3: 快递小货 | Q3: 0 | R3: 21 | S3: 1 | T3: 票 | U3: 2 | V3: 2元/票
B4: 正常走货 | D4: 0 | E4: 100000 | F4: 出货计费重 | G4: KG | H4: 0.01 | I4: 0.01元/KG | N4: 快递 | O4: 正常走货 | P4: 快递大货 | Q4: 21 | R4: 99999 | S4: 出货计费重 | T4: KG | U4: 0.2 | V4: 0.2元/KG
B5: 正常走货 | D5: 100000 | E5: 150000 | F5: 出货计费重 | G5: KG | H5: 0.015 | I5: 0.015元/KG | N5: 专线 | O5: 正常走货 | P5: 专线 | S5: 出货计费重 | T5: KG | U5: 0.1 | V5: 0.1元/KG
B6: 正常走货 | D6: 150000 | E6: 200000 | F6: 出货计费重 | G6: KG | H6: 0.02 | I6: 0.02元/KG | N6: 主营产品 | P6: 主营产品 | U6: 0
B7: 正常走货 | D7: 200000 | E7: 300000 | F7: 出货计费重 | G7: KG | H7: 0.025 | I7: 0.025元/KG
B8: 正常走货 | D8: 300000 | E8: 999999999 | F8: 出货计费重 | G8: KG | H8: 0.035 | I8: 0.035元/KG | N8: 渠道 | O8: 中转状态 | Q8: 大于等于 | R8: 小于 | S8: 取数 | T8: 单位 | U8: 提成系数（元） | V8: 2023.12.15开始
A9: 阶段性的，例如：3月负责线路收货吨数133吨，则提成计算公式为 | N9: 快递 | O9: 正常走货 | P9: 快递小货 | Q9: 0 | R9: 21 | S9: 1 | T9: 票 | U9: 2 | V9: 2元/票
B10: 100000*0.01)+(133000-100000)*0.015=1495元 | N10: 快递 | O10: 正常走货 | P10: 快递大货 | Q10: 21 | R10: 99999 | S10: 出货计费重 | T10: KG | U10: 0.1 | V10: 0.1元/KG
N11: 专线 | O11: 正常走货 | P11: 专线 | S11: 出货计费重 | T11: KG | U11: 0.1 | V11: 0.1元/KG
C12: 出货计费重KG | D12: 提成系数（元） | N12: 主营产品 | P12: 主营产品 | U12: 0
C13: 0 | D13: 0.01 | E13: 0
C14: 100000 | D14: 0.015 | E14: =C14*(D14-D13) -> 500
C15: 150000 | D15: 0.02 | E15: =E14+C15*(D15-D14) -> 1250
C16: 200000 | D16: 0.025 | E16: =E15+C16*(D16-D15) -> 2250
C17: 300000 | D17: 0.035 | E17: =E16+C17*(D17-D16) -> 5250

Sheet 特殊事项扣除
A1: 扣除期间 | B1: 客服名 | C1: 扣除金额 | D1: 单号期间 | E1: 备注 | F1: 单号
A2: 2023-07 | B2: 霹雳火-快递客服(杨帆) | C2: 724.12 | D2: 45110 | F2: TJ01532 | G2: =_xlfn.DISPIMG("ID_9F528AFC3D734C0F93B5BDB826E0677E",1) -> =DISPIMG("ID_9F528AFC3D734C0F93B5BDB826E0677E",1)
A3: 2023-08 | B3: 霹雳火-快递客服(杨帆) | C3: 0.7
A4: 2023-08 | B4: 霹雳火-快递客服(杨帆) | C4: 0.7
A5: 2023-08 | B5: 霹雳火-快递客服(杨帆) | C5: 0.71
A6: 2023-08 | B6: 霹雳火-快递客服(杨帆) | C6: 8.27
A7: 2023-08 | B7: 霹雳火-快递客服(杨帆) | C7: 14.68
A8: 2023-08 | B8: 霹雳火-快递客服(杨帆) | C8: 0.01
A9: 2023-08 | B9: 霹雳火-快递客服(杨帆) | C9: 10.69
A10: 2023-08 | B10: 霹雳火-快递客服(杨帆) | C10: 10.69
A11: 2023-08 | B11: 霹雳火-快递客服(杨帆) | C11: 13.35
A12: 2023-08 | B12: 霹雳火-快递客服(杨帆) | C12: 0.01
A13: 2023-08 | B13: 霹雳火-快递客服(杨帆) | C13: 12.69
A14: 2023-08 | B14: 霹雳火-快递客服(杨帆) | C14: 11.35
... A79: 2023-08 | B79: 霹雳火-快递客服(杨帆) | C79: 17.43

Sheet 提成
A1: 渠道客服提成明细表 | H1: 不含渠道毛利负的
A2: 客服系统名 | B2: 姓名 | C2: 期间 | D2: 渠道 正常走货 出货计费重/KG | E2: 应发提成 | F2: 特殊事项扣除 | G2: 实发 提成 | H2: 公账 | I2: 私账
A3: 风清扬 | B3: 陈晓密 | C3: =业务员明细!$F$1 -> 2026-01 | D3: =ROUND(SUMIFS(业务数据统计!$D:$D,业务数据统计!$B:$B,$A3,业务数据统计!C:C,"渠道"),2) -> 96422 | E3: {=ROUND(LOOKUP(1,0/(D3>提成标准!$C$13:$C$17),提成标准!$D$13:$D$17)*D3-LOOKUP(1,0/(D3>提成标准!$C$13:$C$17),提成标准!$E$13:$E$17),2)} -> 964.22 | F3: =SUMIFS(特殊事项扣除!C:C,特殊事项扣除!A:A,C3,特殊事项扣除!B:B,A3) -> 0 | G3: =E3-F3 -> 964.22
A4: 小旋风 | B4: 吴敏洁 | C4: =业务员明细!$F$1 -> 2026-01 | D4: =ROUND(SUMIFS(业务数据统计!$D:$D,业务数据统计!$B:$B,$A4,业务数据统计!C:C,"渠道"),2) -> 67429.11 | E4: {=ROUND(LOOKUP(1,0/(D4>提成标准!$C$13:$C$17),提成标准!$D$13:$D$17)*D4-LOOKUP(1,0/(D4>提成标准!$C$13:$C$17),提成标准!$E$13:$E$17),2)} -> 674.29 | F4: =SUMIFS(特殊事项扣除!C:C,特殊事项扣除!A:A,C4,特殊事项扣除!B:B,A4) -> 0 | G4: =E4-F4 -> 674.29
A5: 合计： | D5: =SUM(D3:D4) -> 163851.11 | E5: =SUM(E3:E4) -> 1638.51 | F5: =SUM(F3:F4) -> 0 | G5: =SUM(G3:G4) -> 1638.51
F7: 制表人：

Sheet 业务员明细
A1: 渠道客服提成明细表（业务员承担） | F1: 2026-01
A2: 系统名 | B2: 部门 | C2: 运单期间 | D2: 承担金额 | E2: 部门
A3: 马淞浦 | B3: =_xlfn.XLOOKUP(E3,部门!A:A,部门!B:B) -> 销售一部 | C3: =$F$1 -> 2026-01 | D3: =SUMIFS(业务数据统计!E:E,业务数据统计!S:S,A3,业务数据统计!F:F,"是")+0.2 -> 129.49 | E3: =_xlfn.XLOOKUP(A3,业务数据统计!S:S,业务数据统计!T:T,"") -> 营销一部
A4: 朱杰 | B4: =_xlfn.XLOOKUP(E4,部门!A:A,部门!B:B) -> 销售四部 | C4: =$F$1 -> 2026-01 | D4: =SUMIFS(业务数据统计!E:E,业务数据统计!S:S,A4,业务数据统计!F:F,"是") -> 105.48 | E4: =_xlfn.XLOOKUP(A4,业务数据统计!S:S,业务数据统计!T:T,"") -> 营销四部 | G4: 销售一部 | H4: =SUMIFS(D:D,B:B,G4) -> 267.9
A5: 陈炎 | B5: =_xlfn.XLOOKUP(E5,部门!A:A,部门!B:B) -> 销售二部 | C5: =$F$1 -> 2026-01 | D5: =SUMIFS(业务数据统计!E:E,业务数据统计!S:S,A5,业务数据统计!F:F,"是") -> 90.53 | E5: =_xlfn.XLOOKUP(A5,业务数据统计!S:S,业务数据统计!T:T,"") -> 营销二部 | G5: 销售四部 | H5: =SUMIFS(D:D,B:B,G5) -> 312.11
A6: 王拥 | B6: =_xlfn.XLOOKUP(E6,部门!A:A,部门!B:B) -> 销售二部 | C6: =$F$1 -> 2026-01 | D6: =SUMIFS(业务数据统计!E:E,业务数据统计!S:S,A6,业务数据统计!F:F,"是") -> 66.14 | E6: =_xlfn.XLOOKUP(A6,业务数据统计!S:S,业务数据统计!T:T,"") -> 营销二部 | G6: 销售二部 | H6: =SUMIFS(D:D,B:B,G6) -> 322.22
A7: 邓健群 | B7: =_xlfn.XLOOKUP(E7,部门!A:A,部门!B:B) -> 销售三部 | C7: =$F$1 -> 2026-01 | D7: =SUMIFS(业务数据统计!E:E,业务数据统计!S:S,A7,业务数据统计!F:F,"是") -> 53.6 | E7: =_xlfn.XLOOKUP(A7,业务数据统计!S:S,业务数据统计!T:T,"") -> 营销三部 | G7: 销售三部 | H7: =SUMIFS(D:D,B:B,G7) -> 268.83
A8: 陈兵 | B8: =_xlfn.XLOOKUP(E8,部门!A:A,部门!B:B) -> 销售一部 | C8: =$F$1 -> 2026-01 | D8: =SUMIFS(业务数据统计!E:E,业务数据统计!S:S,A8,业务数据统计!F:F,"是") -> 51.23 | E8: =_xlfn.XLOOKUP(A8,业务数据统计!S:S,业务数据统计!T:T,"") -> 营销一部 | G8: 宁波 | H8: =SUMIFS(D:D,B:B,G8) -> 89.42
A9: 周志宇 | B9: =_xlfn.XLOOKUP(E9,部门!A:A,部门!B:B) -> 宁波 | C9: =$F$1 -> 2026-01 | D9: =SUMIFS(业务数据统计!E:E,业务数据统计!S:S,A9,业务数据统计!F:F,"是") -> 47.54 | E9: =_xlfn.XLOOKUP(A9,业务数据统计!S:S,业务数据统计!T:T,"") -> 宁波销售一部 | G9: 销售五部 | H9: =SUMIFS(D:D,B:B,G9) -> 226.95
A10: 陈巧玲 | B10: =_xlfn.XLOOKUP(E10,部门!A:A,部门!B:B) -> 销售三部 | C10: =$F$1 -> 2026-01 | D10: =SUMIFS(业务数据统计!E:E,业务数据统计!S:S,A10,业务数据统计!F:F,"是") -> 46.21 | E10: =_xlfn.XLOOKUP(A10,业务数据统计!S:S,业务数据统计!T:T,"") -> 营销三部 | G10: 厦门 | H10: =SUMIFS(D:D,B:B,G10) -> 30.43
A11: 李凤 | B11: =_xlfn.XLOOKUP(E11,部门!A:A,部门!B:B) -> 销售四部 | C11: =$F$1 -> 2026-01 | D11: =SUMIFS(业务数据统计!E:E,业务数据统计!S:S,A11,业务数据统计!F:F,"是") -> 45.19 | E11: =_xlfn.XLOOKUP(A11,业务数据统计!S:S,业务数据统计!T:T,"") -> 营销四部 | G11: 台州 | H11: =SUMIFS(D:D,B:B,G11) -> 32.24
A12: 冯青青 | B12: =_xlfn.XLOOKUP(E12,部门!A:A,部门!B:B) -> 销售五部 | C12: =$F$1 -> 2026-01 | D12: =SUMIFS(业务数据统计!E:E,业务数据统计!S:S,A12,业务数据统计!F:F,"是") -> 43.01 | E12: =_xlfn.XLOOKUP(A12,业务数据统计!S:S,业务数据统计!T:T,"") -> 营销五部 | G12: 福永 | H12: =SUMIFS(D:D,B:B,G12) -> 34.27
A13: 付乐航 | B13: =_xlfn.XLOOKUP(E13,部门!A:A,部门!B:B) -> 销售五部 | C13: =$F$1 -> 2026-01 | D13: =SUMIFS(业务数据统计!E:E,业务数据统计!S:S,A13,业务数据统计!F:F,"是") -> 39.19 | E13: =_xlfn.XLOOKUP(A13,业务数据统计!S:S,业务数据统计!T:T,"") -> 营销五部 | G13: 深圳 | H13: =SUMIFS(D:D,B:B,G13) -> 39.27
A14: 丁佳伟 | B14: =_xlfn.XLOOKUP(E14,部门!A:A,部门!B:B) -> 销售三部 | C14: =$F$1 -> 2026-01 | D14: =SUMIFS(业务数据统计!E:E,业务数据统计!S:S,A14,业务数据统计!F:F,"是") -> 37.72 | E14: =_xlfn.XLOOKUP(A14,业务数据统计!S:S,业务数据统计!T:T,"") -> 营销三部 | G14: 潍坊 | H14: =SUMIFS(D:D,B:B,G14) -> 8.57
A15: 李可 | B15: =_xlfn.XLOOKUP(E15,部门!A:A,部门!B:B) -> 销售四部 | C15: =$F$1 -> 2026-01 | D15: =SUMIFS(业务数据统计!E:E,业务数据统计!S:S,A15,业务数据统计!F:F,"是") -> 35.69 | E15: =_xlfn.XLOOKUP(A15,业务数据统计!S:S,业务数据统计!T:T,"") -> 营销四部 | G15: 杭州 | H15: =SUMIFS(D:D,B:B,G15) -> 4.74
A16: 徐建 | B16: =_xlfn.XLOOKUP(E16,部门!A:A,部门!B:B) -> 销售三部 | C16: =$F$1 -> 2026-01 | D16: =SUMIFS(业务数据统计!E:E,业务数据统计!S:S,A16,业务数据统计!F:F,"是") -> 33.98 | E16: =_xlfn.XLOOKUP(A16,业务数据统计!S:S,业务数据统计!T:T,"") -> 营销三部 | G16: 广州 | H16: =SUMIFS(D:D,B:B,G16) -> 1.56
A17: 陈颖 | B17: =_xlfn.XLOOKUP(E17,部门!A:A,部门!B:B) -> 销售五部 | C17: =$F$1 -> 2026-01 | D17: =SUMIFS(业务数据统计!E:E,业务数据统计!S:S,A17,业务数据统计!F:F,"是") -> 30.47 | E17: =_xlfn.XLOOKUP(A17,业务数据统计!S:S,业务数据统计!T:T,"") -> 营销五部
A18: 俞平 | B18: =_xlfn.XLOOKUP(E18,部门!A:A,部门!B:B) -> 厦门 | C18: =$F$1 -> 2026-01 | D18: =SUMIFS(业务数据统计!E:E,业务数据统计!S:S,A18,业务数据统计!F:F,"是") -> 30.43 | E18: =_xlfn.XLOOKUP(A18,业务数据统计!S:S,业务数据统计!T:T,"") -> 厦门销售一部
A19: 张俊合 | B19: =_xlfn.XLOOKUP(E19,部门!A:A,部门!B:B) -> 销售五部 | C19: =$F$1 -> 2026-01 | D19: =SUMIFS(业务数据统计!E:E,业务数据统计!S:S,A19,业务数据统计!F:F,"是") -> 29.43 | E19: =_xlfn.XLOOKUP(A19,业务数据统计!S:S,业务数据统计!T:T,"") -> 营销五部 | H19: =SUM(H4:H18) -> 1638.51
A20: 鞠敬伟 | B20: =_xlfn.XLOOKUP(E20,部门!A:A,部门!B:B) -> 销售三部 | C20: =$F$1 -> 2026-01 | D20: =SUMIFS(业务数据统计!E:E,业务数据统计!S:S,A20,业务数据统计!F:F,"是") -> 29.15 | E20: =_xlfn.XLOOKUP(A20,业务数据统计!S:S,业务数据统计!T:T,"") -> 营销三部 | H20: =提成!G5 -> 1638.51
A21: 何林霞 | B21: =_xlfn.XLOOKUP(E21,部门!A:A,部门!B:B) -> 销售二部 | C21: =$F$1 -> 2026-01 | D21: =SUMIFS(业务数据统计!E:E,业务数据统计!S:S,A21,业务数据统计!F:F,"是") -> 27.98 | E21: =_xlfn.XLOOKUP(A21,业务数据统计!S:S,业务数据统计!T:T,"") -> 营销二部 | H21: =H19-H20 -> 0
A22: 徐凌志 | B22: =_xlfn.XLOOKUP(E22,部门!A:A,部门!B:B) -> 宁波 | C22: =$F$1 -> 2026-01 | D22: =SUMIFS(业务数据统计!E:E,业务数据统计!S:S,A22,业务数据统计!F:F,"是") -> 27.67 | E22: =_xlfn.XLOOKUP(A22,业务数据统计!S:S,业务数据统计!T:T,"") -> 宁波销售一部
A23: 陈燚 | B23: =_xlfn.XLOOKUP(E23,部门!A:A,部门!B:B) -> 台州 | C23: =$F$1 -> 2026-01 | D23: =SUMIFS(业务数据统计!E:E,业务数据统计!S:S,A23,业务数据统计!F:F,"是") -> 26.68 | E23: =_xlfn.XLOOKUP(A23,业务数据统计!S:S,业务数据统计!T:T,"") -> 台州销售一部
A24: 王昌金 | B24: =_xlfn.XLOOKUP(E24,部门!A:A,部门!B:B) -> 销售一部 | C24: =$F$1 -> 2026-01 | D24: =SUMIFS(业务数据统计!E:E,业务数据统计!S:S,A24,业务数据统计!F:F,"是") -> 24.51 | E24: =_xlfn.XLOOKUP(A24,业务数据统计!S:S,业务数据统计!T:T,"") -> 营销一部
A25: 黄小丽 | B25: =_xlfn.XLOOKUP(E25,部门!A:A,部门!B:B) -> 销售四部 | C25: =$F$1 -> 2026-01 | D25: =SUMIFS(业务数据统计!E:E,业务数据统计!S:S,A25,业务数据统计!F:F,"是") -> 24.23 | E25: =_xlfn.XLOOKUP(A25,业务数据统计!S:S,业务数据统计!T:T,"") -> 营销四部
A26: 叶伟明 | B26: =_xlfn.XLOOKUP(E26,部门!A:A,部门!B:B) -> 销售一部 | C26: =$F$1 -> 2026-01 | D26: =SUMIFS(业务数据统计!E:E,业务数据统计!S:S,A26,业务数据统计!F:F,"是") -> 24.01 | E26: =_xlfn.XLOOKUP(A26,业务数据统计!S:S,业务数据统计!T:T,"") -> 营销一部
A27: 刘申奥 | B27: =_xlfn.XLOOKUP(E27,部门!A:A,部门!B:B) -> 销售五部 | C27: =$F$1 -> 2026-01 | D27: =SUMIFS(业务数据统计!E:E,业务数据统计!S:S,A27,业务数据统计!F:F,"是") -> 23.3 | E27: =_xlfn.XLOOKUP(A27,业务数据统计!S:S,业务数据统计!T:T,"") -> 营销五部
A28: 张小雪 | B28: =_xlfn.XLOOKUP(E28,部门!A:A,部门!B:B) -> 销售五部 | C28: =$F$1 -> 2026-01 | D28: =SUMIFS(业务数据统计!E:E,业务数据统计!S:S,A28,业务数据统计!F:F,"是") -> 22.71 | E28: =_xlfn.XLOOKUP(A28,业务数据统计!S:S,业务数据统计!T:T,"") -> 营销五部
A29: 王岩岩 | B29: =_xlfn.XLOOKUP(E29,部门!A:A,部门!B:B) -> 销售四部 | C29: =$F$1 -> 2026-01 | D29: =SUMIFS(业务数据统计!E:E,业务数据统计!S:S,A29,业务数据统计!F:F,"是") -> 21.34 | E29: =_xlfn.XLOOKUP(A29,业务数据统计!S:S,业务数据统计!T:T,"") -> 营销四部
A30: 李杰 | B30: =_xlfn.XLOOKUP(E30,部门!A:A,部门!B:B) -> 福永 | C30: =$F$1 -> 2026-01 | D30: =SUMIFS(业务数据统计!E:E,业务数据统计!S:S,A30,业务数据统计!F:F,"是") -> 20.97 | E30: =_xlfn.XLOOKUP(A30,业务数据统计!S:S,业务数据统计!T:T,"") -> 福永销售九部
A31: 左宗伟 | B31: =_xlfn.XLOOKUP(E31,部门!A:A,部门!B:B) -> 销售四部 | C31: =$F$1 -> 2026-01 | D31: =SUMIFS(业务数据统计!E:E,业务数据统计!S:S,A31,业务数据统计!F:F,"是") -> 20.93 | E31: =_xlfn.XLOOKUP(A31,业务数据统计!S:S,业务数据统计!T:T,"") -> 营销四部
A32: 江伟成 | B32: =_xlfn.XLOOKUP(E32,部门!A:A,部门!B:B) -> 销售二部 | C32: =$F$1 -> 2026-01 | D32: =SUMIFS(业务数据统计!E:E,业务数据统计!S:S,A32,业务数据统计!F:F,"是") -> 19.94 | E32: =_xlfn.XLOOKUP(A32,业务数据统计!S:S,业务数据统计!T:T,"") -> 营销二部
A33: 高雨晴 | B33: =_xlfn.XLOOKUP(E33,部门!A:A,部门!B:B) -> 销售二部 | C33: =$F$1 -> 2026-01 | D33: =SUMIFS(业务数据统计!E:E,业务数据统计!S:S,A33,业务数据统计!F:F,"是") -> 19.47 | E33: =_xlfn.XLOOKUP(A33,业务数据统计!S:S,业务数据统计!T:T,"") -> 营销二部
... A115: 于振康 | B115: =_xlfn.XLOOKUP(E115,部门!A:A,部门!B:B) -> 销售一部 | C115: =$F$1 -> 2026-01 | D115: =SUMIFS(业务数据统计!E:E,业务数据统计!S:S,A115,业务数据统计!F:F,"是") -> 0 | E115: =_xlfn.XLOOKUP(A115,业务数据统计!S:S,业务数据统计!T:T,"") -> 营销一部
A116: 合计： | D116: =SUM(D3:D115) -> 1638.51

Sheet 部门
A1: 业务员部门 | B1: 部门
A2: KA部-亮剑队 | B2: KA部
A3: KA部-一组长 | B3: KA部
A4: KA部-群英队 | B4: KA部
A5: 北苑-业务员 | B5: 北苑
A6: 北苑-业务员-陈伟 | B6: 北苑
A7: 北苑-业务员-冯玉勋 | B7: 北苑
A8: 广州分公司-业务员 | B8: 广州
A9: 广州分公司-业务员(曹深研) | B9: 广州
A10: 广州分公司-业务员(练思强) | B10: 广州
A11: 广州分公司-业务员(周源伟) | B11: 广州
A12: 广州分公司-业务员-马井贝 | B12: 广州
... A22: 深圳-业务员-刘薇 | B22: 深圳
A23: 深圳-直客-业务员 | B23: 深圳 | E23: 、
A24: 深圳-直客-坂田 | B24: 深圳
A25: 拓展部-飓风队 | B25: 拓展部-直客
A26: 吴慧俊
A27: 下王公司-业务员 | B27: 下王
A28: 下王公司-总经理 | B28: 下王
A29: 下王-业务员 | B29: 下王
A30: 销售二部-第一队 | B30: 营销二部
A31: 销售二部-昊阳队 | B31: 营销二部
A32: 销售二部-烈火队 | B32: 营销二部
A33: 销售二部-野狼队 | B33: 营销二部
A34: 销售三部-战狼队 | B34: 销售三部
A35: 销售三部-主管 | B35: 销售三部
A36: 销售一部-火箭队 | B36: 销售一部
A37: 销售一部-迈凯伦队 | B37: 销售一部
A38: 销售一部-王炸队 | B38: 销售一部
... A106: 四部KA客服 | B106: 销售四部
