Workbook

Sheet 过机服务商重量差
A1: 运单号 | B1: 服务商单号 | C1: 渠道转单号 | D1: 销售产品 | E1: 产品组 | F1: 服务渠道 | G1: 服务渠道客服 | H1: 客户简称 | I1: 业务员名称 | J1: 出货实重 | K1: 出货材积重 | L1: 出货计费重 | M1: 服务商计费重 | N1: 差值
A2: QS0131-MX | B2: ICBU00000932919 | C2: 1ZG3325W0416448603 | D2: OK-FDX-DHL-TNT | E2: 非主营 | F2: OK-FDX-DHL-TNT | G2: 玉麒麟 | I2: 小飞侠 | J2: 1.87 | K2: 4.059 | L2: 3.5 | M2: 4.5 | N2: 1
A3: TL0131-NL | B3: ICBU00000932943 | C3: 1Z4W260E0409673969 | D3: OK-UPS红单 | E3: 非主营 | F3: OK-UPS红单 | G3: 玉麒麟 | I3: 小飞侠 | J3: 9.23 | K3: 4.277 | L3: 9.5 | M3: 9.5 | N3: 0
A4: FBA15G65R8GW | B4: ICBU00000932665 | C4: RCD24000759946 | D4: 澳大利亚海派-包税 | E4: 非主营 | F4: 澳大利亚海派-包税 | G4: 小旋风 | I4: 高雨晴 | J4: 105.07 | K4: 0.654 | L4: 0.7 | M4: 0.8 | N4: 0.1
A5: FBA15G65P13K | B5: ICBU00000932701 | C5: RCD24000759947 | D5: 澳大利亚海派-包税 | E5: 非主营 | F5: 澳大利亚海派-包税 | G5: 小旋风 | I5: 高雨晴 | J5: 77.91 | K5: 0.647 | L5: 0.8 | M5: 0.8 | N5: 0
A6: SP260122021 | B6: ICBU00000933108 | D6: 欧洲海派-M | E6: 非主营 | F6: 欧洲海派-M | G6: 张诚 | I6: 马淞浦 | J6: 43.64 | K6: 35.783 | L6: 44 | M6: 44 | N6: 0
A7: SP260129024 | B7: ICBU00000933109 | D7: 欧洲海派-M | E7: 非主营 | F7: 欧洲海派-M | G7: 张诚 | I7: 马淞浦 | J7: 235.02 | K7: 201.12 | L7: 236 | M7: 236 | N7: 0
A8: SP260121227 | B8: ICBU00000933107 | D8: 欧洲海派-M | E8: 非主营 | F8: 欧洲海派-M | G8: 张诚 | I8: 马淞浦 | J8: 76.54 | K8: 55.296 | L8: 77 | M8: 77 | N8: 0
A9: SP260123008 | B9: ICBU00000933118 | D9: 欧洲海派-M | E9: 非主营 | F9: 欧洲海派-M | G9: 张诚 | I9: 马淞浦 | J9: 182.35 | K9: 157.348 | L9: 183 | M9: 183 | N9: 0
A10: SP260122003 | B10: ICBU00000933106 | D10: 欧洲海派-M | E10: 非主营 | F10: 欧洲海派-M | G10: 张诚 | I10: 马淞浦 | J10: 131.67 | K10: 103.47 | L10: 132 | M10: 132 | N10: 0
A11: SP260121220 | B11: ICBU00000932842 | C11: KP | D11: 加拿大海派-JY | E11: 非主营 | F11: 加拿大海派-JY | G11: 风清扬 | I11: 马淞浦 | J11: 66.78 | K11: 51.207 | L11: 67 | M11: 67 | N11: 0
A12: SP260120060 | B12: ICBU00000932975 | C12: KP | D12: 加拿大海派-JY | E12: 非主营 | F12: 加拿大海派-JY | G12: 风清扬 | I12: 马淞浦 | J12: 271.26 | K12: 187.498 | L12: 272 | M12: 272 | N12: 0
A13: SP260122050 | B13: ICBU00000932908 | C13: KP | D13: 加拿大海派-JY | E13: 非主营 | F13: 加拿大海派-JY | G13: 风清扬 | I13: 马淞浦 | J13: 136.99 | K13: 98.223 | L13: 138 | M13: 137 | N13: -1
A14: SP260122007 | B14: ICBU00000933117 | D14: 欧洲海派-M | E14: 非主营 | F14: 欧洲海派-M | G14: 张诚 | I14: 马淞浦 | J14: 124.82 | K14: 115.412 | L14: 125 | M14: 125 | N14: 0
A15: SP260121264 | B15: ICBU00000933138 | D15: 欧洲海派-M | E15: 非主营 | F15: 欧洲海派-M | G15: 张诚 | I15: 马淞浦 | J15: 233.25 | K15: 177.097 | L15: 234 | M15: 234 | N15: 0
A16: SP260121188 | B16: ICBU00000932970 | C16: KP | D16: 加拿大海派-JY | E16: 非主营 | F16: 加拿大海派-JY | G16: 风清扬 | I16: 马淞浦 | J16: 36.3 | K16: 28.373 | L16: 37 | M16: 37 | N16: 0
A17: SP260121174 | B17: ICBU00000932897 | C17: KP | D17: 加拿大海派-JY | E17: 非主营 | F17: 加拿大海派-JY | G17: 风清扬 | I17: 马淞浦 | J17: 25.91 | K17: 22.747 | L17: 26 | M17: 26 | N17: 0
A18: SP260121195 | B18: ICBU00000933111 | D18: 欧洲海派-M | E18: 非主营 | F18: 欧洲海派-M | G18: 张诚 | I18: 马淞浦 | J18: 40.95 | K18: 27.728 | L18: 41 | M18: 41 | N18: 0
A19: SP260121223 | B19: ICBU00000933110 | D19: 欧洲海派-M | E19: 非主营 | F19: 欧洲海派-M | G19: 张诚 | I19: 马淞浦 | J19: 312.72 | K19: 224.327 | L19: 313 | M19: 313 | N19: 0
A20: SP260120043-YYZ7-16 | B20: ICBU00000932894 | C20: KP | D20: 加拿大海派-JY | E20: 非主营 | F20: 加拿大海派-JY | G20: 风清扬 | I20: 马淞浦 | J20: 269 | K20: 200.901 | L20: 270 | M20: 269 | N20: -1
A21: SP260126064-YYZ7-38 | B21: ICBU00000932826 | C21: KP | D21: 加拿大海派-JY | E21: 非主营 | F21: 加拿大海派-JY | G21: 风清扬 | I21: 马淞浦 | J21: 730.44 | K21: 652.894 | L21: 732 | M21: 731 | N21: -1
A22: SP260112003 | B22: ICBU00000933121 | D22: 欧洲海派-M | E22: 非主营 | F22: 欧洲海派-M | G22: 张诚 | I22: 马淞浦 | J22: 633.45 | K22: 431.198 | L22: 634 | M22: 634 | N22: 0
A23: HCLSA0131-6 | B23: ICBU00000932498 | C23: TPL000134937 | D23: 澳大利亚海派-含税-SC | E23: 非主营 | F23: 澳大利亚海派-含税-SC | G23: 小旋风 | I23: 刘申奥 | J23: 36.48 | K23: 22.308 | L23: 37 | M23: 43 | N23: 6
A24: SP260121154 | B24: ICBU00000933112 | D24: 欧洲海派-M | E24: 非主营 | F24: 欧洲海派-M | G24: 张诚 | I24: 马淞浦 | J24: 502.74 | K24: 499.672 | L24: 503 | M24: 503 | N24: 0
A25: YKZXX013102 | B25: ICBU00000932200 | C25: 1ZA06B016832064447 | D25: 欧洲德国清专线 | E25: 非主营 | F25: 欧洲德国清专线 | G25: 小旋风 | I25: 张小雪 | J25: 51.07 | K25: 41.317 | L25: 52 | M25: 52 | N25: 0
A26: TM260131-1CA3 | B26: ICBU00000932388 | C26: 888386607575 | D26: OK-FDX-DHL-TNT | E26: 非主营 | F26: OK-FDX-DHL-TNT | G26: 玉麒麟 | I26: 邓健群 | J26: 0.72 | K26: 0 | L26: 1 | M26: 1 | N26: 0
A27: TM260131-2FR2 | B27: ICBU00000932359 | C27: 1ZA06B016818572639 | D27: 欧洲德国清专线 | E27: 非主营 | F27: 欧洲德国清专线 | G27: 小旋风 | I27: 邓健群 | J27: 29.31 | K27: 20.758 | L27: 30 | M27: 30 | N27: 0
A28: HH233M26 | B28: ICBU00000932242 | C28: 1ZF4K3596816247057 | D28: 欧洲专线-HMC | E28: 非主营 | F28: 欧洲专线-HMC | G28: 帅时莹 | I28: 李娟-业务 | J28: 189.88 | K28: 186.461 | L28: 208 | M28: 208 | N28: 0
A29: RSC3104 | B29: ICBU00000933165 | C29: 1Z0E465J0413832648 | D29: OK-FDX-DHL-TNT | E29: 非主营 | F29: OK-FDX-DHL-TNT | G29: 玉麒麟 | I29: 汪祺 | J29: 9.8 | K29: 6.919 | L29: 10 | M29: 10 | N29: 0
A30: RSC3103 | B30: ICBU00000933199 | C30: 1Z0E465J0419105235 | D30: OK-FDX-DHL-TNT | E30: 非主营 | F30: OK-FDX-DHL-TNT | G30: 玉麒麟 | I30: 汪祺 | J30: 9.83 | K30: 7.88 | L30: 10 | M30: 10 | N30: 0
A31: RSC3102 | B31: ICBU00000933162 | C31: 1Z0E465J0419058000 | D31: OK-FDX-DHL-TNT | E31: 非主营 | F31: OK-FDX-DHL-TNT | G31: 玉麒麟 | I31: 汪祺 | J31: 5.31 | K31: 4.997 | L31: 5.5 | M31: 5.5 | N31: 0
A32: RSC3101 | B32: ICBU00000933159 | C32: 1Z0E465J0415072448 | D32: OK-FDX-DHL-TNT | E32: 非主营 | F32: OK-FDX-DHL-TNT | G32: 玉麒麟 | I32: 汪祺 | J32: 6.37 | K32: 4.191 | L32: 6.5 | M32: 6.5 | N32: 0
A33: QLWJ1781704 | B33: ICBU00000932639 | C33: 1Z0E793D0422717448 | D33: OK-UPS红单 | E33: 非主营 | F33: OK-UPS红单 | G33: 玉麒麟 | I33: 宁春阳 | J33: 50.38 | K33: 52.836 | L33: 52 | M33: 56 | N33: 4
A34: JHZW7312 | B34: ICBU00000931347 | C34: 888384610822 | D34: OK-FDX-DHL-TNT | E34: 非主营 | F34: OK-FDX-DHL-TNT | G34: 玉麒麟 | I34: 宋海周 | J34: 28.04 | K34: 18.262 | L34: 29 | M34: 29 | N34: 0
A35: SH0131-2 | B35: ICBU00000932684 | C35: 1ZHF38642014756797 | D35: 加拿大准时达海派UPS | E35: 非主营 | F35: 加拿大准时达海派UPS | G35: 风清扬 | I35: 小飞侠 | J35: 16.97 | K35: 22.182 | L35: 27 | M35: 23 | N35: -4
A36: JPS20260131002 | B36: ICBU00000932924 | C36: CR431657742DE | D36: HST-UPS 6000 | E36: 非主营 | F36: HST-UPS 6000 | G36: 无崖子 | I36: 柴燕玲 | J36: 7.45 | K36: 9.281 | L36: 7.5 | M36: 9.5 | N36: 2
... A49: LM-056 | B49: ICBU00000932113 | C49: 1Z0R6D926806701789 | D49: 欧洲卡航含税(快递派) | E49: 非主营 | F49: 欧洲卡航含税(快递派） | G49: 007 | I49: 张小雪 | J49: 53.99 | K49: 53.065 | L49: 55 | M49: 54 | N49: -1
A50: YKZXX0131 | B50: ICBU00000932135 | D50: 义乌联邦IE-包税 | E50: 非主营 | F50: 义乌联邦IE-包税 | G50: 无崖子 | I50: 张小雪 | J50: 48.64 | K50: 113.528 | L50: 118 | M50: 122 | N50: 4
A51: HJ25613101 | B51: ICBU00000932738 | C51: 888401830517 | D51: JRGJ-专线 | E51: 非主营 | F51: JRGJ-专线 | G51: 帅时莹 | I51: 李凤 | J51: 69.65 | K51: 72.481 | L51: 82 | M51: 73 | N51: -9
A52: 29G6T9 | B52: ICBU00000933001 | C52: CR431656565DE | D52: HST-UPS 6000 | E52: 非主营 | F52: HST-UPS 6000 | G52: 无崖子 | I52: 李可 | J52: 12.39 | K52: 9.758 | L52: 12.5 | M52: 13 | N52: 0.5
A53: UES260100104 | B53: ICBU00000933078 | C53: KP | D53: 美转加快提卡派(HEDE) | E53: 非主营 | F53: 美转加快提卡派(HEDE) | G53: 风清扬 | I53: 张小雪 | J53: 1592.96 | K53: 1176.319 | L53: 1571 | M53: 2573 | N53: 1002
A54: DS260131-90015 | B54: ICBU00000931627 | C54: 888393849785 | D54: 义乌联邦FICP-包税 | E54: 非主营 | F54: 义乌联邦FICP-包税 | G54: 无崖子 | I54: 臧明 | J54: 0.24 | K54: 0 | L54: 0.5 | M54: 0.5 | N54: 0
A55: NS0131 | B55: ICBU00000932227 | C55: 888386680111 | D55: OK-FDX-DHL-TNT | E55: 非主营 | F55: OK-FDX-DHL-TNT | G55: 玉麒麟 | I55: 付乐航 | J55: 0.1 | K55: 0 | L55: 0.5 | M55: 0.5 | N55: 0
A56: D20260131-1 | B56: ICBU00000932917 | C56: 398309170150 | D56: FEDEX速快美国包税6000 | E56: 非主营 | F56: FEDEX速快美国包税6000 | G56: 无崖子 | I56: 施建祥 | J56: 0.06 | K56: 0 | L56: 0.5 | M56: 0.5 | N56: 0
A57: MWR26131-1 | B57: ICBU00000932936 | C57: 1Z4W260E0402266135 | D57: OK-UPS红单 | E57: 非主营 | F57: OK-UPS红单 | G57: 玉麒麟 | I57: 徐建 | J57: 5.87 | K57: 7.157 | L57: 7 | M57: 7.5 | N57: 0.5
A58: YQ131CZ-1 | B58: ICBU00000932663 | C58: 1Z0R6D926809022365 | D58: 欧洲卡航含税(快递派) | E58: 非主营 | F58: 欧洲卡航含税(快递派） | G58: 007 | I58: 张俊合 | J58: 34.11 | K58: 13.86 | L58: 35 | M58: 35 | N58: 0
A59: PTYL-131T | B59: ICBU00000932552 | C59: 1Z4W260E0409162127 | D59: OK-FDX-DHL-TNT | E59: 非主营 | F59: OK-FDX-DHL-TNT | G59: 玉麒麟 | I59: 汪礼平 | J59: 3.01 | K59: 0.878 | L59: 3.5 | M59: 3.5 | N59: 0
A60: HY260131-NL-9 | B60: ICBU00000931782 | C60: 1ZF4K3596803870460 | D60: 欧洲专线-HMC | E60: 非主营 | F60: 欧洲专线-HMC | G60: 帅时莹 | I60: 朱杰 | J60: 127.81 | K60: 53.97 | L60: 131 | M60: 131 | N60: 0
A61: 5ME9963WS | B61: ICBU00000932078 | C61: 1Z0E620D0435857753 | D61: OK-FDX-DHL-TNT | E61: 非主营 | F61: OK-FDX-DHL-TNT | G61: 玉麒麟 | I61: 王岩岩 | J61: 6.27 | K61: 6.863 | L61: 7 | M61: 7 | N61: 0
A62: BSMY20260131-2 | B62: ICBU00000932971 | C62: 1Z0R6D896822740883 | D62: 欧洲快船-JT | E62: 非主营 | F62: 欧洲快船-JT | G62: 风清扬 | I62: 叶伟明 | J62: 26.29 | K62: 13.629 | L62: 39 | M62: 39 | N62: 0
... A80: TX260131-WJ17 | B80: ICBU00000932864 | C80: 1ZF4K3596809766885 | D80: 欧洲专线-HMC | E80: 非主营 | F80: 欧洲专线-HMC | G80: 帅时莹 | I80: 余雨婕 | J80: 117.59 | K80: 79.825 | L80: 131 | M80: 131 | N80: 0
A81: TB013101 | B81: ICBU00000932219 | C81: 1Z0JH5420330751666 | D81: 美国WP | E81: 非主营 | F81: 美国WP | I81: 张小雪 | J81: 1500 | K81: 480 | L81: 1500 | M81: 1500 | N81: 0
A82: FBA1973TX06Q | B82: ICBU00000932857 | C82: 1Z4W260E0411601880 | D82: OK-UPS红单 | E82: 非主营 | F82: OK-UPS红单 | G82: 玉麒麟 | I82: 李得胜 | J82: 14.98 | K82: 14.321 | L82: 15 | M82: 15 | N82: 0
A83: TX260131-LY11 | B83: ICBU00000932888 | C83: AMQ6873695 | D83: 澳大利亚空派-香港飞-SC | E83: 非主营 | F83: 澳大利亚空派-香港飞-SC | G83: 小旋风 | I83: 余雨婕 | J83: 1.42 | K83: 1.922 | L83: 2 | M83: 22 | N83: 20
A84: HCLSA0131-1 | B84: ICBU00000932298 | C84: 15504530823180 | D84: 英国海派包税（快递派） | E84: 非主营 | F84: 英国海派包税（快递派） | G84: 007 | I84: 刘申奥 | J84: 147.65 | K84: 296.148 | L84: 291 | M84: 315 | N84: 24
A85: HCLSA0131-2 | B85: ICBU00000932390 | C85: 15504530853878 | D85: 英国空派-普货-经济-含税-KY | E85: 非主营 | F85: 英国空派-普货-经济-含税-KY | G85: 风清扬 | I85: 刘申奥 | J85: 6.98 | K85: 16.555 | L85: 21 | M85: 26 | N85: 5
A86: YM2613102 | B86: ICBU00000932802 | C86: 888401809040 | D86: JRGJ-专线 | E86: 非主营 | F86: JRGJ-专线 | G86: 帅时莹 | I86: 李凤 | J86: 230.64 | K86: 146.331 | L86: 231 | M86: 231 | N86: 0
A87: 26EYEJ058 | B87: ICBU00000926830 | C87: KP | D87: 欧洲快船-JT | E87: 非主营 | F87: 欧洲快船-JT | G87: 风清扬 | I87: 周志宇 | J87: 290 | K87: 368.16 | L87: 369 | M87: 369 | N87: 0
A88: LKS-PO8302-51 | B88: ICBU00000932022 | C88: KP | D88: 加拿大海派-JY | E88: 非主营 | F88: 加拿大海派-JY | G88: 风清扬 | I88: 马淞浦 | J88: 552.4 | K88: 473.426 | L88: 553 | M88: 553 | N88: 0
A89: FL-260130A | B89: ICBU00000928728 | D89: 美国WP | E89: 非主营 | F89: 美国WP | I89: 陈炎 | J89: 2884.5 | K89: 1045.844 | L89: 2885 | M89: 2885 | N89: 0
A90: HL26131-1 | B90: ICBU00000932189 | C90: 1ZHF05572014691146 | D90: 加拿大空派-大陆飞-UPS派送/6000 | E90: 非主营 | F90: 加拿大空派-大陆飞-UPS派送/6000 | G90: 风清扬 | I90: 丁佳伟 | J90: 17.27 | K90: 21.28 | L90: 21 | M90: 22 | N90: 1
A91: GB0131-DE | B91: ICBU00000931328 | C91: 888382928543 | D91: 上海FEDEX-P价IP | E91: 非主营 | F91: 上海FEDEX-P价IP | G91: 无崖子 | I91: 陈颖 | J91: 0.95 | K91: 1.253 | L91: 1.5 | M91: 1.5 | N91: 0
A92: FBA15LDBQTGT | B92: ICBU00000930712 | C92: 1Z0R6D926808645944 | D92: 欧洲卡航含税(快递派) | E92: 非主营 | F92: 欧洲卡航含税(快递派） | G92: 007 | I92: 小飞侠 | J92: 45.13 | K92: 60.31 | L92: 57 | M92: 61 | N92: 4
A93: GB0131-US01 | B93: ICBU00000931243 | C93: 398309225951 | D93: FEDEX速快美国包税6000 | E93: 非主营 | F93: FEDEX速快美国包税6000 | G93: 无崖子 | I93: 陈颖 | J93: 2.54 | K93: 2.028 | L93: 3 | M93: 3 | N93: 0
A94: WLXB-3GB-1 | B94: ICBU00000929599 | C94: 888384608580 | D94: OK-FDX-DHL-TNT | E94: 非主营 | F94: OK-FDX-DHL-TNT | G94: 玉麒麟 | I94: 邓健群 | J94: 59.33 | K94: 69.886 | L94: 70 | M94: 70 | N94: 0
A95: WLXB-3GB-2 | B95: ICBU00000929600 | C95: 888386159189 | D95: OK-FDX-DHL-TNT | E95: 非主营 | F95: OK-FDX-DHL-TNT | G95: 玉麒麟 | I95: 邓健群 | J95: 59.39 | K95: 68.156 | L95: 69 | M95: 69 | N95: 0
A96: CH20260131-1 | B96: ICBU00000932648 | C96: KP | D96: 英国卡航-卡派-含税-KY | E96: 非主营 | F96: 英国卡航-卡派-含税-KY | G96: 风清扬 | I96: 张德士 | J96: 214.5 | K96: 427.862 | L96: 423 | M96: 428 | N96: 5
A97: JYZ26013101 | B97: ICBU00000931973 | C97: 1ZX30Y730490393478 | D97: 义乌UPS红单直发包税/5000 | E97: 非主营 | F97: 义乌UPS红单直发包税/5000 | G97: 无崖子 | I97: 张小雪 | J97: 60.56 | K97: 19.618 | L97: 62 | M97: 64 | N97: 2
A98: JYZ26013102 | B98: ICBU00000931978 | C98: 1ZX30Y730498888581 | D98: 义乌UPS红单直发包税/5000 | E98: 非主营 | F98: 义乌UPS红单直发包税/5000 | G98: 无崖子 | I98: 张小雪 | J98: 54.28 | K98: 16.499 | L98: 55 | M98: 55 | N98: 0
A99: JLL260131A | B99: ICBU00000932055 | C99: MKP4534281830 | D99: 澳大利亚空派-大陆飞-SC | E99: 非主营 | F99: 澳大利亚空派-大陆飞-SC | G99: 小旋风 | I99: 陈炎 | J99: 428.48 | K99: 436.599 | L99: 429.5 | M99: 437 | N99: 7.5
A100: JLL260131B | B100: ICBU00000932080 | C100: TPL600032612 | D100: 澳大利亚空派-大陆飞-SC | E100: 非主营 | F100: 澳大利亚空派-大陆飞-SC | G100: 小旋风 | I100: 陈炎 | J100: 27.41 | K100: 30.288 | L100: 30 | M100: 31 | N100: 1
A101: JLL260131C | B101: ICBU00000932083 | C101: 888385218542 | D101: OK-FDX-DHL-TNT | E101: 非主营 | F101: OK-FDX-DHL-TNT | G101: 玉麒麟 | I101: 陈炎 | J101: 9.14 | K101: 11.88 | L101: 12 | M101: 12 | N101: 0
... A113: ZJTX2025803 | B113: ICBU00000930190 | C113: 888386075311 | D113: OK-FDX-DHL-TNT | E113: 非主营 | F113: OK-FDX-DHL-TNT | G113: 玉麒麟 | I113: 陈玉琴 | J113: 0.45 | K113: 0 | L113: 0.5 | M113: 0.5 | N113: 0
A114: CZQ260130 | B114: ICBU00000932382 | D114: OK-FDX-DHL-TNT | E114: 非主营 | F114: OK-FDX-DHL-TNT | G114: 玉麒麟 | I114: 蒋龙波 | J114: 0.08 | K114: 0 | L114: 0.5 | M114: 0.5 | N114: 0
A115: FREDA707102 | B115: ICBU00000932392 | C115: 1Z0R6D926803614290 | D115: 欧洲海派含税(快递派) | E115: 非主营 | F115: 欧洲海派含税(快递派） | G115: 007 | I115: 高雨晴 | J115: 22.21 | K115: 26.216 | L115: 26 | M115: 27 | N115: 1
A116: LUNA9305523 | B116: ICBU00000931320 | C116: 1Z0R6D896806053549 | D116: 欧洲快船-JT | E116: 非主营 | F116: 欧洲快船-JT | G116: 风清扬 | I116: 何林霞 | J116: 286.04 | K116: 287.696 | L116: 326 | M116: 326 | N116: 0
A117: RF-1147 | B117: ICBU00000929704 | C117: 1Z0R6D926839601567 | D117: 欧洲海派含税(快递派) | E117: 非主营 | F117: 欧洲海派含税(快递派） | G117: 007 | I117: 王拥 | J117: 2989.26 | K117: 3497.429 | L117: 3374 | M117: 3498 | N117: 124
A118: FG260108020 | B118: ICBU00000931596 | C118: AMQ6873655 | D118: 澳大利亚空派-经济线-SC | E118: 非主营 | F118: 澳大利亚空派-经济线-SC | G118: 小旋风 | I118: 李凤 | J118: 21.65 | K118: 16.246 | L118: 22 | M118: 22 | N118: 0
A119: RC261302 | B119: ICBU00000932130 | C119: SA780165875 | D119: 阿联酋专线-YT | E119: 非主营 | F119: 阿联酋专线-YT | G119: 帅时莹 | I119: 李凤 | J119: 59.99 | K119: 32.905 | L119: 60 | M119: 60 | N119: 0
A120: SQ260108002 | B120: ICBU00000931902 | C120: 500745742652 | D120: OK-UPS蓝单 | E120: 非主营 | F120: OK-UPS蓝单 | G120: 玉麒麟 | I120: 李凤 | J120: 93.76 | K120: 99.404 | L120: 96 | M120: 102 | N120: 6
A121: FL-2601310E | B121: ICBU00000932337 | D121: 美国WP | E121: 非主营 | F121: 美国WP | I121: 陈炎 | J121: 3700.78 | K121: 2441.763 | L121: 3701 | M121: 3701 | N121: 0
A122: HS457-77 | B122: ICBU00000932148 | C122: SA-WJ24626 | D122: 沙特海派 | E122: 非主营 | F122: 沙特海派 | G122: 小旋风 | I122: 左宗伟 | J122: 385.7 | K122: 430.317 | L122: 431 | M122: 431 | N122: 0
A123: RF-7704 | B123: ICBU00000932373 | C123: 1Z0R6D926832267101 | D123: 欧洲海派含税(快递派) | E123: 非主营 | F123: 欧洲海派含税(快递派） | G123: 007 | I123: 王拥 | J123: 849.57 | K123: 251.497 | L123: 865 | M123: 857 | N123: -8
A124: YINHAI2544 | B124: ICBU00000932088 | C124: MY4751 | D124: 沙特空派 | E124: 非主营 | F124: 沙特空派 | G124: 小旋风 | I124: 左宗伟 | J124: 142.72 | K124: 159.809 | L124: 150 | M124: 160 | N124: 10
A125: LR260130 | B125: ICBU00000930956 | C125: MKP24000759952 | D125: 私人地址海派双清含税（AU-S-02） | E125: 非主营 | F125: 私人地址海派双清含税（AU-S-02） | G125: 小旋风 | I125: 孙源圻 | J125: 851.34 | K125: 1312.709 | L125: 1313 | M125: 1313 | N125: 0
A126: FCO0018 | B126: ICBU00000931738 | C126: 398309492050 | D126: YF-联邦包税小包 | E126: 非主营 | F126: YF-联邦包税小包 | G126: 帅时莹 | I126: 李可 | J126: 0.76 | K126: 0 | L126: 1 | M126: 1 | N126: 0
A127: LEKE29318 | B127: ICBU00000932197 | C127: 398310485636 | D127: OK-FDX-DHL-TNT | E127: 非主营 | F127: OK-FDX-DHL-TNT | G127: 玉麒麟 | I127: 宋海周 | J127: 0.55 | K127: 0.95 | L127: 1 | M127: 1 | N127: 0
A128: BLS01307200 | B128: ICBU00000932157 | C128: 1Z80F20X0423193076 | D128: FedEx-通用渠道 | E128: 非主营 | F128: FedEx-通用渠道 | G128: 无崖子 | I128: 高雨晴 | J128: 0.79 | K128: 0.867 | L128: 1 | M128: 1.5 | N128: 0.5
A129: SHANELGORIAL26131-1 | B129: ICBU00000931993 | C129: 1Z0E620D0405399626 | D129: OK-FDX-DHL-TNT | E129: 非主营 | F129: OK-FDX-DHL-TNT | G129: 玉麒麟 | I129: 丁佳伟 | J129: 0.41 | K129: 0.739 | L129: 1 | M129: 1 | N129: 0
A130: FBA19751BCG3 | B130: ICBU00000932097 | C130: KP | D130: 加拿大海派-JY | E130: 非主营 | F130: 加拿大海派-JY | G130: 风清扬 | I130: 陈兵 | J130: 307.31 | K130: 265.858 | L130: 308 | M130: 308 | N130: 0
A131: CN260131-US-46806 | B131: ICBU00000931286 | C131: 398309523280 | D131: YF-联邦包税小包 | E131: 非主营 | F131: YF-联邦包税小包 | G131: 帅时莹 | I131: 朱杰 | J131: 1.98 | K131: 2.567 | L131: 2.5 | M131: 3 | N131: 0.5
A132: CN260131-US-52552 | B132: ICBU00000931289 | C132: 398309602860 | D132: YF-联邦包税小包 | E132: 非主营 | F132: YF-联邦包税小包 | G132: 帅时莹 | I132: 朱杰 | J132: 1.83 | K132: 2.567 | L132: 2.5 | M132: 3 | N132: 0.5
A133: CN260131-US-33778 | B133: ICBU00000931285 | C133: 398309593703 | D133: YF-联邦包税小包 | E133: 非主营 | F133: YF-联邦包税小包 | G133: 帅时莹 | I133: 朱杰 | J133: 2.5 | K133: 2.678 | L133: 3 | M133: 3 | N133: 0
... A154: JT0131-1 | B154: ICBU00000932046 | C154: 1Z0E793D6704433474 | D154: MSHQ-UPS | E154: 非主营 | F154: MSHQ-UPS | G154: 帅时莹 | I154: 王涛 | J154: 5.07 | K154: 11.178 | L154: 10 | M154: 12 | N154: 2
A155: YKZXX013101 | B155: ICBU00000931779 | D155: 义乌联邦IE-包税 | E155: 非主营 | F155: 义乌联邦IE-包税 | G155: 无崖子 | I155: 张小雪 | J155: 51.35 | K155: 55.493 | L155: 56 | M155: 56 | N155: 0
A156: HZHF0037 | B156: ICBU00000925854 | C156: 1ZHF34022038229695 | D156: 加拿大海派-JY | E156: 非主营 | F156: 加拿大海派-JY | G156: 风清扬 | I156: 叶伟明 | J156: 71.14 | K156: 58.448 | L156: 72 | M156: 72 | N156: 0
A157: CX-128879 | B157: ICBU00000931980 | C157: 1Z33W2600493890928 | D157: OK-FDX-DHL-TNT | E157: 非主营 | F157: OK-FDX-DHL-TNT | G157: 玉麒麟 | I157: 江伟成 | J157: 2.99 | K157: 3.584 | L157: 3.5 | M157: 4.5 | N157: 1
A158: 260130GT-LISA3 | B158: ICBU00000928563 | C158: 15504530331795 | D158: 英国空运普货DPD派 | E158: 非主营 | F158: 英国空运普货DPD派 | G158: 小旋风 | I158: 黄小丽 | J158: 18.16 | K158: 48.195 | L158: 33 | M158: 66 | N158: 33
A159: QY26-0131ER01 | B159: ICBU00000931932 | C159: 500745745216 | D159: OK-UPS蓝单 | E159: 非主营 | F159: OK-UPS蓝单 | G159: 玉麒麟 | I159: 王志军 | J159: 15.25 | K159: 13.874 | L159: 15.5 | M159: 16 | N159: 0.5
A160: AQ26131-2 | B160: ICBU00000931871 | C160: 1ZX30Y730491475360 | D160: 义乌UPS红单直发包税/6000 | E160: 非主营 | F160: 义乌UPS红单直发包税/6000 | G160: 无崖子 | I160: 丁佳伟 | J160: 22.05 | K160: 24.798 | L160: 30 | M160: 26 | N160: -4
...

Sheet 业务数据统计
A1: 期间 | B1: 渠道客服 | C1: 大货小货 | D1: 计算提成数据 | E1: 提成系数 | F1: 提成金额 | G1: 出货计费重 | H1: 是否计算提成 | I1: 客户单号 | J1: 服务商单号 | K1: 渠道转单号 | L1: 销售产品 | M1: 应收运费单价 | N1: 产品组 | O1: 结算员 | P1: 目的国家 | Q1: 邮编 | R1: FBA仓库代码 | S1: 客户 | T1: 客户类型 | U1: 业务员 | V1: 业务员部门 | W1: 前线客服 | X1: 申报总价值 | Y1: 货物类型 | Z1: 操作状态 | AA1: 中转状态 | AB1: 退件状态 | AC1: 件数 | AD1: 收货实重 | AE1: 收货计费重 | AF1: 收货比重 | AG1: 服务商计费重 | AH1: 应收 | AI1: 实收 | AJ1: 应收单价 | AK1: 应付 | AL1: 实付 | AM1: 毛利 | AN1: 业务员成本 | AO1: 业务员成本单价 | AP1: 业务员毛利 | AQ1: 产品部毛利 | AR1: 核销时间 | AS1: 应收是否锁定 | AT1: 应付是否锁定 | AU1: 结算服务商 | AV1: 业务服务商 | AW1: 服务渠道 | AX1: 收货机构 | AY1: 到货时间 | AZ1: 到货总单 | BA1: 出货时间 | BB1: 出货总单 | BC1: 附加服务 | BD1: 航空主单号 | BE1: 中文品名 | BF1: 自定义备注
A2: =MID(AY2,1,7) -> 2026-01 | B2: =_xlfn.XLOOKUP(I2,过机服务商重量差!A:A,过机服务商重量差!G:G) -> 玉麒麟 | C2: {=IF(N2="FBA","主营产品",IF(N2="专线","专线",LOOKUP(1,0/((G2>=提成标准!D:D)*(G2<提成标准!E:E)),提成标准!C:C)))} -> 快递小货 | D2: =IF(C2="快递小货",1,IF(C2="主营产品",0,G2)) -> 1 | E2: =_xlfn.XLOOKUP(C2,提成标准!C:C,提成标准!H:H,"") -> 2 | F2: =D2*E2 -> 2 | G2: =_xlfn.XLOOKUP(I2,过机服务商重量差!A:A,过机服务商重量差!L:L) -> 3.5 | H2: =IFERROR(LOOKUP(1,0/((B2=名单!B:B)*(VALUE(AY2)>=名单!E:E)*(VALUE(AY2)<=名单!G:G)*(AA2="正常走货")),名单!H:H),"否") -> 否 | I2: QS0131-MX | J2: 1ZG3325W0416448603 | L2: OK-FDX-DHL-TNT | N2: 非主营 | U2: 小飞侠 | V2: 营销五部 | AA2: 正常走货 | AQ2: 118.16 | AY2: 2026-01-31 22:46:57
A3: =MID(AY3,1,7) -> 2026-01 | B3: =_xlfn.XLOOKUP(I3,过机服务商重量差!A:A,过机服务商重量差!G:G) -> 玉麒麟 | C3: =IF(N3="FBA","主营产品",IF(N3="专线","专线",LOOKUP(1,0/((G3>=提成标准!D:D)*(G3<提成标准!E:E)),提成标准!C:C))) -> 快递小货 | D3: =IF(C3="快递小货",1,IF(C3="主营产品",0,G3)) -> 1 | E3: =_xlfn.XLOOKUP(C3,提成标准!C:C,提成标准!H:H,"") -> 2 | F3: =D3*E3 -> 2 | G3: =_xlfn.XLOOKUP(I3,过机服务商重量差!A:A,过机服务商重量差!L:L) -> 9.5 | H3: =IFERROR(LOOKUP(1,0/((B3=名单!B:B)*(VALUE(AY3)>=名单!E:E)*(VALUE(AY3)<=名单!G:G)*(AA3="正常走货")),名单!H:H),"否") -> 否 | I3: TL0131-NL | J3: 1Z4W260E0409673969 | L3: OK-UPS红单 | N3: 非主营 | U3: 小飞侠 | V3: 营销五部 | AA3: 正常走货 | AQ3: 132.4 | AY3: 2026-01-31 22:46:36
A4: =MID(AY4,1,7) -> 2026-01 | B4: =_xlfn.XLOOKUP(I4,过机服务商重量差!A:A,过机服务商重量差!G:G) -> 小旋风 | C4: =IF(N4="FBA","主营产品",IF(N4="专线","专线",LOOKUP(1,0/((G4>=提成标准!D:D)*(G4<提成标准!E:E)),提成标准!C:C))) -> 快递小货 | D4: =IF(C4="快递小货",1,IF(C4="主营产品",0,G4)) -> 1 | E4: =_xlfn.XLOOKUP(C4,提成标准!C:C,提成标准!H:H,"") -> 2 | F4: =D4*E4 -> 2 | G4: =_xlfn.XLOOKUP(I4,过机服务商重量差!A:A,过机服务商重量差!L:L) -> 0.7 | H4: =IFERROR(LOOKUP(1,0/((B4=名单!B:B)*(VALUE(AY4)>=名单!E:E)*(VALUE(AY4)<=名单!G:G)*(AA4="正常走货")),名单!H:H),"否") -> 否 | I4: FBA15G65R8GW | J4: RCD24000759946 | L4: 澳大利亚海派-包税 | N4: 非主营 | U4: 高雨晴 | V4: 营销二部 | AA4: 正常走货 | AQ4: 420 | AY4: 2026-01-31 22:45:45
A5: =MID(AY5,1,7) -> 2026-01 | B5: =_xlfn.XLOOKUP(I5,过机服务商重量差!A:A,过机服务商重量差!G:G) -> 小旋风 | C5: =IF(N5="FBA","主营产品",IF(N5="专线","专线",LOOKUP(1,0/((G5>=提成标准!D:D)*(G5<提成标准!E:E)),提成标准!C:C))) -> 快递小货 | D5: =IF(C5="快递小货",1,IF(C5="主营产品",0,G5)) -> 1 | E5: =_xlfn.XLOOKUP(C5,提成标准!C:C,提成标准!H:H,"") -> 2 | F5: =D5*E5 -> 2 | G5: =_xlfn.XLOOKUP(I5,过机服务商重量差!A:A,过机服务商重量差!L:L) -> 0.8 | H5: =IFERROR(LOOKUP(1,0/((B5=名单!B:B)*(VALUE(AY5)>=名单!E:E)*(VALUE(AY5)<=名单!G:G)*(AA5="正常走货")),名单!H:H),"否") -> 否 | I5: FBA15G65P13K | J5: RCD24000759947 | L5: 澳大利亚海派-包税 | N5: 非主营 | U5: 高雨晴 | V5: 营销二部 | AA5: 正常走货 | AQ5: 800 | AY5: 2026-01-31 22:45:28
A6: =MID(AY6,1,7) -> 2026-01 | B6: =_xlfn.XLOOKUP(I6,过机服务商重量差!A:A,过机服务商重量差!G:G) -> 张诚 | C6: =IF(N6="FBA","主营产品",IF(N6="专线","专线",LOOKUP(1,0/((G6>=提成标准!D:D)*(G6<提成标准!E:E)),提成标准!C:C))) -> 快递大货 | D6: =IF(C6="快递小货",1,IF(C6="主营产品",0,G6)) -> 44 | E6: =_xlfn.XLOOKUP(C6,提成标准!C:C,提成标准!H:H,"") -> 0.1 | F6: =D6*E6 -> 4.4 | G6: =_xlfn.XLOOKUP(I6,过机服务商重量差!A:A,过机服务商重量差!L:L) -> 44 | H6: =IFERROR(LOOKUP(1,0/((B6=名单!B:B)*(VALUE(AY6)>=名单!E:E)*(VALUE(AY6)<=名单!G:G)*(AA6="正常走货")),名单!H:H),"否") -> 否 | I6: SP260122021 | L6: 欧洲海卡包税-MM | N6: 非主营 | U6: 马淞浦 | V6: 营销一部 | AA6: 正常走货 | AQ6: 400 | AY6: 2026-01-31 22:43:03
A7: =MID(AY7,1,7) -> 2026-01 | B7: =_xlfn.XLOOKUP(I7,过机服务商重量差!A:A,过机服务商重量差!G:G) -> 张诚 | C7: =IF(N7="FBA","主营产品",IF(N7="专线","专线",LOOKUP(1,0/((G7>=提成标准!D:D)*(G7<提成标准!E:E)),提成标准!C:C))) -> 快递大货 | D7: =IF(C7="快递小货",1,IF(C7="主营产品",0,G7)) -> 236 | E7: =_xlfn.XLOOKUP(C7,提成标准!C:C,提成标准!H:H,"") -> 0.1 | F7: =D7*E7 -> 23.6 | G7: =_xlfn.XLOOKUP(I7,过机服务商重量差!A:A,过机服务商重量差!L:L) -> 236 | H7: =IFERROR(LOOKUP(1,0/((B7=名单!B:B)*(VALUE(AY7)>=名单!E:E)*(VALUE(AY7)<=名单!G:G)*(AA7="正常走货")),名单!H:H),"否") -> 否 | I7: SP260129024 | L7: 欧洲海卡包税-MM | N7: 非主营 | U7: 马淞浦 | V7: 营销一部 | AA7: 正常走货 | AQ7: 2832 | AY7: 2026-01-31 22:42:39
A8: =MID(AY8,1,7) -> 2026-01 | B8: =_xlfn.XLOOKUP(I8,过机服务商重量差!A:A,过机服务商重量差!G:G) -> 张诚 | C8: =IF(N8="FBA","主营产品",IF(N8="专线","专线",LOOKUP(1,0/((G8>=提成标准!D:D)*(G8<提成标准!E:E)),提成标准!C:C))) -> 快递大货 | D8: =IF(C8="快递小货",1,IF(C8="主营产品",0,G8)) -> 77 | E8: =_xlfn.XLOOKUP(C8,提成标准!C:C,提成标准!H:H,"") -> 0.1 | F8: =D8*E8 -> 7.7 | G8: =_xlfn.XLOOKUP(I8,过机服务商重量差!A:A,过机服务商重量差!L:L) -> 77 | H8: =IFERROR(LOOKUP(1,0/((B8=名单!B:B)*(VALUE(AY8)>=名单!E:E)*(VALUE(AY8)<=名单!G:G)*(AA8="正常走货")),名单!H:H),"否") -> 否 | I8: SP260121227 | L8: 欧洲海卡包税-MM | N8: 非主营 | U8: 马淞浦 | V8: 营销一部 | AA8: 正常走货 | AQ8: 924 | AY8: 2026-01-31 22:42:32
A9: =MID(AY9,1,7) -> 2026-01 | B9: =_xlfn.XLOOKUP(I9,过机服务商重量差!A:A,过机服务商重量差!G:G) -> 张诚 | C9: =IF(N9="FBA","主营产品",IF(N9="专线","专线",LOOKUP(1,0/((G9>=提成标准!D:D)*(G9<提成标准!E:E)),提成标准!C:C))) -> 快递大货 | D9: =IF(C9="快递小货",1,IF(C9="主营产品",0,G9)) -> 183 | E9: =_xlfn.XLOOKUP(C9,提成标准!C:C,提成标准!H:H,"") -> 0.1 | F9: =D9*E9 -> 18.3 | G9: =_xlfn.XLOOKUP(I9,过机服务商重量差!A:A,过机服务商重量差!L:L) -> 183 | H9: =IFERROR(LOOKUP(1,0/((B9=名单!B:B)*(VALUE(AY9)>=名单!E:E)*(VALUE(AY9)<=名单!G:G)*(AA9="正常走货")),名单!H:H),"否") -> 否 | I9: SP260123008 | L9: 欧洲海卡包税-MM | N9: 非主营 | U9: 马淞浦 | V9: 营销一部 | AA9: 正常走货 | AQ9: 2196 | AY9: 2026-01-31 22:40:53
A10: =MID(AY10,1,7) -> 2026-01 | B10: =_xlfn.XLOOKUP(I10,过机服务商重量差!A:A,过机服务商重量差!G:G) -> 张诚 | C10: =IF(N10="FBA","主营产品",IF(N10="专线","专线",LOOKUP(1,0/((G10>=提成标准!D:D)*(G10<提成标准!E:E)),提成标准!C:C))) -> 快递大货 | D10: =IF(C10="快递小货",1,IF(C10="主营产品",0,G10)) -> 132 | E10: =_xlfn.XLOOKUP(C10,提成标准!C:C,提成标准!H:H,"") -> 0.1 | F10: =D10*E10 -> 13.2 | G10: =_xlfn.XLOOKUP(I10,过机服务商重量差!A:A,过机服务商重量差!L:L) -> 132 | H10: =IFERROR(LOOKUP(1,0/((B10=名单!B:B)*(VALUE(AY10)>=名单!E:E)*(VALUE(AY10)<=名单!G:G)*(AA10="正常走货")),名单!H:H),"否") -> 否 | I10: SP260122003 | L10: 欧洲海卡包税-MM | N10: 非主营 | U10: 马淞浦 | V10: 营销一部 | AA10: 正常走货 | AQ10: 1584 | AY10: 2026-01-31 22:39:00
A11: =MID(AY11,1,7) -> 2026-01 | B11: =_xlfn.XLOOKUP(I11,过机服务商重量差!A:A,过机服务商重量差!G:G) -> 风清扬 | C11: =IF(N11="FBA","主营产品",IF(N11="专线","专线",LOOKUP(1,0/((G11>=提成标准!D:D)*(G11<提成标准!E:E)),提成标准!C:C))) -> 快递大货 | D11: =IF(C11="快递小货",1,IF(C11="主营产品",0,G11)) -> 67 | E11: =_xlfn.XLOOKUP(C11,提成标准!C:C,提成标准!H:H,"") -> 0.1 | F11: =D11*E11 -> 6.7 | G11: =_xlfn.XLOOKUP(I11,过机服务商重量差!A:A,过机服务商重量差!L:L) -> 67 | H11: =IFERROR(LOOKUP(1,0/((B11=名单!B:B)*(VALUE(AY11)>=名单!E:E)*(VALUE(AY11)<=名单!G:G)*(AA11="正常走货")),名单!H:H),"否") -> 否 | I11: SP260121220 | J11: KP | L11: 加拿大海派-JY | N11: 非主营 | U11: 马淞浦 | V11: 营销一部 | AA11: 正常走货 | AQ11: -99.5 | AY11: 2026-01-31 22:37:31
A12: =MID(AY12,1,7) -> 2026-01 | B12: =_xlfn.XLOOKUP(I12,过机服务商重量差!A:A,过机服务商重量差!G:G) -> 风清扬 | C12: =IF(N12="FBA","主营产品",IF(N12="专线","专线",LOOKUP(1,0/((G12>=提成标准!D:D)*(G12<提成标准!E:E)),提成标准!C:C))) -> 快递大货 | D12: =IF(C12="快递小货",1,IF(C12="主营产品",0,G12)) -> 272 | E12: =_xlfn.XLOOKUP(C12,提成标准!C:C,提成标准!H:H,"") -> 0.1 | F12: =D12*E12 -> 27.2 | G12: =_xlfn.XLOOKUP(I12,过机服务商重量差!A:A,过机服务商重量差!L:L) -> 272 | H12: =IFERROR(LOOKUP(1,0/((B12=名单!B:B)*(VALUE(AY12)>=名单!E:E)*(VALUE(AY12)<=名单!G:G)*(AA12="正常走货")),名单!H:H),"否") -> 否 | I12: SP260120060 | J12: KP | L12: 加拿大海派-JY | N12: 非主营 | U12: 马淞浦 | V12: 营销一部 | AA12: 正常走货 | AQ12: 126.4 | AY12: 2026-01-31 22:37:02
A13: =MID(AY13,1,7) -> 2026-01 | B13: =_xlfn.XLOOKUP(I13,过机服务商重量差!A:A,过机服务商重量差!G:G) -> 风清扬 | C13: =IF(N13="FBA","主营产品",IF(N13="专线","专线",LOOKUP(1,0/((G13>=提成标准!D:D)*(G13<提成标准!E:E)),提成标准!C:C))) -> 快递大货 | D13: =IF(C13="快递小货",1,IF(C13="主营产品",0,G13)) -> 138 | E13: =_xlfn.XLOOKUP(C13,提成标准!C:C,提成标准!H:H,"") -> 0.1 | F13: =D13*E13 -> 13.8 | G13: =_xlfn.XLOOKUP(I13,过机服务商重量差!A:A,过机服务商重量差!L:L) -> 138 | H13: =IFERROR(LOOKUP(1,0/((B13=名单!B:B)*(VALUE(AY13)>=名单!E:E)*(VALUE(AY13)<=名单!G:G)*(AA13="正常走货")),名单!H:H),"否") -> 否 | I13: SP260122050 | J13: KP | L13: 加拿大海派-JY | N13: 非主营 | U13: 马淞浦 | V13: 营销一部 | AA13: 正常走货 | AQ13: 139.3 | AY13: 2026-01-31 22:36:32
A14: =MID(AY14,1,7) -> 2026-01 | B14: =_xlfn.XLOOKUP(I14,过机服务商重量差!A:A,过机服务商重量差!G:G) -> 张诚 | C14: =IF(N14="FBA","主营产品",IF(N14="专线","专线",LOOKUP(1,0/((G14>=提成标准!D:D)*(G14<提成标准!E:E)),提成标准!C:C))) -> 快递大货 | D14: =IF(C14="快递小货",1,IF(C14="主营产品",0,G14)) -> 125 | E14: =_xlfn.XLOOKUP(C14,提成标准!C:C,提成标准!H:H,"") -> 0.1 | F14: =D14*E14 -> 12.5 | G14: =_xlfn.XLOOKUP(I14,过机服务商重量差!A:A,过机服务商重量差!L:L) -> 125 | H14: =IFERROR(LOOKUP(1,0/((B14=名单!B:B)*(VALUE(AY14)>=名单!E:E)*(VALUE(AY14)<=名单!G:G)*(AA14="正常走货")),名单!H:H),"否") -> 否 | I14: SP260122007 | L14: 欧洲海卡包税-MM | N14: 非主营 | U14: 马淞浦 | V14: 营销一部 | AA14: 正常走货 | AQ14: 1562.5 | AY14: 2026-01-31 22:31:06
A15: =MID(AY15,1,7) -> 2026-01 | B15: =_xlfn.XLOOKUP(I15,过机服务商重量差!A:A,过机服务商重量差!G:G) -> 张诚 | C15: =IF(N15="FBA","主营产品",IF(N15="专线","专线",LOOKUP(1,0/((G15>=提成标准!D:D)*(G15<提成标准!E:E)),提成标准!C:C))) -> 快递大货 | D15: =IF(C15="快递小货",1,IF(C15="主营产品",0,G15)) -> 234 | E15: =_xlfn.XLOOKUP(C15,提成标准!C:C,提成标准!H:H,"") -> 0.1 | F15: =D15*E15 -> 23.4 | G15: =_xlfn.XLOOKUP(I15,过机服务商重量差!A:A,过机服务商重量差!L:L) -> 234 | H15: =IFERROR(LOOKUP(1,0/((B15=名单!B:B)*(VALUE(AY15)>=名单!E:E)*(VALUE(AY15)<=名单!G:G)*(AA15="正常走货")),名单!H:H),"否") -> 否 | I15: SP260121264 | L15: 欧洲海卡包税-MM | N15: 非主营 | U15: 马淞浦 | V15: 营销一部 | AA15: 正常走货 | AQ15: 2925 | AY15: 2026-01-31 22:26:23
A16: =MID(AY16,1,7) -> 2026-01 | B16: =_xlfn.XLOOKUP(I16,过机服务商重量差!A:A,过机服务商重量差!G:G) -> 风清扬 | C16: =IF(N16="FBA","主营产品",IF(N16="专线","专线",LOOKUP(1,0/((G16>=提成标准!D:D)*(G16<提成标准!E:E)),提成标准!C:C))) -> 快递大货 | D16: =IF(C16="快递小货",1,IF(C16="主营产品",0,G16)) -> 37 | E16: =_xlfn.XLOOKUP(C16,提成标准!C:C,提成标准!H:H,"") -> 0.1 | F16: =D16*E16 -> 3.7 | G16: =_xlfn.XLOOKUP(I16,过机服务商重量差!A:A,过机服务商重量差!L:L) -> 37 | H16: =IFERROR(LOOKUP(1,0/((B16=名单!B:B)*(VALUE(AY16)>=名单!E:E)*(VALUE(AY16)<=名单!G:G)*(AA16="正常走货")),名单!H:H),"否") -> 否 | I16: SP260121188 | J16: KP | L16: 加拿大海派-JY | N16: 非主营 | U16: 马淞浦 | V16: 营销一部 | AA16: 正常走货 | AQ16: 29.9 | AY16: 2026-01-31 22:24:58
A17: =MID(AY17,1,7) -> 2026-01 | B17: =_xlfn.XLOOKUP(I17,过机服务商重量差!A:A,过机服务商重量差!G:G) -> 风清扬 | C17: =IF(N17="FBA","主营产品",IF(N17="专线","专线",LOOKUP(1,0/((G17>=提成标准!D:D)*(G17<提成标准!E:E)),提成标准!C:C))) -> 快递大货 | D17: =IF(C17="快递小货",1,IF(C17="主营产品",0,G17)) -> 26 | E17: =_xlfn.XLOOKUP(C17,提成标准!C:C,提成标准!H:H,"") -> 0.1 | F17: =D17*E17 -> 2.6 | G17: =_xlfn.XLOOKUP(I17,过机服务商重量差!A:A,过机服务商重量差!L:L) -> 26 | H17: =IFERROR(LOOKUP(1,0/((B17=名单!B:B)*(VALUE(AY17)>=名单!E:E)*(VALUE(AY17)<=名单!G:G)*(AA17="正常走货")),名单!H:H),"否") -> 否 | I17: SP260121174 | J17: KP | L17: 加拿大海派-JY | N17: 非主营 | U17: 马淞浦 | V17: 营销一部 | AA17: 正常走货 | AQ17: 173.4 | AY17: 2026-01-31 22:24:21
A18: =MID(AY18,1,7) -> 2026-01 | B18: =_xlfn.XLOOKUP(I18,过机服务商重量差!A:A,过机服务商重量差!G:G) -> 张诚 | C18: =IF(N18="FBA","主营产品",IF(N18="专线","专线",LOOKUP(1,0/((G18>=提成标准!D:D)*(G18<提成标准!E:E)),提成标准!C:C))) -> 快递大货 | D18: =IF(C18="快递小货",1,IF(C18="主营产品",0,G18)) -> 41 | E18: =_xlfn.XLOOKUP(C18,提成标准!C:C,提成标准!H:H,"") -> 0.1 | F18: =D18*E18 -> 4.1 | G18: =_xlfn.XLOOKUP(I18,过机服务商重量差!A:A,过机服务商重量差!L:L) -> 41 | H18: =IFERROR(LOOKUP(1,0/((B18=名单!B:B)*(VALUE(AY18)>=名单!E:E)*(VALUE(AY18)<=名单!G:G)*(AA18="正常走货")),名单!H:H),"否") -> 否 | I18: SP260121195 | L18: 欧洲海卡包税-MM | N18: 非主营 | U18: 马淞浦 | V18: 营销一部 | AA18: 正常走货 | AQ18: 594 | AY18: 2026-01-31 22:24:04
A19: =MID(AY19,1,7) -> 2026-01 | B19: =_xlfn.XLOOKUP(I19,过机服务商重量差!A:A,过机服务商重量差!G:G) -> 张诚 | C19: =IF(N19="FBA","主营产品",IF(N19="专线","专线",LOOKUP(1,0/((G19>=提成标准!D:D)*(G19<提成标准!E:E)),提成标准!C:C))) -> 快递大货 | D19: =IF(C19="快递小货",1,IF(C19="主营产品",0,G19)) -> 313 | E19: =_xlfn.XLOOKUP(C19,提成标准!C:C,提成标准!H:H,"") -> 0.1 | F19: =D19*E19 -> 31.3 | G19: =_xlfn.XLOOKUP(I19,过机服务商重量差!A:A,过机服务商重量差!L:L) -> 313 | H19: =IFERROR(LOOKUP(1,0/((B19=名单!B:B)*(VALUE(AY19)>=名单!E:E)*(VALUE(AY19)<=名单!G:G)*(AA19="正常走货")),名单!H:H),"否") -> 否 | I19: SP260121223 | L19: 欧洲海卡包税-MM | N19: 非主营 | U19: 马淞浦 | V19: 营销一部 | AA19: 正常走货 | AQ19: 4225.5 | AY19: 2026-01-31 22:20:47
A20: =MID(AY20,1,7) -> 2026-01 | B20: =_xlfn.XLOOKUP(I20,过机服务商重量差!A:A,过机服务商重量差!G:G) -> 风清扬 | C20: =IF(N20="FBA","主营产品",IF(N20="专线","专线",LOOKUP(1,0/((G20>=提成标准!D:D)*(G20<提成标准!E:E)),提成标准!C:C))) -> 快递大货 | D20: =IF(C20="快递小货",1,IF(C20="主营产品",0,G20)) -> 270 | E20: =_xlfn.XLOOKUP(C20,提成标准!C:C,提成标准!H:H,"") -> 0.1 | F20: =D20*E20 -> 27 | G20: =_xlfn.XLOOKUP(I20,过机服务商重量差!A:A,过机服务商重量差!L:L) -> 270 | H20: =IFERROR(LOOKUP(1,0/((B20=名单!B:B)*(VALUE(AY20)>=名单!E:E)*(VALUE(AY20)<=名单!G:G)*(AA20="正常走货")),名单!H:H),"否") -> 否 | I20: SP260120043-YYZ7-16 | J20: KP | L20: 加拿大海派-JY | N20: 非主营 | U20: 马淞浦 | V20: 营销一部 | AA20: 正常走货 | AQ20: -1287.4 | AY20: 2026-01-31 22:18:11
A21: =MID(AY21,1,7) -> 2026-01 | B21: =_xlfn.XLOOKUP(I21,过机服务商重量差!A:A,过机服务商重量差!G:G) -> 风清扬 | C21: =IF(N21="FBA","主营产品",IF(N21="专线","专线",LOOKUP(1,0/((G21>=提成标准!D:D)*(G21<提成标准!E:E)),提成标准!C:C))) -> 快递大货 | D21: =IF(C21="快递小货",1,IF(C21="主营产品",0,G21)) -> 732 | E21: =_xlfn.XLOOKUP(C21,提成标准!C:C,提成标准!H:H,"") -> 0.1 | F21: =D21*E21 -> 73.2 | G21: =_xlfn.XLOOKUP(I21,过机服务商重量差!A:A,过机服务商重量差!L:L) -> 732 | H21: =IFERROR(LOOKUP(1,0/((B21=名单!B:B)*(VALUE(AY21)>=名单!E:E)*(VALUE(AY21)<=名单!G:G)*(AA21="正常走货")),名单!H:H),"否") -> 否 | I21: SP260126064-YYZ7-38 | J21: KP | L21: 加拿大海派-JY | N21: 非主营 | U21: 马淞浦 | V21: 营销一部 | AA21: 正常走货 | AQ21: -2935.6 | AY21: 2026-01-31 22:17:08
A22: =MID(AY22,1,7) -> 2026-01 | B22: =_xlfn.XLOOKUP(I22,过机服务商重量差!A:A,过机服务商重量差!G:G) -> 张诚 | C22: =IF(N22="FBA","主营产品",IF(N22="专线","专线",LOOKUP(1,0/((G22>=提成标准!D:D)*(G22<提成标准!E:E)),提成标准!C:C))) -> 快递大货 | D22: =IF(C22="快递小货",1,IF(C22="主营产品",0,G22)) -> 634 | E22: =_xlfn.XLOOKUP(C22,提成标准!C:C,提成标准!H:H,"") -> 0.1 | F22: =D22*E22 -> 63.4 | G22: =_xlfn.XLOOKUP(I22,过机服务商重量差!A:A,过机服务商重量差!L:L) -> 634 | H22: =IFERROR(LOOKUP(1,0/((B22=名单!B:B)*(VALUE(AY22)>=名单!E:E)*(VALUE(AY22)<=名单!G:G)*(AA22="正常走货")),名单!H:H),"否") -> 否 | I22: SP260112003 | L22: 欧洲海卡包税-MM | N22: 非主营 | U22: 马淞浦 | V22: 营销一部 | AA22: 正常走货 | AQ22: 7975.8 | AY22: 2026-01-31 22:12:25
A23: =MID(AY23,1,7) -> 2026-01 | B23: =_xlfn.XLOOKUP(I23,过机服务商重量差!A:A,过机服务商重量差!G:G) -> 小旋风 | C23: =IF(N23="FBA","主营产品",IF(N23="专线","专线",LOOKUP(1,0/((G23>=提成标准!D:D)*(G23<提成标准!E:E)),提成标准!C:C))) -> 快递大货 | D23: =IF(C23="快递小货",1,IF(C23="主营产品",0,G23)) -> 37 | E23: =_xlfn.XLOOKUP(C23,提成标准!C:C,提成标准!H:H,"") -> 0.1 | F23: =D23*E23 -> 3.7 | G23: =_xlfn.XLOOKUP(I23,过机服务商重量差!A:A,过机服务商重量差!L:L) -> 37 | H23: =IFERROR(LOOKUP(1,0/((B23=名单!B:B)*(VALUE(AY23)>=名单!E:E)*(VALUE(AY23)<=名单!G:G)*(AA23="正常走货")),名单!H:H),"否") -> 否 | I23: HCLSA0131-6 | J23: TPL000134937 | L23: 澳大利亚海派-含税-SC | N23: 非主营 | U23: 刘申奥 | V23: 营销五部 | AA23: 正常走货 | AQ23: 195.9 | AY23: 2026-01-31 22:08:59
A24: =MID(AY24,1,7) -> 2026-01 | B24: =_xlfn.XLOOKUP(I24,过机服务商重量差!A:A,过机服务商重量差!G:G) -> 张诚 | C24: =IF(N24="FBA","主营产品",IF(N24="专线","专线",LOOKUP(1,0/((G24>=提成标准!D:D)*(G24<提成标准!E:E)),提成标准!C:C))) -> 快递大货 | D24: =IF(C24="快递小货",1,IF(C24="主营产品",0,G24)) -> 503 | E24: =_xlfn.XLOOKUP(C24,提成标准!C:C,提成标准!H:H,"") -> 0.1 | F24: =D24*E24 -> 50.3 | G24: =_xlfn.XLOOKUP(I24,过机服务商重量差!A:A,过机服务商重量差!L:L) -> 503 | H24: =IFERROR(LOOKUP(1,0/((B24=名单!B:B)*(VALUE(AY24)>=名单!E:E)*(VALUE(AY24)<=名单!G:G)*(AA24="正常走货")),名单!H:H),"否") -> 否 | I24: SP260121154 | L24: 欧洲海卡包税-MM | N24: 非主营 | U24: 马淞浦 | V24: 营销一部 | AA24: 正常走货 | AQ24: 6287.5 | AY24: 2026-01-31 22:01:04
A25: =MID(AY25,1,7) -> 2026-01 | B25: =_xlfn.XLOOKUP(I25,过机服务商重量差!A:A,过机服务商重量差!G:G) -> 小旋风 | C25: =IF(N25="FBA","主营产品",IF(N25="专线","专线",LOOKUP(1,0/((G25>=提成标准!D:D)*(G25<提成标准!E:E)),提成标准!C:C))) -> 快递大货 | D25: =IF(C25="快递小货",1,IF(C25="主营产品",0,G25)) -> 52 | E25: =_xlfn.XLOOKUP(C25,提成标准!C:C,提成标准!H:H,"") -> 0.1 | F25: =D25*E25 -> 5.2 | G25: =_xlfn.XLOOKUP(I25,过机服务商重量差!A:A,过机服务商重量差!L:L) -> 52 | H25: =IFERROR(LOOKUP(1,0/((B25=名单!B:B)*(VALUE(AY25)>=名单!E:E)*(VALUE(AY25)<=名单!G:G)*(AA25="正常走货")),名单!H:H),"否") -> 否 | I25: YKZXX013102 | J25: 1ZA06B016832064447 | L25: 欧洲德国清专线 | N25: 非主营 | U25: 张小雪 | V25: 营销五部 | AA25: 正常走货 | AQ25: 2794 | AY25: 2026-01-31 21:13:41
A26: =MID(AY26,1,7) -> 2026-01 | B26: =_xlfn.XLOOKUP(I26,过机服务商重量差!A:A,过机服务商重量差!G:G) -> 玉麒麟 | C26: =IF(N26="FBA","主营产品",IF(N26="专线","专线",LOOKUP(1,0/((G26>=提成标准!D:D)*(G26<提成标准!E:E)),提成标准!C:C))) -> 快递小货 | D26: =IF(C26="快递小货",1,IF(C26="主营产品",0,G26)) -> 1 | E26: =_xlfn.XLOOKUP(C26,提成标准!C:C,提成标准!H:H,"") -> 2 | F26: =D26*E26 -> 2 | G26: =_xlfn.XLOOKUP(I26,过机服务商重量差!A:A,过机服务商重量差!L:L) -> 1 | H26: =IFERROR(LOOKUP(1,0/((B26=名单!B:B)*(VALUE(AY26)>=名单!E:E)*(VALUE(AY26)<=名单!G:G)*(AA26="正常走货")),名单!H:H),"否") -> 否 | I26: TM260131-1CA3 | J26: 888386607575 | L26: OK-FDX-DHL-TNT | N26: 非主营 | U26: 邓健群 | V26: 营销三部 | AA26: 正常走货 | AQ26: 17.92 | AY26: 2026-01-31 21:02:14
A27: =MID(AY27,1,7) -> 2026-01 | B27: =_xlfn.XLOOKUP(I27,过机服务商重量差!A:A,过机服务商重量差!G:G) -> 小旋风 | C27: =IF(N27="FBA","主营产品",IF(N27="专线","专线",LOOKUP(1,0/((G27>=提成标准!D:D)*(G27<提成标准!E:E)),提成标准!C:C))) -> 快递大货 | D27: =IF(C27="快递小货",1,IF(C27="主营产品",0,G27)) -> 30 | E27: =_xlfn.XLOOKUP(C27,提成标准!C:C,提成标准!H:H,"") -> 0.1 | F27: =D27*E27 -> 3 | G27: =_xlfn.XLOOKUP(I27,过机服务商重量差!A:A,过机服务商重量差!L:L) -> 30 | H27: =IFERROR(LOOKUP(1,0/((B27=名单!B:B)*(VALUE(AY27)>=名单!E:E)*(VALUE(AY27)<=名单!G:G)*(AA27="正常走货")),名单!H:H),"否") -> 否 | I27: TM260131-2FR2 | J27: 1ZA06B016818572639 | L27: 欧洲德国清专线 | N27: 非主营 | U27: 邓健群 | V27: 营销三部 | AA27: 正常走货 | AQ27: 1500 | AY27: 2026-01-31 21:00:55
A28: =MID(AY28,1,7) -> 2026-01 | B28: =_xlfn.XLOOKUP(I28,过机服务商重量差!A:A,过机服务商重量差!G:G) -> 帅时莹 | C28: =IF(N28="FBA","主营产品",IF(N28="专线","专线",LOOKUP(1,0/((G28>=提成标准!D:D)*(G28<提成标准!E:E)),提成标准!C:C))) -> 快递大货 | D28: =IF(C28="快递小货",1,IF(C28="主营产品",0,G28)) -> 208 | E28: =_xlfn.XLOOKUP(C28,提成标准!C:C,提成标准!H:H,"") -> 0.1 | F28: =D28*E28 -> 20.8 | G28: =_xlfn.XLOOKUP(I28,过机服务商重量差!A:A,过机服务商重量差!L:L) -> 208 | H28: =IFERROR(LOOKUP(1,0/((B28=名单!B:B)*(VALUE(AY28)>=名单!E:E)*(VALUE(AY28)<=名单!G:G)*(AA28="正常走货")),名单!H:H),"否") -> 否 | I28: HH233M26 | J28: 1ZF4K3596816247057 | L28: 欧洲专线-HMC | N28: 非主营 | U28: 李娟-业务 | V28: 营销四部 | AA28: 正常走货 | AQ28: 2700 | AY28: 2026-01-31 20:59:02
A29: =MID(AY29,1,7) -> 2026-01 | B29: =_xlfn.XLOOKUP(I29,过机服务商重量差!A:A,过机服务商重量差!G:G) -> 玉麒麟 | C29: =IF(N29="FBA","主营产品",IF(N29="专线","专线",LOOKUP(1,0/((G29>=提成标准!D:D)*(G29<提成标准!E:E)),提成标准!C:C))) -> 快递小货 | D29: =IF(C29="快递小货",1,IF(C29="主营产品",0,G29)) -> 1 | E29: =_xlfn.XLOOKUP(C29,提成标准!C:C,提成标准!H:H,"") -> 2 | F29: =D29*E29 -> 2 | G29: =_xlfn.XLOOKUP(I29,过机服务商重量差!A:A,过机服务商重量差!L:L) -> 10 | H29: =IFERROR(LOOKUP(1,0/((B29=名单!B:B)*(VALUE(AY29)>=名单!E:E)*(VALUE(AY29)<=名单!G:G)*(AA29="正常走货")),名单!H:H),"否") -> 否 | I29: RSC3104 | J29: 1Z0E465J0413832648 | L29: OK-FDX-DHL-TNT | N29: 非主营 | U29: 汪祺 | V29: 营销二部 | AA29: 正常走货 | AQ29: 101.6 | AY29: 2026-01-31 20:56:27
A30: =MID(AY30,1,7) -> 2026-01 | B30: =_xlfn.XLOOKUP(I30,过机服务商重量差!A:A,过机服务商重量差!G:G) -> 玉麒麟 | C30: =IF(N30="FBA","主营产品",IF(N30="专线","专线",LOOKUP(1,0/((G30>=提成标准!D:D)*(G30<提成标准!E:E)),提成标准!C:C))) -> 快递小货 | D30: =IF(C30="快递小货",1,IF(C30="主营产品",0,G30)) -> 1 | E30: =_xlfn.XLOOKUP(C30,提成标准!C:C,提成标准!H:H,"") -> 2 | F30: =D30*E30 -> 2 | G30: =_xlfn.XLOOKUP(I30,过机服务商重量差!A:A,过机服务商重量差!L:L) -> 10 | H30: =IFERROR(LOOKUP(1,0/((B30=名单!B:B)*(VALUE(AY30)>=名单!E:E)*(VALUE(AY30)<=名单!G:G)*(AA30="正常走货")),名单!H:H),"否") -> 否 | I30: RSC3103 | J30: 1Z0E465J0419105235 | L30: OK-FDX-DHL-TNT | N30: 非主营 | U30: 汪祺 | V30: 营销二部 | AA30: 正常走货 | AQ30: 101.6 | AY30: 2026-01-31 20:56:22
A31: =MID(AY31,1,7) -> 2026-01 | B31: =_xlfn.XLOOKUP(I31,过机服务商重量差!A:A,过机服务商重量差!G:G) -> 玉麒麟 | C31: =IF(N31="FBA","主营产品",IF(N31="专线","专线",LOOKUP(1,0/((G31>=提成标准!D:D)*(G31<提成标准!E:E)),提成标准!C:C))) -> 快递小货 | D31: =IF(C31="快递小货",1,IF(C31="主营产品",0,G31)) -> 1 | E31: =_xlfn.XLOOKUP(C31,提成标准!C:C,提成标准!H:H,"") -> 2 | F31: =D31*E31 -> 2 | G31: =_xlfn.XLOOKUP(I31,过机服务商重量差!A:A,过机服务商重量差!L:L) -> 5.5 | H31: =IFERROR(LOOKUP(1,0/((B31=名单!B:B)*(VALUE(AY31)>=名单!E:E)*(VALUE(AY31)<=名单!G:G)*(AA31="正常走货")),名单!H:H),"否") -> 否 | I31: RSC3102 | J31: 1Z0E465J0419058000 | L31: OK-FDX-DHL-TNT | N31: 非主营 | U31: 汪祺 | V31: 营销二部 | AA31: 正常走货 | AQ31: 101.6 | AY31: 2026-01-31 20:56:04
A32: =MID(AY32,1,7) -> 2026-01 | B32: =_xlfn.XLOOKUP(I32,过机服务商重量差!A:A,过机服务商重量差!G:G) -> 玉麒麟 | C32: =IF(N32="FBA","主营产品",IF(N32="专线","专线",LOOKUP(1,0/((G32>=提成标准!D:D)*(G32<提成标准!E:E)),提成标准!C:C))) -> 快递小货 | D32: =IF(C32="快递小货",1,IF(C32="主营产品",0,G32)) -> 1 | E32: =_xlfn.XLOOKUP(C32,提成标准!C:C,提成标准!H:H,"") -> 2 | F32: =D32*E32 -> 2 | G32: =_xlfn.XLOOKUP(I32,过机服务商重量差!A:A,过机服务商重量差!L:L) -> 6.5 | H32: =IFERROR(LOOKUP(1,0/((B32=名单!B:B)*(VALUE(AY32)>=名单!E:E)*(VALUE(AY32)<=名单!G:G)*(AA32="正常走货")),名单!H:H),"否") -> 否 | I32: RSC3101 | J32: 1Z0E465J0415072448 | L32: OK-FDX-DHL-TNT | N32: 非主营 | U32: 汪祺 | V32: 营销二部 | AA32: 正常走货 | AQ32: 101.6 | AY32: 2026-01-31 20:55:58
A33: =MID(AY33,1,7) -> 2026-01 | B33: =_xlfn.XLOOKUP(I33,过机服务商重量差!A:A,过机服务商重量差!G:G) -> 玉麒麟 | C33: =IF(N33="FBA","主营产品",IF(N33="专线","专线",LOOKUP(1,0/((G33>=提成标准!D:D)*(G33<提成标准!E:E)),提成标准!C:C))) -> 快递大货 | D33: =IF(C33="快递小货",1,IF(C33="主营产品",0,G33)) -> 52 | E33: =_xlfn.XLOOKUP(C33,提成标准!C:C,提成标准!H:H,"") -> 0.1 | F33: =D33*E33 -> 5.2 | G33: =_xlfn.XLOOKUP(I33,过机服务商重量差!A:A,过机服务商重量差!L:L) -> 52 | H33: =IFERROR(LOOKUP(1,0/((B33=名单!B:B)*(VALUE(AY33)>=名单!E:E)*(VALUE(AY33)<=名单!G:G)*(AA33="正常走货")),名单!H:H),"否") -> 否 | I33: QLWJ1781704 | J33: 1Z0E793D0422717448 | L33: OK-UPS红单 | N33: 非主营 | U33: 宁春阳 | V33: 营销二部 | AA33: 正常走货 | AQ33: 421.1 | AY33: 2026-01-31 20:53:03
A34: =MID(AY34,1,7) -> 2026-01 | B34: =_xlfn.XLOOKUP(I34,过机服务商重量差!A:A,过机服务商重量差!G:G) -> 玉麒麟 | C34: =IF(N34="FBA","主营产品",IF(N34="专线","专线",LOOKUP(1,0/((G34>=提成标准!D:D)*(G34<提成标准!E:E)),提成标准!C:C))) -> 快递大货 | D34: =IF(C34="快递小货",1,IF(C34="主营产品",0,G34)) -> 29 | E34: =_xlfn.XLOOKUP(C34,提成标准!C:C,提成标准!H:H,"") -> 0.1 | F34: =D34*E34 -> 2.9 | G34: =_xlfn.XLOOKUP(I34,过机服务商重量差!A:A,过机服务商重量差!L:L) -> 29 | H34: =IFERROR(LOOKUP(1,0/((B34=名单!B:B)*(VALUE(AY34)>=名单!E:E)*(VALUE(AY34)<=名单!G:G)*(AA34="正常走货")),名单!H:H),"否") -> 否 | I34: JHZW7312 | J34: 888384610822 | L34: OK-FDX-DHL-TNT | N34: 非主营 | U34: 宋海周 | V34: 营销二部 | AA34: 正常走货 | AQ34: 101.64 | AY34: 2026-01-31 20:46:55
A35: =MID(AY35,1,7) -> 2026-01 | B35: =_xlfn.XLOOKUP(I35,过机服务商重量差!A:A,过机服务商重量差!G:G) -> 风清扬 | C35: =IF(N35="FBA","主营产品",IF(N35="专线","专线",LOOKUP(1,0/((G35>=提成标准!D:D)*(G35<提成标准!E:E)),提成标准!C:C))) -> 快递大货 | D35: =IF(C35="快递小货",1,IF(C35="主营产品",0,G35)) -> 27 | E35: =_xlfn.XLOOKUP(C35,提成标准!C:C,提成标准!H:H,"") -> 0.1 | F35: =D35*E35 -> 2.7 | G35: =_xlfn.XLOOKUP(I35,过机服务商重量差!A:A,过机服务商重量差!L:L) -> 27 | H35: =IFERROR(LOOKUP(1,0/((B35=名单!B:B)*(VALUE(AY35)>=名单!E:E)*(VALUE(AY35)<=名单!G:G)*(AA35="正常走货")),名单!H:H),"否") -> 否 | I35: SH0131-2 | J35: 1ZHF38642014756797 | L35: 加拿大准时达海派UPS | N35: 非主营 | U35: 小飞侠 | V35: 营销五部 | AA35: 正常走货 | AQ35: 377 | AY35: 2026-01-31 20:43:24
A36: =MID(AY36,1,7) -> 2026-01 | B36: =_xlfn.XLOOKUP(I36,过机服务商重量差!A:A,过机服务商重量差!G:G) -> 无崖子 | C36: {=IF(N36="FBA","主营产品",IF(N36="专线","专线",LOOKUP(1,0/((G36>=提成标准!D:D)*(G36<提成标准!E:E)),提成标准!C:C)))} -> 快递小货 | D36: =IF(C36="快递小货",1,IF(C36="主营产品",0,G36)) -> 1 | E36: =_xlfn.XLOOKUP(C36,提成标准!C:C,提成标准!H:H,"") -> 2 | F36: =D36*E36 -> 2 | G36: =_xlfn.XLOOKUP(I36,过机服务商重量差!A:A,过机服务商重量差!L:L) -> 7.5 | H36: =IFERROR(LOOKUP(1,0/((B36=名单!B:B)*(VALUE(AY36)>=名单!E:E)*(VALUE(AY36)<=名单!G:G)*(AA36="正常走货")),名单!H:H),"否") -> 是 | I36: JPS20260131002 | J36: CR431657742DE | L36: HST-UPS 6000 | N36: 非主营 | U36: 柴燕玲 | V36: 四部KA客服 | AA36: 正常走货 | AQ36: 225 | AY36: 2026-01-31 20:41:12
A37: =MID(AY37,1,7) -> 2026-01 | B37: =_xlfn.XLOOKUP(I37,过机服务商重量差!A:A,过机服务商重量差!G:G) -> 无崖子 | C37: =IF(N37="FBA","主营产品",IF(N37="专线","专线",LOOKUP(1,0/((G37>=提成标准!D:D)*(G37<提成标准!E:E)),提成标准!C:C))) -> 快递小货 | D37: =IF(C37="快递小货",1,IF(C37="主营产品",0,G37)) -> 1 | E37: =_xlfn.XLOOKUP(C37,提成标准!C:C,提成标准!H:H,"") -> 2 | F37: =D37*E37 -> 2 | G37: =_xlfn.XLOOKUP(I37,过机服务商重量差!A:A,过机服务商重量差!L:L) -> 6 | H37: =IFERROR(LOOKUP(1,0/((B37=名单!B:B)*(VALUE(AY37)>=名单!E:E)*(VALUE(AY37)<=名单!G:G)*(AA37="正常走货")),名单!H:H),"否") -> 是 | I37: JPS20260131001 | J37: CR431657314DE | L37: HST-UPS 6000 | N37: 非主营 | U37: 柴燕玲 | V37: 四部KA客服 | AA37: 正常走货 | AQ37: 229.36 | AY37: 2026-01-31 20:41:04
A38: =MID(AY38,1,7) -> 2026-01 | B38: =_xlfn.XLOOKUP(I38,过机服务商重量差!A:A,过机服务商重量差!G:G) -> 玉麒麟 | C38: =IF(N38="FBA","主营产品",IF(N38="专线","专线",LOOKUP(1,0/((G38>=提成标准!D:D)*(G38<提成标准!E:E)),提成标准!C:C))) -> 快递大货 | D38: =IF(C38="快递小货",1,IF(C38="主营产品",0,G38)) -> 25 | E38: =_xlfn.XLOOKUP(C38,提成标准!C:C,提成标准!H:H,"") -> 0.1 | F38: =D38*E38 -> 2.5 | G38: =_xlfn.XLOOKUP(I38,过机服务商重量差!A:A,过机服务商重量差!L:L) -> 25 | H38: =IFERROR(LOOKUP(1,0/((B38=名单!B:B)*(VALUE(AY38)>=名单!E:E)*(VALUE(AY38)<=名单!G:G)*(AA38="正常走货")),名单!H:H),"否") -> 否 | I38: PBI3-FBA19757N66N | J38: 1Z0E465J0407453337 | L38: OK-FDX-DHL-TNT | N38: 非主营 | U38: 李娟-业务 | V38: 营销四部 | AA38: 正常走货 | AQ38: 329.1 | AY38: 2026-01-31 20:40:50
A39: =MID(AY39,1,7) -> 2026-01 | B39: =_xlfn.XLOOKUP(I39,过机服务商重量差!A:A,过机服务商重量差!G:G) -> 帅时莹 | C39: =IF(N39="FBA","主营产品",IF(N39="专线","专线",LOOKUP(1,0/((G39>=提成标准!D:D)*(G39<提成标准!E:E)),提成标准!C:C))) -> 快递小货 | D39: =IF(C39="快递小货",1,IF(C39="主营产品",0,G39)) -> 1 | E39: =_xlfn.XLOOKUP(C39,提成标准!C:C,提成标准!H:H,"") -> 2 | F39: =D39*E39 -> 2 | G39: =_xlfn.XLOOKUP(I39,过机服务商重量差!A:A,过机服务商重量差!L:L) -> 3.5 | H39: =IFERROR(LOOKUP(1,0/((B39=名单!B:B)*(VALUE(AY39)>=名单!E:E)*(VALUE(AY39)<=名单!G:G)*(AA39="正常走货")),名单!H:H),"否") -> 否 | I39: 95T6963 | J39: 1ZG3333D0406480200 | L39: MSHQ-UPS | N39: 非主营 | U39: 李娟-业务 | V39: 营销四部 | AA39: 正常走货 | AQ39: 139.1 | AY39: 2026-01-31 20:40:36
A40: =MID(AY40,1,7) -> 2026-01 | B40: =_xlfn.XLOOKUP(I40,过机服务商重量差!A:A,过机服务商重量差!G:G) -> 风清扬 | C40: =IF(N40="FBA","主营产品",IF(N40="专线","专线",LOOKUP(1,0/((G40>=提成标准!D:D)*(G40<提成标准!E:E)),提成标准!C:C))) -> 快递大货 | D40: =IF(C40="快递小货",1,IF(C40="主营产品",0,G40)) -> 142 | E40: =_xlfn.XLOOKUP(C40,提成标准!C:C,提成标准!H:H,"") -> 0.1 | F40: =D40*E40 -> 14.2 | G40: =_xlfn.XLOOKUP(I40,过机服务商重量差!A:A,过机服务商重量差!L:L) -> 142 | H40: =IFERROR(LOOKUP(1,0/((B40=名单!B:B)*(VALUE(AY40)>=名单!E:E)*(VALUE(AY40)<=名单!G:G)*(AA40="正常走货")),名单!H:H),"否") -> 否 | I40: 24543733501033648 | J40: 881072500 | L40: 东南亚专线 | N40: 非主营 | U40: 丁佳伟 | V40: 营销三部 | AA40: 正常走货 | AQ40: 1361 | AY40: 2026-01-31 20:40:27
A41: =MID(AY41,1,7) -> 2026-01 | B41: =_xlfn.XLOOKUP(I41,过机服务商重量差!A:A,过机服务商重量差!G:G) -> 玉麒麟 | C41: =IF(N41="FBA","主营产品",IF(N41="专线","专线",LOOKUP(1,0/((G41>=提成标准!D:D)*(G41<提成标准!E:E)),提成标准!C:C))) -> 快递小货 | D41: =IF(C41="快递小货",1,IF(C41="主营产品",0,G41)) -> 1 | E41: =_xlfn.XLOOKUP(C41,提成标准!C:C,提成标准!H:H,"") -> 2 | F41: =D41*E41 -> 2 | G41: =_xlfn.XLOOKUP(I41,过机服务商重量差!A:A,过机服务商重量差!L:L) -> 5 | H41: =IFERROR(LOOKUP(1,0/((B41=名单!B:B)*(VALUE(AY41)>=名单!E:E)*(VALUE(AY41)<=名单!G:G)*(AA41="正常走货")),名单!H:H),"否") -> 否 | I41: TM260131-1FL1 | J41: 1Z4W260E0410561907 | L41: OK-FDX-DHL-TNT | N41: 非主营 | U41: 邓健群 | V41: 营销三部 | AA41: 正常走货 | AQ41: 91.2 | AY41: 2026-01-31 20:38:36
A42: =MID(AY42,1,7) -> 2026-01 | B42: =_xlfn.XLOOKUP(I42,过机服务商重量差!A:A,过机服务商重量差!G:G) -> 玉麒麟 | C42: =IF(N42="FBA","主营产品",IF(N42="专线","专线",LOOKUP(1,0/((G42>=提成标准!D:D)*(G42<提成标准!E:E)),提成标准!C:C))) -> 快递大货 | D42: =IF(C42="快递小货",1,IF(C42="主营产品",0,G42)) -> 25 | E42: =_xlfn.XLOOKUP(C42,提成标准!C:C,提成标准!H:H,"") -> 0.1 | F42: =D42*E42 -> 2.5 | G42: =_xlfn.XLOOKUP(I42,过机服务商重量差!A:A,过机服务商重量差!L:L) -> 25 | H42: =IFERROR(LOOKUP(1,0/((B42=名单!B:B)*(VALUE(AY42)>=名单!E:E)*(VALUE(AY42)<=名单!G:G)*(AA42="正常走货")),名单!H:H),"否") -> 否 | I42: AY-2274 | J42: 1ZA06B016812392639 | L42: OK-FDX-DHL-TNT | N42: 非主营 | U42: 王拥 | V42: 营销二部 | AA42: 正常走货 | AQ42: 267.5 | AY42: 2026-01-31 20:34:44
A43: =MID(AY43,1,7) -> 2026-01 | B43: =_xlfn.XLOOKUP(I43,过机服务商重量差!A:A,过机服务商重量差!G:G) -> 玉麒麟 | C43: =IF(N43="FBA","主营产品",IF(N43="专线","专线",LOOKUP(1,0/((G43>=提成标准!D:D)*(G43<提成标准!E:E)),提成标准!C:C))) -> 快递小货 | D43: =IF(C43="快递小货",1,IF(C43="主营产品",0,G43)) -> 1 | E43: =_xlfn.XLOOKUP(C43,提成标准!C:C,提成标准!H:H,"") -> 2 | F43: =D43*E43 -> 2 | G43: =_xlfn.XLOOKUP(I43,过机服务商重量差!A:A,过机服务商重量差!L:L) -> 4 | H43: =IFERROR(LOOKUP(1,0/((B43=名单!B:B)*(VALUE(AY43)>=名单!E:E)*(VALUE(AY43)<=名单!G:G)*(AA43="正常走货")),名单!H:H),"否") -> 否 | I43: DCSP-260131-1 | J43: 398309103634 | L43: OK-FDX-DHL-TNT | N43: 非主营 | U43: 王昌金 | V43: 营销一部 | AA43: 正常走货 | AQ43: 102.2 | AY43: 2026-01-31 20:33:07
A44: =MID(AY44,1,7) -> 2026-01 | B44: =_xlfn.XLOOKUP(I44,过机服务商重量差!A:A,过机服务商重量差!G:G) -> 无崖子 | C44: =IF(N44="FBA","主营产品",IF(N44="专线","专线",LOOKUP(1,0/((G44>=提成标准!D:D)*(G44<提成标准!E:E)),提成标准!C:C))) -> 快递小货 | D44: =IF(C44="快递小货",1,IF(C44="主营产品",0,G44)) -> 1 | E44: =_xlfn.XLOOKUP(C44,提成标准!C:C,提成标准!H:H,"") -> 2 | F44: =D44*E44 -> 2 | G44: =_xlfn.XLOOKUP(I44,过机服务商重量差!A:A,过机服务商重量差!L:L) -> 2 | H44: =IFERROR(LOOKUP(1,0/((B44=名单!B:B)*(VALUE(AY44)>=名单!E:E)*(VALUE(AY44)<=名单!G:G)*(AA44="正常走货")),名单!H:H),"否") -> 是 | I44: NAT260131US-01 | J44: 398309210400 | L44: FEDEX速快美国包税6000 | N44: 非主营 | U44: 冯青青 | V44: 营销五部 | AA44: 正常走货 | AQ44: 0 | AY44: 2026-01-31 20:32:11
A45: =MID(AY45,1,7) -> 2026-01 | B45: =_xlfn.XLOOKUP(I45,过机服务商重量差!A:A,过机服务商重量差!G:G) -> 无崖子 | C45: =IF(N45="FBA","主营产品",IF(N45="专线","专线",LOOKUP(1,0/((G45>=提成标准!D:D)*(G45<提成标准!E:E)),提成标准!C:C))) -> 快递小货 | D45: =IF(C45="快递小货",1,IF(C45="主营产品",0,G45)) -> 1 | E45: =_xlfn.XLOOKUP(C45,提成标准!C:C,提成标准!H:H,"") -> 2 | F45: =D45*E45 -> 2 | G45: =_xlfn.XLOOKUP(I45,过机服务商重量差!A:A,过机服务商重量差!L:L) -> 2.5 | H45: =IFERROR(LOOKUP(1,0/((B45=名单!B:B)*(VALUE(AY45)>=名单!E:E)*(VALUE(AY45)<=名单!G:G)*(AA45="正常走货")),名单!H:H),"否") -> 是 | I45: NAF260129US-01 | J45: 398309185163 | L45: FEDEX速快美国包税6000 | N45: 非主营 | U45: 冯青青 | V45: 营销五部 | AA45: 正常走货 | AQ45: 0 | AY45: 2026-01-31 20:32:00
A46: =MID(AY46,1,7) -> 2026-01 | B46: =_xlfn.XLOOKUP(I46,过机服务商重量差!A:A,过机服务商重量差!G:G) -> 007 | C46: =IF(N46="FBA","主营产品",IF(N46="专线","专线",LOOKUP(1,0/((G46>=提成标准!D:D)*(G46<提成标准!E:E)),提成标准!C:C))) -> 快递小货 | D46: =IF(C46="快递小货",1,IF(C46="主营产品",0,G46)) -> 1 | E46: =_xlfn.XLOOKUP(C46,提成标准!C:C,提成标准!H:H,"") -> 2 | F46: =D46*E46 -> 2 | G46: =_xlfn.XLOOKUP(I46,过机服务商重量差!A:A,过机服务商重量差!L:L) -> 12 | H46: =IFERROR(LOOKUP(1,0/((B46=名单!B:B)*(VALUE(AY46)>=名单!E:E)*(VALUE(AY46)<=名单!G:G)*(AA46="正常走货")),名单!H:H),"否") -> 否 | I46: NAE251223IT-01 | J46: 1Z0R6D926808379429 | L46: 欧洲卡航含税(快递派) | N46: 非主营 | U46: 冯青青 | V46: 营销五部 | AA46: 正常走货 | AQ46: 290 | AY46: 2026-01-31 20:31:53
A47: =MID(AY47,1,7) -> 2026-01 | B47: =_xlfn.XLOOKUP(I47,过机服务商重量差!A:A,过机服务商重量差!G:G) -> 小旋风 | C47: =IF(N47="FBA","主营产品",IF(N47="专线","专线",LOOKUP(1,0/((G47>=提成标准!D:D)*(G47<提成标准!E:E)),提成标准!C:C))) -> 快递大货 | D47: =IF(C47="快递小货",1,IF(C47="主营产品",0,G47)) -> 30 | E47: =_xlfn.XLOOKUP(C47,提成标准!C:C,提成标准!H:H,"") -> 0.1 | F47: =D47*E47 -> 3 | G47: =_xlfn.XLOOKUP(I47,过机服务商重量差!A:A,过机服务商重量差!L:L) -> 30 | H47: =IFERROR(LOOKUP(1,0/((B47=名单!B:B)*(VALUE(AY47)>=名单!E:E)*(VALUE(AY47)<=名单!G:G)*(AA47="正常走货")),名单!H:H),"否") -> 否 | I47: SYFS0131-1 | J47: 1ZA06B016818065580 | L47: 欧洲德国清专线 | N47: 非主营 | U47: 汪祺 | V47: 营销二部 | AA47: 正常走货 | AQ47: 1441.5 | AY47: 2026-01-31 20:31:43
A48: =MID(AY48,1,7) -> 2026-01 | B48: =_xlfn.XLOOKUP(I48,过机服务商重量差!A:A,过机服务商重量差!G:G) -> 玉麒麟 | C48: =IF(N48="FBA","主营产品",IF(N48="专线","专线",LOOKUP(1,0/((G48>=提成标准!D:D)*(G48<提成标准!E:E)),提成标准!C:C))) -> 快递小货 | D48: =IF(C48="快递小货",1,IF(C48="主营产品",0,G48)) -> 1 | E48: =_xlfn.XLOOKUP(C48,提成标准!C:C,提成标准!H:H,"") -> 2 | F48: =D48*E48 -> 2 | G48: =_xlfn.XLOOKUP(I48,过机服务商重量差!A:A,过机服务商重量差!L:L) -> 8.5 | H48: =IFERROR(LOOKUP(1,0/((B48=名单!B:B)*(VALUE(AY48)>=名单!E:E)*(VALUE(AY48)<=名单!G:G)*(AA48="正常走货")),名单!H:H),"否") -> 否 | I48: ZAMY01311553 | J48: 1Z0E465J0411470917 | L48: OK-FDX-DHL-TNT | N48: 非主营 | U48: 冯青青 | V48: 营销五部 | AA48: 正常走货 | AQ48: 49.8 | AY48: 2026-01-31 20:27:10
A49: =MID(AY49,1,7) -> 2026-01 | B49: =_xlfn.XLOOKUP(I49,过机服务商重量差!A:A,过机服务商重量差!G:G) -> 007 | C49: =IF(N49="FBA","主营产品",IF(N49="专线","专线",LOOKUP(1,0/((G49>=提成标准!D:D)*(G49<提成标准!E:E)),提成标准!C:C))) -> 快递大货 | D49: =IF(C49="快递小货",1,IF(C49="主营产品",0,G49)) -> 55 | E49: =_xlfn.XLOOKUP(C49,提成标准!C:C,提成标准!H:H,"") -> 0.1 | F49: =D49*E49 -> 5.5 | G49: =_xlfn.XLOOKUP(I49,过机服务商重量差!A:A,过机服务商重量差!L:L) -> 55 | H49: =IFERROR(LOOKUP(1,0/((B49=名单!B:B)*(VALUE(AY49)>=名单!E:E)*(VALUE(AY49)<=名单!G:G)*(AA49="正常走货")),名单!H:H),"否") -> 否 | I49: LM-056 | J49: 1Z0R6D926806701789 | L49: 欧洲卡航含税(快递派) | N49: 非主营 | U49: 张小雪 | V49: 营销五部 | AA49: 正常走货 | AQ49: 770 | AY49: 2026-01-31 20:26:38
A50: =MID(AY50,1,7) -> 2026-01 | B50: =_xlfn.XLOOKUP(I50,过机服务商重量差!A:A,过机服务商重量差!G:G) -> 无崖子 | C50: =IF(N50="FBA","主营产品",IF(N50="专线","专线",LOOKUP(1,0/((G50>=提成标准!D:D)*(G50<提成标准!E:E)),提成标准!C:C))) -> 快递大货 | D50: =IF(C50="快递小货",1,IF(C50="主营产品",0,G50)) -> 118 | E50: =_xlfn.XLOOKUP(C50,提成标准!C:C,提成标准!H:H,"") -> 0.1 | F50: =D50*E50 -> 11.8 | G50: =_xlfn.XLOOKUP(I50,过机服务商重量差!A:A,过机服务商重量差!L:L) -> 118 | H50: =IFERROR(LOOKUP(1,0/((B50=名单!B:B)*(VALUE(AY50)>=名单!E:E)*(VALUE(AY50)<=名单!G:G)*(AA50="正常走货")),名单!H:H),"否") -> 否 | I50: YKZXX0131 | L50: 义乌联邦IE-包税 | N50: 非主营 | U50: 张小雪 | V50: 营销五部 | AA50: 已退件 | AQ50: 0 | AY50: 2026-01-31 20:17:55
A51: =MID(AY51,1,7) -> 2026-01 | B51: =_xlfn.XLOOKUP(I51,过机服务商重量差!A:A,过机服务商重量差!G:G) -> 帅时莹 | C51: =IF(N51="FBA","主营产品",IF(N51="专线","专线",LOOKUP(1,0/((G51>=提成标准!D:D)*(G51<提成标准!E:E)),提成标准!C:C))) -> 快递大货 | D51: =IF(C51="快递小货",1,IF(C51="主营产品",0,G51)) -> 82 | E51: =_xlfn.XLOOKUP(C51,提成标准!C:C,提成标准!H:H,"") -> 0.1 | F51: =D51*E51 -> 8.2 | G51: =_xlfn.XLOOKUP(I51,过机服务商重量差!A:A,过机服务商重量差!L:L) -> 82 | H51: =IFERROR(LOOKUP(1,0/((B51=名单!B:B)*(VALUE(AY51)>=名单!E:E)*(VALUE(AY51)<=名单!G:G)*(AA51="正常走货")),名单!H:H),"否") -> 否 | I51: HJ25613101 | J51: 888401830517 | L51: JRGJ-专线 | N51: 非主营 | U51: 李凤 | V51: 营销四部 | AA51: 正常走货 | AQ51: 284 | AY51: 2026-01-31 20:11:57
A52: =MID(AY52,1,7) -> 2026-01 | B52: =_xlfn.XLOOKUP(I52,过机服务商重量差!A:A,过机服务商重量差!G:G) -> 无崖子 | C52: =IF(N52="FBA","主营产品",IF(N52="专线","专线",LOOKUP(1,0/((G52>=提成标准!D:D)*(G52<提成标准!E:E)),提成标准!C:C))) -> 快递小货 | D52: =IF(C52="快递小货",1,IF(C52="主营产品",0,G52)) -> 1 | E52: =_xlfn.XLOOKUP(C52,提成标准!C:C,提成标准!H:H,"") -> 2 | F52: =D52*E52 -> 2 | G52: =_xlfn.XLOOKUP(I52,过机服务商重量差!A:A,过机服务商重量差!L:L) -> 12.5 | H52: =IFERROR(LOOKUP(1,0/((B52=名单!B:B)*(VALUE(AY52)>=名单!E:E)*(VALUE(AY52)<=名单!G:G)*(AA52="正常走货")),名单!H:H),"否") -> 是 | I52: 29G6T9 | J52: CR431656565DE | L52: HST-UPS 6000 | N52: 非主营 | U52: 李可 | V52: 营销四部 | AA52: 正常走货 | AQ52: 176.56 | AY52: 2026-01-31 20:06:50
A53: =MID(AY53,1,7) -> 2026-01 | B53: =_xlfn.XLOOKUP(I53,过机服务商重量差!A:A,过机服务商重量差!G:G) -> 风清扬 | C53: =IF(N53="FBA","主营产品",IF(N53="专线","专线",LOOKUP(1,0/((G53>=提成标准!D:D)*(G53<提成标准!E:E)),提成标准!C:C))) -> 快递大货 | D53: =IF(C53="快递小货",1,IF(C53="主营产品",0,G53)) -> 1571 | E53: =_xlfn.XLOOKUP(C53,提成标准!C:C,提成标准!H:H,"") -> 0.1 | F53: =D53*E53 -> 157.1 | G53: =_xlfn.XLOOKUP(I53,过机服务商重量差!A:A,过机服务商重量差!L:L) -> 1571 | H53: =IFERROR(LOOKUP(1,0/((B53=名单!B:B)*(VALUE(AY53)>=名单!E:E)*(VALUE(AY53)<=名单!G:G)*(AA53="正常走货")),名单!H:H),"否") -> 否 | I53: UES260100104 | J53: KP | L53: 美转加快提卡派(HEDE) | N53: 非主营 | U53: 张小雪 | V53: 营销五部 | AA53: 正常走货 | AQ53: 25028 | AY53: 2026-01-31 20:02:23
A54: =MID(AY54,1,7) -> 2026-01 | B54: =_xlfn.XLOOKUP(I54,过机服务商重量差!A:A,过机服务商重量差!G:G) -> 无崖子 | C54: =IF(N54="FBA","主营产品",IF(N54="专线","专线",LOOKUP(1,0/((G54>=提成标准!D:D)*(G54<提成标准!E:E)),提成标准!C:C))) -> 快递小货 | D54: =IF(C54="快递小货",1,IF(C54="主营产品",0,G54)) -> 1 | E54: =_xlfn.XLOOKUP(C54,提成标准!C:C,提成标准!H:H,"") -> 2 | F54: =D54*E54 -> 2 | G54: =_xlfn.XLOOKUP(I54,过机服务商重量差!A:A,过机服务商重量差!L:L) -> 0.5 | H54: =IFERROR(LOOKUP(1,0/((B54=名单!B:B)*(VALUE(AY54)>=名单!E:E)*(VALUE(AY54)<=名单!G:G)*(AA54="正常走货")),名单!H:H),"否") -> 是 | I54: DS260131-90015 | J54: 888393849785 | L54: 义乌联邦FICP-包税 | N54: 非主营 | U54: 臧明 | V54: 北苑总经办 | AA54: 正常走货 | AQ54: 0 | AY54: 2026-01-31 19:55:43
A55: =MID(AY55,1,7) -> 2026-01 | B55: =_xlfn.XLOOKUP(I55,过机服务商重量差!A:A,过机服务商重量差!G:G) -> 玉麒麟 | C55: =IF(N55="FBA","主营产品",IF(N55="专线","专线",LOOKUP(1,0/((G55>=提成标准!D:D)*(G55<提成标准!E:E)),提成标准!C:C))) -> 快递小货 | D55: =IF(C55="快递小货",1,IF(C55="主营产品",0,G55)) -> 1 | E55: =_xlfn.XLOOKUP(C55,提成标准!C:C,提成标准!H:H,"") -> 2 | F55: =D55*E55 -> 2 | G55: =_xlfn.XLOOKUP(I55,过机服务商重量差!A:A,过机服务商重量差!L:L) -> 0.5 | H55: =IFERROR(LOOKUP(1,0/((B55=名单!B:B)*(VALUE(AY55)>=名单!E:E)*(VALUE(AY55)<=名单!G:G)*(AA55="正常走货")),名单!H:H),"否") -> 否 | I55: NS0131 | J55: 888386680111 | L55: OK-FDX-DHL-TNT | N55: 非主营 | U55: 付乐航 | V55: 营销五部 | AA55: 正常走货 | AQ55: 69.81 | AY55: 2026-01-31 19:55:35
A56: =MID(AY56,1,7) -> 2026-01 | B56: =_xlfn.XLOOKUP(I56,过机服务商重量差!A:A,过机服务商重量差!G:G) -> 无崖子 | C56: =IF(N56="FBA","主营产品",IF(N56="专线","专线",LOOKUP(1,0/((G56>=提成标准!D:D)*(G56<提成标准!E:E)),提成标准!C:C))) -> 快递小货 | D56: =IF(C56="快递小货",1,IF(C56="主营产品",0,G56)) -> 1 | E56: =_xlfn.XLOOKUP(C56,提成标准!C:C,提成标准!H:H,"") -> 2 | F56: =D56*E56 -> 2 | G56: =_xlfn.XLOOKUP(I56,过机服务商重量差!A:A,过机服务商重量差!L:L) -> 0.5 | H56: =IFERROR(LOOKUP(1,0/((B56=名单!B:B)*(VALUE(AY56)>=名单!E:E)*(VALUE(AY56)<=名单!G:G)*(AA56="正常走货")),名单!H:H),"否") -> 是 | I56: D20260131-1 | J56: 398309170150 | L56: FEDEX速快美国包税6000 | N56: 非主营 | U56: 施建祥 | V56: 营销三部 | AA56: 正常走货 | AQ56: 0 | AY56: 2026-01-31 19:55:30
A57: =MID(AY57,1,7) -> 2026-01 | B57: =_xlfn.XLOOKUP(I57,过机服务商重量差!A:A,过机服务商重量差!G:G) -> 玉麒麟 | C57: =IF(N57="FBA","主营产品",IF(N57="专线","专线",LOOKUP(1,0/((G57>=提成标准!D:D)*(G57<提成标准!E:E)),提成标准!C:C))) -> 快递小货 | D57: =IF(C57="快递小货",1,IF(C57="主营产品",0,G57)) -> 1 | E57: =_xlfn.XLOOKUP(C57,提成标准!C:C,提成标准!H:H,"") -> 2 | F57: =D57*E57 -> 2 | G57: =_xlfn.XLOOKUP(I57,过机服务商重量差!A:A,过机服务商重量差!L:L) -> 7 | H57: =IFERROR(LOOKUP(1,0/((B57=名单!B:B)*(VALUE(AY57)>=名单!E:E)*(VALUE(AY57)<=名单!G:G)*(AA57="正常走货")),名单!H:H),"否") -> 否 | I57: MWR26131-1 | J57: 1Z4W260E0402266135 | L57: OK-UPS红单 | N57: 非主营 | U57: 徐建 | V57: 营销三部 | AA57: 正常走货 | AQ57: 43.3 | AY57: 2026-01-31 19:54:51
A58: =MID(AY58,1,7) -> 2026-01 | B58: =_xlfn.XLOOKUP(I58,过机服务商重量差!A:A,过机服务商重量差!G:G) -> 007 | C58: =IF(N58="FBA","主营产品",IF(N58="专线","专线",LOOKUP(1,0/((G58>=提成标准!D:D)*(G58<提成标准!E:E)),提成标准!C:C))) -> 快递大货 | D58: =IF(C58="快递小货",1,IF(C58="主营产品",0,G58)) -> 35 | E58: =_xlfn.XLOOKUP(C58,提成标准!C:C,提成标准!H:H,"") -> 0.1 | F58: =D58*E58 -> 3.5 | G58: =_xlfn.XLOOKUP(I58,过机服务商重量差!A:A,过机服务商重量差!L:L) -> 35 | H58: =IFERROR(LOOKUP(1,0/((B58=名单!B:B)*(VALUE(AY58)>=名单!E:E)*(VALUE(AY58)<=名单!G:G)*(AA58="正常走货")),名单!H:H),"否") -> 否 | I58: YQ131CZ-1 | J58: 1Z0R6D926809022365 | L58: 欧洲卡航含税(快递派) | N58: 非主营 | U58: 张俊合 | V58: 营销五部 | AA58: 正常走货 | AQ58: 490 | AY58: 2026-01-31 19:47:27
A59: =MID(AY59,1,7) -> 2026-01 | B59: =_xlfn.XLOOKUP(I59,过机服务商重量差!A:A,过机服务商重量差!G:G) -> 玉麒麟 | C59: =IF(N59="FBA","主营产品",IF(N59="专线","专线",LOOKUP(1,0/((G59>=提成标准!D:D)*(G59<提成标准!E:E)),提成标准!C:C))) -> 快递小货 | D59: =IF(C59="快递小货",1,IF(C59="主营产品",0,G59)) -> 1 | E59: =_xlfn.XLOOKUP(C59,提成标准!C:C,提成标准!H:H,"") -> 2 | F59: =D59*E59 -> 2 | G59: =_xlfn.XLOOKUP(I59,过机服务商重量差!A:A,过机服务商重量差!L:L) -> 3.5 | H59: =IFERROR(LOOKUP(1,0/((B59=名单!B:B)*(VALUE(AY59)>=名单!E:E)*(VALUE(AY59)<=名单!G:G)*(AA59="正常走货")),名单!H:H),"否") -> 否 | I59: PTYL-131T | J59: 1Z4W260E0409162127 | L59: OK-FDX-DHL-TNT | N59: 非主营 | U59: 汪礼平 | V59: 营销一部 | AA59: 正常走货 | AQ59: 62.5 | AY59: 2026-01-31 19:47:08
A60: =MID(AY60,1,7) -> 2026-01 | B60: =_xlfn.XLOOKUP(I60,过机服务商重量差!A:A,过机服务商重量差!G:G) -> 帅时莹 | C60: =IF(N60="FBA","主营产品",IF(N60="专线","专线",LOOKUP(1,0/((G60>=提成标准!D:D)*(G60<提成标准!E:E)),提成标准!C:C))) -> 快递大货 | D60: =IF(C60="快递小货",1,IF(C60="主营产品",0,G60)) -> 131 | E60: =_xlfn.XLOOKUP(C60,提成标准!C:C,提成标准!H:H,"") -> 0.1 | F60: =D60*E60 -> 13.1 | G60: =_xlfn.XLOOKUP(I60,过机服务商重量差!A:A,过机服务商重量差!L:L) -> 131 | H60: =IFERROR(LOOKUP(1,0/((B60=名单!B:B)*(VALUE(AY60)>=名单!E:E)*(VALUE(AY60)<=名单!G:G)*(AA60="正常走货")),名单!H:H),"否") -> 否 | I60: HY260131-NL-9 | J60: 1ZF4K3596803870460 | L60: 欧洲专线-HMC | N60: 非主营 | U60: 朱杰 | V60: 营销四部 | AA60: 正常走货 | AQ60: 1650 | AY60: 2026-01-31 19:46:55
A61: =MID(AY61,1,7) -> 2026-01 | B61: =_xlfn.XLOOKUP(I61,过机服务商重量差!A:A,过机服务商重量差!G:G) -> 玉麒麟 | C61: =IF(N61="FBA","主营产品",IF(N61="专线","专线",LOOKUP(1,0/((G61>=提成标准!D:D)*(G61<提成标准!E:E)),提成标准!C:C))) -> 快递小货 | D61: =IF(C61="快递小货",1,IF(C61="主营产品",0,G61)) -> 1 | E61: =_xlfn.XLOOKUP(C61,提成标准!C:C,提成标准!H:H,"") -> 2 | F61: =D61*E61 -> 2 | G61: =_xlfn.XLOOKUP(I61,过机服务商重量差!A:A,过机服务商重量差!L:L) -> 7 | H61: =IFERROR(LOOKUP(1,0/((B61=名单!B:B)*(VALUE(AY61)>=名单!E:E)*(VALUE(AY61)<=名单!G:G)*(AA61="正常走货")),名单!H:H),"否") -> 否 | I61: 5ME9963WS | J61: 1Z0E620D0435857753 | L61: OK-FDX-DHL-TNT | N61: 非主营 | U61: 王岩岩 | V61: 营销四部 | AA61: 正常走货 | AQ61: 61.63 | AY61: 2026-01-31 19:43:27
A62: =MID(AY62,1,7) -> 2026-01 | B62: =_xlfn.XLOOKUP(I62,过机服务商重量差!A:A,过机服务商重量差!G:G) -> 风清扬 | C62: =IF(N62="FBA","主营产品",IF(N62="专线","专线",LOOKUP(1,0/((G62>=提成标准!D:D)*(G62<提成标准!E:E)),提成标准!C:C))) -> 快递大货 | D62: =IF(C62="快递小货",1,IF(C62="主营产品",0,G62)) -> 39 | E62: =_xlfn.XLOOKUP(C62,提成标准!C:C,提成标准!H:H,"") -> 0.1 | F62: =D62*E62 -> 3.9 | G62: =_xlfn.XLOOKUP(I62,过机服务商重量差!A:A,过机服务商重量差!L:L) -> 39 | H62: =IFERROR(LOOKUP(1,0/((B62=名单!B:B)*(VALUE(AY62)>=名单!E:E)*(VALUE(AY62)<=名单!G:G)*(AA62="正常走货")),名单!H:H),"否") -> 否 | I62: BSMY20260131-2 | J62: 1Z0R6D896822740883 | L62: 欧洲快船-JT | N62: 非主营 | U62: 叶伟明 | V62: 营销一部 | AA62: 正常走货 | AQ62: 273.9 | AY62: 2026-01-31 19:40:56
... A88: =MID(AY88,1,7) -> 2026-01 | B88: =_xlfn.XLOOKUP(I88,过机服务商重量差!A:A,过机服务商重量差!G:G) -> 风清扬 | C88: =IF(N88="FBA","主营产品",IF(N88="专线","专线",LOOKUP(1,0/((G88>=提成标准!D:D)*(G88<提成标准!E:E)),提成标准!C:C))) -> 快递大货 | D88: =IF(C88="快递小货",1,IF(C88="主营产品",0,G88)) -> 553 | E88: =_xlfn.XLOOKUP(C88,提成标准!C:C,提成标准!H:H,"") -> 0.1 | F88: =D88*E88 -> 55.3 | G88: =_xlfn.XLOOKUP(I88,过机服务商重量差!A:A,过机服务商重量差!L:L) -> 553 | H88: =IFERROR(LOOKUP(1,0/((B88=名单!B:B)*(VALUE(AY88)>=名单!E:E)*(VALUE(AY88)<=名单!G:G)*(AA88="正常走货")),名单!H:H),"否") -> 否 | I88: LKS-PO8302-51 | J88: KP | L88: 加拿大海派-JY | N88: 非主营 | U88: 马淞浦 | V88: 营销一部 | AA88: 正常走货 | AQ88: -1637.8 | AY88: 2026-01-31 18:24:31
A89: =MID(AY89,1,7) -> 2026-01 | B89: =_xlfn.XLOOKUP(I89,过机服务商重量差!A:A,过机服务商重量差!G:G) | C89: =IF(N89="FBA","主营产品",IF(N89="专线","专线",LOOKUP(1,0/((G89>=提成标准!D:D)*(G89<提成标准!E:E)),提成标准!C:C))) -> 快递大货 | D89: =IF(C89="快递小货",1,IF(C89="主营产品",0,G89)) -> 2885 | E89: =_xlfn.XLOOKUP(C89,提成标准!C:C,提成标准!H:H,"") -> 0.1 | F89: =D89*E89 -> 288.5 | G89: =_xlfn.XLOOKUP(I89,过机服务商重量差!A:A,过机服务商重量差!L:L) -> 2885 | H89: =IFERROR(LOOKUP(1,0/((B89=名单!B:B)*(VALUE(AY89)>=名单!E:E)*(VALUE(AY89)<=名单!G:G)*(AA89="正常走货")),名单!H:H),"否") -> 否 | I89: FL-260130A | L89: 美国WP | N89: 非主营 | U89: 陈炎 | V89: 营销二部 | AA89: 正常走货 | AQ89: 8631 | AY89: 2026-01-31 18:22:36
A90: =MID(AY90,1,7) -> 2026-01 | B90: =_xlfn.XLOOKUP(I90,过机服务商重量差!A:A,过机服务商重量差!G:G) -> 风清扬 | C90: =IF(N90="FBA","主营产品",IF(N90="专线","专线",LOOKUP(1,0/((G90>=提成标准!D:D)*(G90<提成标准!E:E)),提成标准!C:C))) -> 快递大货 | D90: =IF(C90="快递小货",1,IF(C90="主营产品",0,G90)) -> 21 | E90: =_xlfn.XLOOKUP(C90,提成标准!C:C,提成标准!H:H,"") -> 0.1 | F90: =D90*E90 -> 2.1 | G90: =_xlfn.XLOOKUP(I90,过机服务商重量差!A:A,过机服务商重量差!L:L) -> 21 | H90: =IFERROR(LOOKUP(1,0/((B90=名单!B:B)*(VALUE(AY90)>=名单!E:E)*(VALUE(AY90)<=名单!G:G)*(AA90="正常走货")),名单!H:H),"否") -> 否 | I90: HL26131-1 | J90: 1ZHF05572014691146 | L90: 加拿大空派-大陆飞-UPS派送/6000 | N90: 非主营 | U90: 丁佳伟 | V90: 营销三部 | AA90: 正常走货 | AQ90: 0 | AY90: 2026-01-31 18:17:30
A91: =MID(AY91,1,7) -> 2026-01 | B91: =_xlfn.XLOOKUP(I91,过机服务商重量差!A:A,过机服务商重量差!G:G) -> 无崖子 | C91: =IF(N91="FBA","主营产品",IF(N91="专线","专线",LOOKUP(1,0/((G91>=提成标准!D:D)*(G91<提成标准!E:E)),提成标准!C:C))) -> 快递小货 | D91: =IF(C91="快递小货",1,IF(C91="主营产品",0,G91)) -> 1 | E91: =_xlfn.XLOOKUP(C91,提成标准!C:C,提成标准!H:H,"") -> 2 | F91: =D91*E91 -> 2 | G91: =_xlfn.XLOOKUP(I91,过机服务商重量差!A:A,过机服务商重量差!L:L) -> 1.5 | H91: =IFERROR(LOOKUP(1,0/((B91=名单!B:B)*(VALUE(AY91)>=名单!E:E)*(VALUE(AY91)<=名单!G:G)*(AA91="正常走货")),名单!H:H),"否") -> 是 | I91: GB0131-DE | J91: 888382928543 | L91: 上海FEDEX-P价IP | N91: 非主营 | U91: 陈颖 | V91: 营销五部 | AA91: 正常走货 | AQ91: -1.06 | AY91: 2026-01-31 18:17:22
A92: =MID(AY92,1,7) -> 2026-01 | B92: =_xlfn.XLOOKUP(I92,过机服务商重量差!A:A,过机服务商重量差!G:G) -> 007 | C92: =IF(N92="FBA","主营产品",IF(N92="专线","专线",LOOKUP(1,0/((G92>=提成标准!D:D)*(G92<提成标准!E:E)),提成标准!C:C))) -> 快递大货 | D92: =IF(C92="快递小货",1,IF(C92="主营产品",0,G92)) -> 57 | E92: =_xlfn.XLOOKUP(C92,提成标准!C:C,提成标准!H:H,"") -> 0.1 | F92: =D92*E92 -> 5.7 | G92: =_xlfn.XLOOKUP(I92,过机服务商重量差!A:A,过机服务商重量差!L:L) -> 57 | H92: =IFERROR(LOOKUP(1,0/((B92=名单!B:B)*(VALUE(AY92)>=名单!E:E)*(VALUE(AY92)<=名单!G:G)*(AA92="正常走货")),名单!H:H),"否") -> 否 | I92: FBA15LDBQTGT | J92: 1Z0R6D926808645944 | L92: 欧洲卡航含税(快递派) | N92: 非主营 | U92: 小飞侠 | V92: 营销五部 | AA92: 正常走货 | AQ92: 655.5 | AY92: 2026-01-31 18:17:16
A93: =MID(AY93,1,7) -> 2026-01 | B93: =_xlfn.XLOOKUP(I93,过机服务商重量差!A:A,过机服务商重量差!G:G) -> 无崖子 | C93: =IF(N93="FBA","主营产品",IF(N93="专线","专线",LOOKUP(1,0/((G93>=提成标准!D:D)*(G93<提成标准!E:E)),提成标准!C:C))) -> 快递小货 | D93: =IF(C93="快递小货",1,IF(C93="主营产品",0,G93)) -> 1 | E93: =_xlfn.XLOOKUP(C93,提成标准!C:C,提成标准!H:H,"") -> 2 | F93: =D93*E93 -> 2 | G93: =_xlfn.XLOOKUP(I93,过机服务商重量差!A:A,过机服务商重量差!L:L) -> 3 | H93: =IFERROR(LOOKUP(1,0/((B93=名单!B:B)*(VALUE(AY93)>=名单!E:E)*(VALUE(AY93)<=名单!G:G)*(AA93="正常走货")),名单!H:H),"否") -> 是 | I93: GB0131-US01 | J93: 398309225951 | L93: FEDEX速快美国包税6000 | N93: 非主营 | U93: 陈颖 | V93: 营销五部 | AA93: 正常走货 | AQ93: 0 | AY93: 2026-01-31 18:16:44
A94: =MID(AY94,1,7) -> 2026-01 | B94: =_xlfn.XLOOKUP(I94,过机服务商重量差!A:A,过机服务商重量差!G:G) -> 玉麒麟 | C94: =IF(N94="FBA","主营产品",IF(N94="专线","专线",LOOKUP(1,0/((G94>=提成标准!D:D)*(G94<提成标准!E:E)),提成标准!C:C))) -> 快递大货 | D94: =IF(C94="快递小货",1,IF(C94="主营产品",0,G94)) -> 70 | E94: =_xlfn.XLOOKUP(C94,提成标准!C:C,提成标准!H:H,"") -> 0.1 | F94: =D94*E94 -> 7 | G94: =_xlfn.XLOOKUP(I94,过机服务商重量差!A:A,过机服务商重量差!L:L) -> 70 | H94: =IFERROR(LOOKUP(1,0/((B94=名单!B:B)*(VALUE(AY94)>=名单!E:E)*(VALUE(AY94)<=名单!G:G)*(AA94="正常走货")),名单!H:H),"否") -> 否 | I94: WLXB-3GB-1 | J94: 888384608580 | L94: OK-FDX-DHL-TNT | N94: 非主营 | U94: 邓健群 | V94: 营销三部 | AA94: 正常走货 | AQ94: 710.58 | AY94: 2026-01-31 18:16:27
A95: =MID(AY95,1,7) -> 2026-01 | B95: =_xlfn.XLOOKUP(I95,过机服务商重量差!A:A,过机服务商重量差!G:G) -> 玉麒麟 | C95: =IF(N95="FBA","主营产品",IF(N95="专线","专线",LOOKUP(1,0/((G95>=提成标准!D:D)*(G95<提成标准!E:E)),提成标准!C:C))) -> 快递大货 | D95: =IF(C95="快递小货",1,IF(C95="主营产品",0,G95)) -> 69 | E95: =_xlfn.XLOOKUP(C95,提成标准!C:C,提成标准!H:H,"") -> 0.1 | F95: =D95*E95 -> 6.9 | G95: =_xlfn.XLOOKUP(I95,过机服务商重量差!A:A,过机服务商重量差!L:L) -> 69 | H95: =IFERROR(LOOKUP(1,0/((B95=名单!B:B)*(VALUE(AY95)>=名单!E:E)*(VALUE(AY95)<=名单!G:G)*(AA95="正常走货")),名单!H:H),"否") -> 否 | I95: WLXB-3GB-2 | J95: 888386159189 | L95: OK-FDX-DHL-TNT | N95: 非主营 | U95: 邓健群 | V95: 营销三部 | AA95: 正常走货 | AQ95: 805.17 | AY95: 2026-01-31 18:16:03
A96: =MID(AY96,1,7) -> 2026-01 | B96: =_xlfn.XLOOKUP(I96,过机服务商重量差!A:A,过机服务商重量差!G:G) -> 风清扬 | C96: =IF(N96="FBA","主营产品",IF(N96="专线","专线",LOOKUP(1,0/((G96>=提成标准!D:D)*(G96<提成标准!E:E)),提成标准!C:C))) -> 快递大货 | D96: =IF(C96="快递小货",1,IF(C96="主营产品",0,G96)) -> 423 | E96: =_xlfn.XLOOKUP(C96,提成标准!C:C,提成标准!H:H,"") -> 0.1 | F96: =D96*E96 -> 42.3 | G96: =_xlfn.XLOOKUP(I96,过机服务商重量差!A:A,过机服务商重量差!L:L) -> 423 | H96: =IFERROR(LOOKUP(1,0/((B96=名单!B:B)*(VALUE(AY96)>=名单!E:E)*(VALUE(AY96)<=名单!G:G)*(AA96="正常走货")),名单!H:H),"否") -> 否 | I96: CH20260131-1 | J96: KP | L96: 英国卡航-卡派-含税-KY | N96: 非主营 | U96: 张德士 | V96: 营销一部 | AA96: 正常走货 | AQ96: 100 | AY96: 2026-01-31 18:14:49
A97: =MID(AY97,1,7) -> 2026-01 | B97: =_xlfn.XLOOKUP(I97,过机服务商重量差!A:A,过机服务商重量差!G:G) -> 无崖子 | C97: =IF(N97="FBA","主营产品",IF(N97="专线","专线",LOOKUP(1,0/((G97>=提成标准!D:D)*(G97<提成标准!E:E)),提成标准!C:C))) -> 快递大货 | D97: =IF(C97="快递小货",1,IF(C97="主营产品",0,G97)) -> 62 | E97: =_xlfn.XLOOKUP(C97,提成标准!C:C,提成标准!H:H,"") -> 0.1 | F97: =D97*E97 -> 6.2 | G97: =_xlfn.XLOOKUP(I97,过机服务商重量差!A:A,过机服务商重量差!L:L) -> 62 | H97: =IFERROR(LOOKUP(1,0/((B97=名单!B:B)*(VALUE(AY97)>=名单!E:E)*(VALUE(AY97)<=名单!G:G)*(AA97="正常走货")),名单!H:H),"否") -> 是 | I97: JYZ26013101 | J97: 1ZX30Y730490393478 | L97: 义乌UPS红单直发包税/5000 | N97: 非主营 | U97: 张小雪 | V97: 营销五部 | AA97: 正常走货 | AQ97: 31.4 | AY97: 2026-01-31 18:09:43
A98: =MID(AY98,1,7) -> 2026-01 | B98: =_xlfn.XLOOKUP(I98,过机服务商重量差!A:A,过机服务商重量差!G:G) -> 无崖子 | C98: =IF(N98="FBA","主营产品",IF(N98="专线","专线",LOOKUP(1,0/((G98>=提成标准!D:D)*(G98<提成标准!E:E)),提成标准!C:C))) -> 快递大货 | D98: =IF(C98="快递小货",1,IF(C98="主营产品",0,G98)) -> 55 | E98: =_xlfn.XLOOKUP(C98,提成标准!C:C,提成标准!H:H,"") -> 0.1 | F98: =D98*E98 -> 5.5 | G98: =_xlfn.XLOOKUP(I98,过机服务商重量差!A:A,过机服务商重量差!L:L) -> 55 | H98: =IFERROR(LOOKUP(1,0/((B98=名单!B:B)*(VALUE(AY98)>=名单!E:E)*(VALUE(AY98)<=名单!G:G)*(AA98="正常走货")),名单!H:H),"否") -> 是 | I98: JYZ26013102 | J98: 1ZX30Y730498888581 | L98: 义乌UPS红单直发包税/5000 | N98: 非主营 | U98: 张小雪 | V98: 营销五部 | AA98: 正常走货 | AQ98: 27.9 | AY98: 2026-01-31 18:05:23
A99: =MID(AY99,1,7) -> 2026-01 | B99: =_xlfn.XLOOKUP(I99,过机服务商重量差!A:A,过机服务商重量差!G:G) -> 小旋风 | C99: =IF(N99="FBA","主营产品",IF(N99="专线","专线",LOOKUP(1,0/((G99>=提成标准!D:D)*(G99<提成标准!E:E)),提成标准!C:C))) -> 快递大货 | D99: =IF(C99="快递小货",1,IF(C99="主营产品",0,G99)) -> 429.5 | E99: =_xlfn.XLOOKUP(C99,提成标准!C:C,提成标准!H:H,"") -> 0.1 | F99: =D99*E99 -> 42.95 | G99: =_xlfn.XLOOKUP(I99,过机服务商重量差!A:A,过机服务商重量差!L:L) -> 429.5 | H99: =IFERROR(LOOKUP(1,0/((B99=名单!B:B)*(VALUE(AY99)>=名单!E:E)*(VALUE(AY99)<=名单!G:G)*(AA99="正常走货")),名单!H:H),"否") -> 否 | I99: JLL260131A | J99: MKP4534281830 | L99: 澳大利亚空派-大陆飞-SC | N99: 非主营 | U99: 陈炎 | V99: 营销二部 | AA99: 正常走货 | AQ99: 2700.03 | AY99: 2026-01-31 17:59:41
A100: =MID(AY100,1,7) -> 2026-01 | B100: =_xlfn.XLOOKUP(I100,过机服务商重量差!A:A,过机服务商重量差!G:G) -> 小旋风 | C100: =IF(N100="FBA","主营产品",IF(N100="专线","专线",LOOKUP(1,0/((G100>=提成标准!D:D)*(G100<提成标准!E:E)),提成标准!C:C))) -> 快递大货 | D100: =IF(C100="快递小货",1,IF(C100="主营产品",0,G100)) -> 30 | E100: =_xlfn.XLOOKUP(C100,提成标准!C:C,提成标准!H:H,"") -> 0.1 | F100: =D100*E100 -> 3 | G100: =_xlfn.XLOOKUP(I100,过机服务商重量差!A:A,过机服务商重量差!L:L) -> 30 | H100: =IFERROR(LOOKUP(1,0/((B100=名单!B:B)*(VALUE(AY100)>=名单!E:E)*(VALUE(AY100)<=名单!G:G)*(AA100="正常走货")),名单!H:H),"否") -> 否 | I100: JLL260131B | J100: TPL600032612 | L100: 澳大利亚空派-大陆飞-SC | N100: 非主营 | U100: 陈炎 | V100: 营销二部 | AA100: 正常走货 | AQ100: 163 | AY100: 2026-01-31 17:59:29
A101: =MID(AY101,1,7) -> 2026-01 | B101: =_xlfn.XLOOKUP(I101,过机服务商重量差!A:A,过机服务商重量差!G:G) -> 玉麒麟 | C101: =IF(N101="FBA","主营产品",IF(N101="专线","专线",LOOKUP(1,0/((G101>=提成标准!D:D)*(G101<提成标准!E:E)),提成标准!C:C))) -> 快递小货 | D101: =IF(C101="快递小货",1,IF(C101="主营产品",0,G101)) -> 1 | E101: =_xlfn.XLOOKUP(C101,提成标准!C:C,提成标准!H:H,"") -> 2 | F101: =D101*E101 -> 2 | G101: =_xlfn.XLOOKUP(I101,过机服务商重量差!A:A,过机服务商重量差!L:L) -> 12 | H101: =IFERROR(LOOKUP(1,0/((B101=名单!B:B)*(VALUE(AY101)>=名单!E:E)*(VALUE(AY101)<=名单!G:G)*(AA101="正常走货")),名单!H:H),"否") -> 否 | I101: JLL260131C | J101: 888385218542 | L101: OK-FDX-DHL-TNT | N101: 非主营 | U101: 陈炎 | V101: 营销二部 | AA101: 正常走货 | AQ101: 89 | AY101: 2026-01-31 17:59:12
... A113: =MID(AY113,1,7) -> 2026-01 | B113: =_xlfn.XLOOKUP(I113,过机服务商重量差!A:A,过机服务商重量差!G:G) -> 玉麒麟 | C113: =IF(N113="FBA","主营产品",IF(N113="专线","专线",LOOKUP(1,0/((G113>=提成标准!D:D)*(G113<提成标准!E:E)),提成标准!C:C))) -> 快递小货 | D113: =IF(C113="快递小货",1,IF(C113="主营产品",0,G113)) -> 1 | E113: =_xlfn.XLOOKUP(C113,提成标准!C:C,提成标准!H:H,"") -> 2 | F113: =D113*E113 -> 2 | G113: =_xlfn.XLOOKUP(I113,过机服务商重量差!A:A,过机服务商重量差!L:L) -> 0.5 | H113: =IFERROR(LOOKUP(1,0/((B113=名单!B:B)*(VALUE(AY113)>=名单!E:E)*(VALUE(AY113)<=名单!G:G)*(AA113="正常走货")),名单!H:H),"否") -> 否 | I113: ZJTX2025803 | J113: 888386075311 | L113: OK-FDX-DHL-TNT | N113: 非主营 | U113: 陈玉琴 | V113: 营销五部 | AA113: 正常走货 | AQ113: 71.02 | AY113: 2026-01-31 16:55:46
A114: =MID(AY114,1,7) -> 2026-01 | B114: =_xlfn.XLOOKUP(I114,过机服务商重量差!A:A,过机服务商重量差!G:G) -> 玉麒麟 | C114: =IF(N114="FBA","主营产品",IF(N114="专线","专线",LOOKUP(1,0/((G114>=提成标准!D:D)*(G114<提成标准!E:E)),提成标准!C:C))) -> 快递小货 | D114: =IF(C114="快递小货",1,IF(C114="主营产品",0,G114)) -> 1 | E114: =_xlfn.XLOOKUP(C114,提成标准!C:C,提成标准!H:H,"") -> 2 | F114: =D114*E114 -> 2 | G114: =_xlfn.XLOOKUP(I114,过机服务商重量差!A:A,过机服务商重量差!L:L) -> 0.5 | H114: =IFERROR(LOOKUP(1,0/((B114=名单!B:B)*(VALUE(AY114)>=名单!E:E)*(VALUE(AY114)<=名单!G:G)*(AA114="正常走货")),名单!H:H),"否") -> 否 | I114: CZQ260130 | L114: OK-FDX-DHL-TNT | N114: 非主营 | U114: 蒋龙波 | V114: 营销三部 | AA114: 正常走货 | AQ114: 23.5 | AY114: 2026-01-31 16:55:40
A115: =MID(AY115,1,7) -> 2026-01 | B115: =_xlfn.XLOOKUP(I115,过机服务商重量差!A:A,过机服务商重量差!G:G) -> 007 | C115: =IF(N115="FBA","主营产品",IF(N115="专线","专线",LOOKUP(1,0/((G115>=提成标准!D:D)*(G115<提成标准!E:E)),提成标准!C:C))) -> 快递大货 | D115: =IF(C115="快递小货",1,IF(C115="主营产品",0,G115)) -> 26 | E115: =_xlfn.XLOOKUP(C115,提成标准!C:C,提成标准!H:H,"") -> 0.1 | F115: =D115*E115 -> 2.6 | G115: =_xlfn.XLOOKUP(I115,过机服务商重量差!A:A,过机服务商重量差!L:L) -> 26 | H115: =IFERROR(LOOKUP(1,0/((B115=名单!B:B)*(VALUE(AY115)>=名单!E:E)*(VALUE(AY115)<=名单!G:G)*(AA115="正常走货")),名单!H:H),"否") -> 否 | I115: FREDA707102 | J115: 1Z0R6D926803614290 | L115: 欧洲海派含税(快递派) | N115: 非主营 | U115: 高雨晴 | V115: 营销二部 | AA115: 正常走货 | AQ115: 223.6 | AY115: 2026-01-31 16:55:24
A116: =MID(AY116,1,7) -> 2026-01 | B116: =_xlfn.XLOOKUP(I116,过机服务商重量差!A:A,过机服务商重量差!G:G) -> 风清扬 | C116: =IF(N116="FBA","主营产品",IF(N116="专线","专线",LOOKUP(1,0/((G116>=提成标准!D:D)*(G116<提成标准!E:E)),提成标准!C:C))) -> 快递大货 | D116: =IF(C116="快递小货",1,IF(C116="主营产品",0,G116)) -> 326 | E116: =_xlfn.XLOOKUP(C116,提成标准!C:C,提成标准!H:H,"") -> 0.1 | F116: =D116*E116 -> 32.6 | G116: =_xlfn.XLOOKUP(I116,过机服务商重量差!A:A,过机服务商重量差!L:L) -> 326 | H116: =IFERROR(LOOKUP(1,0/((B116=名单!B:B)*(VALUE(AY116)>=名单!E:E)*(VALUE(AY116)<=名单!G:G)*(AA116="正常走货")),名单!H:H),"否") -> 否 | I116: LUNA9305523 | J116: 1Z0R6D896806053549 | L116: 欧洲快船-JT | N116: 非主营 | U116: 何林霞 | V116: 营销二部 | AA116: 正常走货 | AQ116: 2871 | AY116: 2026-01-31 16:54:57
A117: =MID(AY117,1,7) -> 2026-01 | B117: =_xlfn.XLOOKUP(I117,过机服务商重量差!A:A,过机服务商重量差!G:G) -> 007 | C117: =IF(N117="FBA","主营产品",IF(N117="专线","专线",LOOKUP(1,0/((G117>=提成标准!D:D)*(G117<提成标准!E:E)),提成标准!C:C))) -> 快递大货 | D117: =IF(C117="快递小货",1,IF(C117="主营产品",0,G117)) -> 3374 | E117: =_xlfn.XLOOKUP(C117,提成标准!C:C,提成标准!H:H,"") -> 0.1 | F117: =D117*E117 -> 337.4 | G117: =_xlfn.XLOOKUP(I117,过机服务商重量差!A:A,过机服务商重量差!L:L) -> 3374 | H117: =IFERROR(LOOKUP(1,0/((B117=名单!B:B)*(VALUE(AY117)>=名单!E:E)*(VALUE(AY117)<=名单!G:G)*(AA117="正常走货")),名单!H:H),"否") -> 否 | I117: RF-1147 | J117: 1Z0R6D926839601567 | L117: 欧洲海派含税(快递派) | N117: 非主营 | U117: 王拥 | V117: 营销二部 | AA117: 正常走货 | AQ117: 29016.4 | AY117: 2026-01-31 16:53:00
A118: =MID(AY118,1,7) -> 2026-01 | B118: =_xlfn.XLOOKUP(I118,过机服务商重量差!A:A,过机服务商重量差!G:G) -> 小旋风 | C118: =IF(N118="FBA","主营产品",IF(N118="专线","专线",LOOKUP(1,0/((G118>=提成标准!D:D)*(G118<提成标准!E:E)),提成标准!C:C))) -> 快递大货 | D118: =IF(C118="快递小货",1,IF(C118="主营产品",0,G118)) -> 22 | E118: =_xlfn.XLOOKUP(C118,提成标准!C:C,提成标准!H:H,"") -> 0.1 | F118: =D118*E118 -> 2.2 | G118: =_xlfn.XLOOKUP(I118,过机服务商重量差!A:A,过机服务商重量差!L:L) -> 22 | H118: =IFERROR(LOOKUP(1,0/((B118=名单!B:B)*(VALUE(AY118)>=名单!E:E)*(VALUE(AY118)<=名单!G:G)*(AA118="正常走货")),名单!H:H),"否") -> 否 | I118: FG260108020 | J118: AMQ6873655 | L118: 澳大利亚空派-经济线-SC | N118: 非主营 | U118: 李凤 | V118: 营销四部 | AA118: 正常走货 | AQ118: 110 | AY118: 2026-01-31 16:51:26
A119: =MID(AY119,1,7) -> 2026-01 | B119: =_xlfn.XLOOKUP(I119,过机服务商重量差!A:A,过机服务商重量差!G:G) -> 帅时莹 | C119: =IF(N119="FBA","主营产品",IF(N119="专线","专线",LOOKUP(1,0/((G119>=提成标准!D:D)*(G119<提成标准!E:E)),提成标准!C:C))) -> 快递大货 | D119: =IF(C119="快递小货",1,IF(C119="主营产品",0,G119)) -> 60 | E119: =_xlfn.XLOOKUP(C119,提成标准!C:C,提成标准!H:H,"") -> 0.1 | F119: =D119*E119 -> 6 | G119: =_xlfn.XLOOKUP(I119,过机服务商重量差!A:A,过机服务商重量差!L:L) -> 60 | H119: =IFERROR(LOOKUP(1,0/((B119=名单!B:B)*(VALUE(AY119)>=名单!E:E)*(VALUE(AY119)<=名单!G:G)*(AA119="正常走货")),名单!H:H),"否") -> 否 | I119: RC261302 | J119: SA780165875 | L119: 阿联酋专线-YT | N119: 非主营 | U119: 李凤 | V119: 营销四部 | AA119: 正常走货 | AQ119: 210 | AY119: 2026-01-31 16:47:46
A120: =MID(AY120,1,7) -> 2026-01 | B120: =_xlfn.XLOOKUP(I120,过机服务商重量差!A:A,过机服务商重量差!G:G) -> 玉麒麟 | C120: =IF(N120="FBA","主营产品",IF(N120="专线","专线",LOOKUP(1,0/((G120>=提成标准!D:D)*(G120<提成标准!E:E)),提成标准!C:C))) -> 快递大货 | D120: =IF(C120="快递小货",1,IF(C120="主营产品",0,G120)) -> 96 | E120: =_xlfn.XLOOKUP(C120,提成标准!C:C,提成标准!H:H,"") -> 0.1 | F120: =D120*E120 -> 9.6 | G120: =_xlfn.XLOOKUP(I120,过机服务商重量差!A:A,过机服务商重量差!L:L) -> 96 | H120: =IFERROR(LOOKUP(1,0/((B120=名单!B:B)*(VALUE(AY120)>=名单!E:E)*(VALUE(AY120)<=名单!G:G)*(AA120="正常走货")),名单!H:H),"否") -> 否 | I120: SQ260108002 | J120: 500745742652 | L120: OK-UPS蓝单 | N120: 非主营 | U120: 李凤 | V120: 营销四部 | AA120: 正常走货 | AQ120: 1779 | AY120: 2026-01-31 16:46:22
A121: =MID(AY121,1,7) -> 2026-01 | B121: =_xlfn.XLOOKUP(I121,过机服务商重量差!A:A,过机服务商重量差!G:G) | C121: =IF(N121="FBA","主营产品",IF(N121="专线","专线",LOOKUP(1,0/((G121>=提成标准!D:D)*(G121<提成标准!E:E)),提成标准!C:C))) -> 快递大货 | D121: =IF(C121="快递小货",1,IF(C121="主营产品",0,G121)) -> 3701 | E121: =_xlfn.XLOOKUP(C121,提成标准!C:C,提成标准!H:H,"") -> 0.1 | F121: =D121*E121 -> 370.1 | G121: =_xlfn.XLOOKUP(I121,过机服务商重量差!A:A,过机服务商重量差!L:L) -> 3701 | H121: =IFERROR(LOOKUP(1,0/((B121=名单!B:B)*(VALUE(AY121)>=名单!E:E)*(VALUE(AY121)<=名单!G:G)*(AA121="正常走货")),名单!H:H),"否") -> 否 | I121: FL-2601310E | L121: 美国WP | N121: 非主营 | U121: 陈炎 | V121: 营销二部 | AA121: 正常走货 | AQ121: 3709 | AY121: 2026-01-31 16:43:29
A122: =MID(AY122,1,7) -> 2026-01 | B122: =_xlfn.XLOOKUP(I122,过机服务商重量差!A:A,过机服务商重量差!G:G) -> 小旋风 | C122: =IF(N122="FBA","主营产品",IF(N122="专线","专线",LOOKUP(1,0/((G122>=提成标准!D:D)*(G122<提成标准!E:E)),提成标准!C:C))) -> 快递大货 | D122: =IF(C122="快递小货",1,IF(C122="主营产品",0,G122)) -> 431 | E122: =_xlfn.XLOOKUP(C122,提成标准!C:C,提成标准!H:H,"") -> 0.1 | F122: =D122*E122 -> 43.1 | G122: =_xlfn.XLOOKUP(I122,过机服务商重量差!A:A,过机服务商重量差!L:L) -> 431 | H122: =IFERROR(LOOKUP(1,0/((B122=名单!B:B)*(VALUE(AY122)>=名单!E:E)*(VALUE(AY122)<=名单!G:G)*(AA122="正常走货")),名单!H:H),"否") -> 否 | I122: HS457-77 | J122: SA-WJ24626 | L122: 沙特海派 | N122: 非主营 | U122: 左宗伟 | V122: 营销四部 | AA122: 正常走货 | AQ122: 3670 | AY122: 2026-01-31 16:42:07
A123: =MID(AY123,1,7) -> 2026-01 | B123: =_xlfn.XLOOKUP(I123,过机服务商重量差!A:A,过机服务商重量差!G:G) -> 007 | C123: =IF(N123="FBA","主营产品",IF(N123="专线","专线",LOOKUP(1,0/((G123>=提成标准!D:D)*(G123<提成标准!E:E)),提成标准!C:C))) -> 快递大货 | D123: =IF(C123="快递小货",1,IF(C123="主营产品",0,G123)) -> 865 | E123: =_xlfn.XLOOKUP(C123,提成标准!C:C,提成标准!H:H,"") -> 0.1 | F123: =D123*E123 -> 86.5 | G123: =_xlfn.XLOOKUP(I123,过机服务商重量差!A:A,过机服务商重量差!L:L) -> 865 | H123: =IFERROR(LOOKUP(1,0/((B123=名单!B:B)*(VALUE(AY123)>=名单!E:E)*(VALUE(AY123)<=名单!G:G)*(AA123="正常走货")),名单!H:H),"否") -> 否 | I123: RF-7704 | J123: 1Z0R6D926832267101 | L123: 欧洲海派含税(快递派) | N123: 非主营 | U123: 王拥 | V123: 营销二部 | AA123: 正常走货 | AQ123: 7439 | AY123: 2026-01-31 16:37:12
A124: =MID(AY124,1,7) -> 2026-01 | B124: =_xlfn.XLOOKUP(I124,过机服务商重量差!A:A,过机服务商重量差!G:G) -> 小旋风 | C124: =IF(N124="FBA","主营产品",IF(N124="专线","专线",LOOKUP(1,0/((G124>=提成标准!D:D)*(G124<提成标准!E:E)),提成标准!C:C))) -> 快递大货 | D124: =IF(C124="快递小货",1,IF(C124="主营产品",0,G124)) -> 150 | E124: =_xlfn.XLOOKUP(C124,提成标准!C:C,提成标准!H:H,"") -> 0.1 | F124: =D124*E124 -> 15 | G124: =_xlfn.XLOOKUP(I124,过机服务商重量差!A:A,过机服务商重量差!L:L) -> 150 | H124: =IFERROR(LOOKUP(1,0/((B124=名单!B:B)*(VALUE(AY124)>=名单!E:E)*(VALUE(AY124)<=名单!G:G)*(AA124="正常走货")),名单!H:H),"否") -> 否 | I124: YINHAI2544 | J124: MY4751 | L124: 沙特空派 | N124: 非主营 | U124: 左宗伟 | V124: 营销四部 | AA124: 正常走货 | AQ124: 830 | AY124: 2026-01-31 16:34:06
A125: =MID(AY125,1,7) -> 2026-01 | B125: =_xlfn.XLOOKUP(I125,过机服务商重量差!A:A,过机服务商重量差!G:G) -> 小旋风 | C125: =IF(N125="FBA","主营产品",IF(N125="专线","专线",LOOKUP(1,0/((G125>=提成标准!D:D)*(G125<提成标准!E:E)),提成标准!C:C))) -> 快递大货 | D125: =IF(C125="快递小货",1,IF(C125="主营产品",0,G125)) -> 1313 | E125: =_xlfn.XLOOKUP(C125,提成标准!C:C,提成标准!H:H,"") -> 0.1 | F125: =D125*E125 -> 131.3 | G125: =_xlfn.XLOOKUP(I125,过机服务商重量差!A:A,过机服务商重量差!L:L) -> 1313 | H125: =IFERROR(LOOKUP(1,0/((B125=名单!B:B)*(VALUE(AY125)>=名单!E:E)*(VALUE(AY125)<=名单!G:G)*(AA125="正常走货")),名单!H:H),"否") -> 否 | I125: LR260130 | J125: MKP24000759952 | L125: 私人地址海派双清含税（AU-S-02） | N125: 非主营 | U125: 孙源圻 | V125: 营销三部 | AA125: 正常走货 | AQ125: 8140.6 | AY125: 2026-01-31 16:32:23
A126: =MID(AY126,1,7) -> 2026-01 | B126: =_xlfn.XLOOKUP(I126,过机服务商重量差!A:A,过机服务商重量差!G:G) -> 帅时莹 | C126: =IF(N126="FBA","主营产品",IF(N126="专线","专线",LOOKUP(1,0/((G126>=提成标准!D:D)*(G126<提成标准!E:E)),提成标准!C:C))) -> 快递小货 | D126: =IF(C126="快递小货",1,IF(C126="主营产品",0,G126)) -> 1 | E126: =_xlfn.XLOOKUP(C126,提成标准!C:C,提成标准!H:H,"") -> 2 | F126: =D126*E126 -> 2 | G126: =_xlfn.XLOOKUP(I126,过机服务商重量差!A:A,过机服务商重量差!L:L) -> 1 | H126: =IFERROR(LOOKUP(1,0/((B126=名单!B:B)*(VALUE(AY126)>=名单!E:E)*(VALUE(AY126)<=名单!G:G)*(AA126="正常走货")),名单!H:H),"否") -> 否 | I126: FCO0018 | J126: 398309492050 | L126: YF-联邦包税小包 | N126: 非主营 | U126: 李可 | V126: 营销四部 | AA126: 正常走货 | AQ126: 102 | AY126: 2026-01-31 16:31:06
A127: =MID(AY127,1,7) -> 2026-01 | B127: =_xlfn.XLOOKUP(I127,过机服务商重量差!A:A,过机服务商重量差!G:G) -> 玉麒麟 | C127: =IF(N127="FBA","主营产品",IF(N127="专线","专线",LOOKUP(1,0/((G127>=提成标准!D:D)*(G127<提成标准!E:E)),提成标准!C:C))) -> 快递小货 | D127: =IF(C127="快递小货",1,IF(C127="主营产品",0,G127)) -> 1 | E127: =_xlfn.XLOOKUP(C127,提成标准!C:C,提成标准!H:H,"") -> 2 | F127: =D127*E127 -> 2 | G127: =_xlfn.XLOOKUP(I127,过机服务商重量差!A:A,过机服务商重量差!L:L) -> 1 | H127: =IFERROR(LOOKUP(1,0/((B127=名单!B:B)*(VALUE(AY127)>=名单!E:E)*(VALUE(AY127)<=名单!G:G)*(AA127="正常走货")),名单!H:H),"否") -> 否 | I127: LEKE29318 | J127: 398310485636 | L127: OK-FDX-DHL-TNT | N127: 非主营 | U127: 宋海周 | V127: 营销二部 | AA127: 正常走货 | AQ127: 44.6 | AY127: 2026-01-31 16:30:52
A128: =MID(AY128,1,7) -> 2026-01 | B128: =_xlfn.XLOOKUP(I128,过机服务商重量差!A:A,过机服务商重量差!G:G) -> 无崖子 | C128: =IF(N128="FBA","主营产品",IF(N128="专线","专线",LOOKUP(1,0/((G128>=提成标准!D:D)*(G128<提成标准!E:E)),提成标准!C:C))) -> 快递小货 | D128: =IF(C128="快递小货",1,IF(C128="主营产品",0,G128)) -> 1 | E128: =_xlfn.XLOOKUP(C128,提成标准!C:C,提成标准!H:H,"") -> 2 | F128: =D128*E128 -> 2 | G128: =_xlfn.XLOOKUP(I128,过机服务商重量差!A:A,过机服务商重量差!L:L) -> 1 | H128: =IFERROR(LOOKUP(1,0/((B128=名单!B:B)*(VALUE(AY128)>=名单!E:E)*(VALUE(AY128)<=名单!G:G)*(AA128="正常走货")),名单!H:H),"否") -> 是 | I128: BLS01307200 | J128: 1Z80F20X0423193076 | L128: FedEx-通用渠道 | N128: 非主营 | U128: 高雨晴 | V128: 营销二部 | AA128: 正常走货 | AQ128: 133.67 | AY128: 2026-01-31 16:30:47
A129: =MID(AY129,1,7) -> 2026-01 | B129: =_xlfn.XLOOKUP(I129,过机服务商重量差!A:A,过机服务商重量差!G:G) -> 玉麒麟 | C129: =IF(N129="FBA","主营产品",IF(N129="专线","专线",LOOKUP(1,0/((G129>=提成标准!D:D)*(G129<提成标准!E:E)),提成标准!C:C))) -> 快递小货 | D129: =IF(C129="快递小货",1,IF(C129="主营产品",0,G129)) -> 1 | E129: =_xlfn.XLOOKUP(C129,提成标准!C:C,提成标准!H:H,"") -> 2 | F129: =D129*E129 -> 2 | G129: =_xlfn.XLOOKUP(I129,过机服务商重量差!A:A,过机服务商重量差!L:L) -> 1 | H129: =IFERROR(LOOKUP(1,0/((B129=名单!B:B)*(VALUE(AY129)>=名单!E:E)*(VALUE(AY129)<=名单!G:G)*(AA129="正常走货")),名单!H:H),"否") -> 否 | I129: SHANELGORIAL26131-1 | J129: 1Z0E620D0405399626 | L129: OK-FDX-DHL-TNT | N129: 非主营 | U129: 丁佳伟 | V129: 营销三部 | AA129: 正常走货 | AQ129: 78.93 | AY129: 2026-01-31 16:25:09
A130: =MID(AY130,1,7) -> 2026-01 | B130: =_xlfn.XLOOKUP(I130,过机服务商重量差!A:A,过机服务商重量差!G:G) -> 风清扬 | C130: =IF(N130="FBA","主营产品",IF(N130="专线","专线",LOOKUP(1,0/((G130>=提成标准!D:D)*(G130<提成标准!E:E)),提成标准!C:C))) -> 快递大货 | D130: =IF(C130="快递小货",1,IF(C130="主营产品",0,G130)) -> 308 | E130: =_xlfn.XLOOKUP(C130,提成标准!C:C,提成标准!H:H,"") -> 0.1 | F130: =D130*E130 -> 30.8 | G130: =_xlfn.XLOOKUP(I130,过机服务商重量差!A:A,过机服务商重量差!L:L) -> 308 | H130: =IFERROR(LOOKUP(1,0/((B130=名单!B:B)*(VALUE(AY130)>=名单!E:E)*(VALUE(AY130)<=名单!G:G)*(AA130="正常走货")),名单!H:H),"否") -> 否 | I130: FBA19751BCG3 | J130: KP | L130: 加拿大海派-JY | N130: 非主营 | U130: 陈兵 | V130: 营销一部 | AA130: 正常走货 | AQ130: 1047.2 | AY130: 2026-01-31 16:15:10
A131: =MID(AY131,1,7) -> 2026-01 | B131: =_xlfn.XLOOKUP(I131,过机服务商重量差!A:A,过机服务商重量差!G:G) -> 帅时莹 | C131: =IF(N131="FBA","主营产品",IF(N131="专线","专线",LOOKUP(1,0/((G131>=提成标准!D:D)*(G131<提成标准!E:E)),提成标准!C:C))) -> 快递小货 | D131: =IF(C131="快递小货",1,IF(C131="主营产品",0,G131)) -> 1 | E131: =_xlfn.XLOOKUP(C131,提成标准!C:C,提成标准!H:H,"") -> 2 | F131: =D131*E131 -> 2 | G131: =_xlfn.XLOOKUP(I131,过机服务商重量差!A:A,过机服务商重量差!L:L) -> 2.5 | H131: =IFERROR(LOOKUP(1,0/((B131=名单!B:B)*(VALUE(AY131)>=名单!E:E)*(VALUE(AY131)<=名单!G:G)*(AA131="正常走货")),名单!H:H),"否") -> 否 | I131: CN260131-US-46806 | J131: 398309523280 | L131: YF-联邦包税小包 | N131: 非主营 | U131: 朱杰 | V131: 营销四部 | AA131: 正常走货 | AQ131: 76 | AY131: 2026-01-31 16:06:49
A132: =MID(AY132,1,7) -> 2026-01 | B132: =_xlfn.XLOOKUP(I132,过机服务商重量差!A:A,过机服务商重量差!G:G) -> 帅时莹 | C132: =IF(N132="FBA","主营产品",IF(N132="专线","专线",LOOKUP(1,0/((G132>=提成标准!D:D)*(G132<提成标准!E:E)),提成标准!C:C))) -> 快递小货 | D132: =IF(C132="快递小货",1,IF(C132="主营产品",0,G132)) -> 1 | E132: =_xlfn.XLOOKUP(C132,提成标准!C:C,提成标准!H:H,"") -> 2 | F132: =D132*E132 -> 2 | G132: =_xlfn.XLOOKUP(I132,过机服务商重量差!A:A,过机服务商重量差!L:L) -> 2.5 | H132: =IFERROR(LOOKUP(1,0/((B132=名单!B:B)*(VALUE(AY132)>=名单!E:E)*(VALUE(AY132)<=名单!G:G)*(AA132="正常走货")),名单!H:H),"否") -> 否 | I132: CN260131-US-52552 | J132: 398309602860 | L132: YF-联邦包税小包 | N132: 非主营 | U132: 朱杰 | V132: 营销四部 | AA132: 正常走货 | AQ132: 76 | AY132: 2026-01-31 16:06:40
A133: =MID(AY133,1,7) -> 2026-01 | B133: =_xlfn.XLOOKUP(I133,过机服务商重量差!A:A,过机服务商重量差!G:G) -> 帅时莹 | C133: =IF(N133="FBA","主营产品",IF(N133="专线","专线",LOOKUP(1,0/((G133>=提成标准!D:D)*(G133<提成标准!E:E)),提成标准!C:C))) -> 快递小货 | D133: =IF(C133="快递小货",1,IF(C133="主营产品",0,G133)) -> 1 | E133: =_xlfn.XLOOKUP(C133,提成标准!C:C,提成标准!H:H,"") -> 2 | F133: =D133*E133 -> 2 | G133: =_xlfn.XLOOKUP(I133,过机服务商重量差!A:A,过机服务商重量差!L:L) -> 3 | H133: =IFERROR(LOOKUP(1,0/((B133=名单!B:B)*(VALUE(AY133)>=名单!E:E)*(VALUE(AY133)<=名单!G:G)*(AA133="正常走货")),名单!H:H),"否") -> 否 | I133: CN260131-US-33778 | J133: 398309593703 | L133: YF-联邦包税小包 | N133: 非主营 | U133: 朱杰 | V133: 营销四部 | AA133: 正常走货 | AQ133: 46 | AY133: 2026-01-31 16:06:34
... A154: =MID(AY154,1,7) -> 2026-01 | B154: =_xlfn.XLOOKUP(I154,过机服务商重量差!A:A,过机服务商重量差!G:G) -> 帅时莹 | C154: =IF(N154="FBA","主营产品",IF(N154="专线","专线",LOOKUP(1,0/((G154>=提成标准!D:D)*(G154<提成标准!E:E)),提成标准!C:C))) -> 快递小货 | D154: =IF(C154="快递小货",1,IF(C154="主营产品",0,G154)) -> 1 | E154: =_xlfn.XLOOKUP(C154,提成标准!C:C,提成标准!H:H,"") -> 2 | F154: =D154*E154 -> 2 | G154: =_xlfn.XLOOKUP(I154,过机服务商重量差!A:A,过机服务商重量差!L:L) -> 10 | H154: =IFERROR(LOOKUP(1,0/((B154=名单!B:B)*(VALUE(AY154)>=名单!E:E)*(VALUE(AY154)<=名单!G:G)*(AA154="正常走货")),名单!H:H),"否") -> 否 | I154: JT0131-1 | J154: 1Z0E793D6704433474 | L154: MSHQ-UPS | N154: 非主营 | U154: 王涛 | V154: 营销四部 | AA154: 正常走货 | AQ154: 86.35 | AY154: 2026-01-31 15:33:10
A155: =MID(AY155,1,7) -> 2026-01 | B155: =_xlfn.XLOOKUP(I155,过机服务商重量差!A:A,过机服务商重量差!G:G) -> 无崖子 | C155: =IF(N155="FBA","主营产品",IF(N155="专线","专线",LOOKUP(1,0/((G155>=提成标准!D:D)*(G155<提成标准!E:E)),提成标准!C:C))) -> 快递大货 | D155: =IF(C155="快递小货",1,IF(C155="主营产品",0,G155)) -> 56 | E155: =_xlfn.XLOOKUP(C155,提成标准!C:C,提成标准!H:H,"") -> 0.1 | F155: =D155*E155 -> 5.6 | G155: =_xlfn.XLOOKUP(I155,过机服务商重量差!A:A,过机服务商重量差!L:L) -> 56 | H155: =IFERROR(LOOKUP(1,0/((B155=名单!B:B)*(VALUE(AY155)>=名单!E:E)*(VALUE(AY155)<=名单!G:G)*(AA155="正常走货")),名单!H:H),"否") -> 否 | I155: YKZXX013101 | L155: 义乌联邦IE-包税 | N155: 非主营 | U155: 张小雪 | V155: 营销五部 | AA155: 已退件 | AQ155: 0 | AY155: 2026-01-31 15:33:00
A156: =MID(AY156,1,7) -> 2026-01 | B156: =_xlfn.XLOOKUP(I156,过机服务商重量差!A:A,过机服务商重量差!G:G) -> 风清扬 | C156: =IF(N156="FBA","主营产品",IF(N156="专线","专线",LOOKUP(1,0/((G156>=提成标准!D:D)*(G156<提成标准!E:E)),提成标准!C:C))) -> 快递大货 | D156: =IF(C156="快递小货",1,IF(C156="主营产品",0,G156)) -> 72 | E156: =_xlfn.XLOOKUP(C156,提成标准!C:C,提成标准!H:H,"") -> 0.1 | F156: =D156*E156 -> 7.2 | G156: =_xlfn.XLOOKUP(I156,过机服务商重量差!A:A,过机服务商重量差!L:L) -> 72 | H156: =IFERROR(LOOKUP(1,0/((B156=名单!B:B)*(VALUE(AY156)>=名单!E:E)*(VALUE(AY156)<=名单!G:G)*(AA156="正常走货")),名单!H:H),"否") -> 否 | I156: HZHF0037 | J156: 1ZHF34022038229695 | L156: 加拿大海派-JY | N156: 非主营 | U156: 叶伟明 | V156: 营销一部 | AA156: 正常走货 | AQ156: 36 | AY156: 2026-01-31 15:32:33
...

Sheet 名单
A1: 姓名 | B1: 客服系统名 | C1: 姓名 | D1: 入职时间 | E1: 提成计算开始日期 | F1: 结束日期（手填） | G1: 结束日期 | H1: 是否计算提成
B2: 无崖子 | C2: 陈巧玲 | E2: 45078 | G2: =IF(F2="",TODAY(),F2) -> 46114 | H2: 是
B3: 霹雳火-快递客服(杨帆) | C3: 杨帆 | E3: 45123 | F3: 45276 | G3: =IF(F3="",TODAY(),F3) -> 45276 | H3: 是

Sheet 提成标准
A2: 渠道 | B2: 中转状态 | D2: 大于等于 | E2: 小于 | F2: 取数 | G2: 单位 | H2: 提成系数（元） | N2: 渠道 | O2: 中转状态 | Q2: 大于等于 | R2: 小于 | S2: 取数 | T2: 单位 | U2: 提成系数（元） | V2: 截止到2023.12.14（其中杨帆的是到离职日16日）
A3: 快递 | B3: 正常走货 | C3: 快递小货 | D3: 0 | E3: 21 | F3: 1 | G3: 票 | H3: 2 | I3: 2元/票 | N3: 快递 | O3: 正常走货 | P3: 快递小货 | Q3: 0 | R3: 21 | S3: 1 | T3: 票 | U3: 2 | V3: 2元/票
A4: 快递 | B4: 正常走货 | C4: 快递大货 | D4: 21 | E4: 99999 | F4: 出货计费重 | G4: KG | H4: 0.1 | I4: 0.1元/KG | N4: 快递 | O4: 正常走货 | P4: 快递大货 | Q4: 21 | R4: 99999 | S4: 出货计费重 | T4: KG | U4: 0.2 | V4: 0.2元/KG
A5: 专线 | B5: 正常走货 | C5: 专线 | F5: 出货计费重 | G5: KG | H5: 0.1 | I5: 0.1元/KG | N5: 专线 | O5: 正常走货 | P5: 专线 | S5: 出货计费重 | T5: KG | U5: 0.1 | V5: 0.1元/KG
A6: 主营产品 | C6: 主营产品 | H6: 0 | N6: 主营产品 | P6: 主营产品 | U6: 0
N8: 渠道 | O8: 中转状态 | Q8: 大于等于 | R8: 小于 | S8: 取数 | T8: 单位 | U8: 提成系数（元） | V8: 2023.12.15开始
N9: 快递 | O9: 正常走货 | P9: 快递小货 | Q9: 0 | R9: 21 | S9: 1 | T9: 票 | U9: 2 | V9: 2元/票
N10: 快递 | O10: 正常走货 | P10: 快递大货 | Q10: 21 | R10: 99999 | S10: 出货计费重 | T10: KG | U10: 0.1 | V10: 0.1元/KG
N11: 专线 | O11: 正常走货 | P11: 专线 | S11: 出货计费重 | T11: KG | U11: 0.1 | V11: 0.1元/KG
N12: 主营产品 | P12: 主营产品 | U12: 0

Sheet 特殊事项扣除
A1: 扣除期间 | B1: 客服名 | C1: 扣除金额 | D1: 单号期间 | E1: 备注 | F1: 单号
A2: 2023-07 | B2: 霹雳火-快递客服(杨帆) | C2: 724.12 | D2: 45110 | F2: TJ01532 | G2: =_xlfn.DISPIMG("ID_9F528AFC3D734C0F93B5BDB826E0677E",1) -> =DISPIMG("ID_9F528AFC3D734C0F93B5BDB826E0677E",1)
A3: 2023-08 | B3: 霹雳火-快递客服(杨帆) | C3: 0.7
A4: 2023-08 | B4: 霹雳火-快递客服(杨帆) | C4: 0.7
A5: 2023-08 | B5: 霹雳火-快递客服(杨帆) | C5: 0.71
A6: 2023-08 | B6: 霹雳火-快递客服(杨帆) | C6: 8.27
A7: 2023-08 | B7: 霹雳火-快递客服(杨帆) | C7: 14.68
A8: 2023-08 | B8: 霹雳火-快递客服(杨帆) | C8: 0.01
A9: 2023-08 | B9: 霹雳火-快递客服(杨帆) | C9: 10.69
A10: 2023-08 | B10: 霹雳火-快递客服(杨帆) | C10: 10.69
A11: 2023-08 | B11: 霹雳火-快递客服(杨帆) | C11: 13.35
A12: 2023-08 | B12: 霹雳火-快递客服(杨帆) | C12: 0.01
A13: 2023-08 | B13: 霹雳火-快递客服(杨帆) | C13: 12.69
A14: 2023-08 | B14: 霹雳火-快递客服(杨帆) | C14: 11.35
... A79: 2023-08 | B79: 霹雳火-快递客服(杨帆) | C79: 17.43

Sheet 提成
A1: 渠道客服提成明细表
D2: 快递小货 | E2: 快递大货 | F2: 专线 | G2: 快递小货 | H2: 快递大货 | I2: 专线 | J2: 快递小货 | K2: 快递大货 | L2: 专线
A3: 客服系统名 | B3: 姓名 | C3: 期间 | D3: 快递小货 票数 | E3: 快递大货 出货计费重 | F3: 专线 出货计费重 | G3: 快递小货 提成系数 | H3: 快递大货 提成系数 | I3: 专线 提成系数 | J3: 快递小货 提成 | K3: 快递大货 提成 | L3: 专线 提成 | M3: 应发提成 合计 | N3: 特殊事项扣除 | O3: 实发 提成
A4: 无崖子 | C4: =业务员明细!F1 -> 2026-01 | D4: =COUNTIFS(业务数据统计!$C:$C,$D$2,业务数据统计!$H:$H,"是",业务数据统计!$B:$B,$A4) -> 583 | E4: =SUMIFS(业务数据统计!$G:$G,业务数据统计!$C:$C,E$2,业务数据统计!$B:$B,$A4,业务数据统计!$H:$H,"是") -> 11759.5 | F4: =SUMIFS(业务数据统计!$G:$G,业务数据统计!$C:$C,F$2,业务数据统计!$B:$B,$A4,业务数据统计!$H:$H,"是") -> 0 | G4: =_xlfn.XLOOKUP(G$2,提成标准!$C:$C,提成标准!$H:$H) -> 2 | H4: =_xlfn.XLOOKUP(H$2,提成标准!$C:$C,提成标准!$H:$H) -> 0.1 | I4: =_xlfn.XLOOKUP(I$2,提成标准!$C:$C,提成标准!$H:$H) -> 0.1 | J4: =D4*G4 -> 1166 | K4: =H4*E4 -> 1175.95 | L4: =I4*F4 -> 0 | M4: =SUM(J4:L4) -> 2341.95 | N4: =SUMIFS(特殊事项扣除!C:C,特殊事项扣除!A:A,C4,特殊事项扣除!B:B,A4) -> 0 | O4: =M4-N4 -> 2341.95 | P4: 其中发给江雯756元，剩余的是渠道部的成本
A5: 合计： | D5: =SUM(D4:D4) -> 583 | E5: =SUM(E4:E4) -> 11759.5 | F5: =SUM(F4:F4) -> 0 | G5: =_xlfn.XLOOKUP(G$2,提成标准!$C:$C,提成标准!$H:$H) -> 2 | H5: =_xlfn.XLOOKUP(H$2,提成标准!$C:$C,提成标准!$H:$H) -> 0.1 | I5: =_xlfn.XLOOKUP(I$2,提成标准!$C:$C,提成标准!$H:$H) -> 0.1 | J5: =SUM(J4:J4) -> 1166 | K5: =SUM(K4:K4) -> 1175.95 | L5: =SUM(L4:L4) -> 0 | M5: =SUM(M4:M4) -> 2341.95 | N5: =SUM(N4:N4) -> 0 | O5: =SUM(O4:O4) -> 2341.95
N7: 制表人：
I12: 此表是渠道部提成数据，只登记，但不发放提成 | N12: 目前是按照江雯的单独提成制度发给江雯提成

Sheet 业务员明细
A1: 渠道客服提成明细表（业务员承担） | F1: 2026-01
A2: 系统名 | B2: 部门 | C2: 运单期间 | D2: 承担金额 | E2: 部门
A3: 柴燕玲 | B3: =_xlfn.XLOOKUP(E3,部门!A:A,部门!B:B) -> 销售四部 | C3: =$F$1 -> 2026-01 | D3: =SUMIFS(业务数据统计!F:F,业务数据统计!U:U,A3,业务数据统计!H:H,"是") -> 62.5 | E3: =_xlfn.XLOOKUP(A3,业务数据统计!U:U,业务数据统计!V:V,"") -> 四部KA客服
A4: 冯青青 | B4: =_xlfn.XLOOKUP(E4,部门!A:A,部门!B:B) -> 销售五部 | C4: =$F$1 -> 2026-01 | D4: =SUMIFS(业务数据统计!F:F,业务数据统计!U:U,A4,业务数据统计!H:H,"是") -> 177 | E4: =_xlfn.XLOOKUP(A4,业务数据统计!U:U,业务数据统计!V:V,"") -> 营销五部
A5: 张小雪 | B5: =_xlfn.XLOOKUP(E5,部门!A:A,部门!B:B) -> 销售五部 | C5: =$F$1 -> 2026-01 | D5: =SUMIFS(业务数据统计!F:F,业务数据统计!U:U,A5,业务数据统计!H:H,"是") -> 216.1 | E5: =_xlfn.XLOOKUP(A5,业务数据统计!U:U,业务数据统计!V:V,"") -> 营销五部
A6: 李可 | B6: =_xlfn.XLOOKUP(E6,部门!A:A,部门!B:B) -> 销售四部 | C6: =$F$1 -> 2026-01 | D6: =SUMIFS(业务数据统计!F:F,业务数据统计!U:U,A6,业务数据统计!H:H,"是") -> 238.5 | E6: =_xlfn.XLOOKUP(A6,业务数据统计!U:U,业务数据统计!V:V,"") -> 营销四部
A7: 臧明 | B7: =_xlfn.XLOOKUP(E7,部门!A:A,部门!B:B) -> 销售四部 | C7: =$F$1 -> 2026-01 | D7: =SUMIFS(业务数据统计!F:F,业务数据统计!U:U,A7,业务数据统计!H:H,"是") -> 93.9 | E7: =_xlfn.XLOOKUP(A7,业务数据统计!U:U,业务数据统计!V:V,"") -> 北苑总经办
A8: 施建祥 | B8: =_xlfn.XLOOKUP(E8,部门!A:A,部门!B:B) -> 销售三部 | C8: =$F$1 -> 2026-01 | D8: =SUMIFS(业务数据统计!F:F,业务数据统计!U:U,A8,业务数据统计!H:H,"是") -> 6 | E8: =_xlfn.XLOOKUP(A8,业务数据统计!U:U,业务数据统计!V:V,"") -> 营销三部 | G8: 杭州 | H8: =SUMIFS(D:D,B:B,G8) -> 2
A9: 陈颖 | B9: =_xlfn.XLOOKUP(E9,部门!A:A,部门!B:B) -> 销售五部 | C9: =$F$1 -> 2026-01 | D9: =SUMIFS(业务数据统计!F:F,业务数据统计!U:U,A9,业务数据统计!H:H,"是") -> 215.6 | E9: =_xlfn.XLOOKUP(A9,业务数据统计!U:U,业务数据统计!V:V,"") -> 营销五部 | G9: 宁波 | H9: =SUMIFS(D:D,B:B,G9) -> 8.5
A10: 高雨晴 | B10: =_xlfn.XLOOKUP(E10,部门!A:A,部门!B:B) -> 销售二部 | C10: =$F$1 -> 2026-01 | D10: =SUMIFS(业务数据统计!F:F,业务数据统计!U:U,A10,业务数据统计!H:H,"是") -> 6 | E10: =_xlfn.XLOOKUP(A10,业务数据统计!U:U,业务数据统计!V:V,"") -> 营销二部 | G10: 台州 | H10: =SUMIFS(D:D,B:B,G10) -> 2
A11: 张雪 | B11: =_xlfn.XLOOKUP(E11,部门!A:A,部门!B:B) -> 销售四部 | C11: =$F$1 -> 2026-01 | D11: =SUMIFS(业务数据统计!F:F,业务数据统计!U:U,A11,业务数据统计!H:H,"是") -> 56.5 | E11: =_xlfn.XLOOKUP(A11,业务数据统计!U:U,业务数据统计!V:V,"") -> 营销四部 | G11: 销售二部 | H11: =SUMIFS(D:D,B:B,G11) -> 118.6
A12: 丁佳伟 | B12: =_xlfn.XLOOKUP(E12,部门!A:A,部门!B:B) -> 销售三部 | C12: =$F$1 -> 2026-01 | D12: =SUMIFS(业务数据统计!F:F,业务数据统计!U:U,A12,业务数据统计!H:H,"是") -> 286.9 | E12: =_xlfn.XLOOKUP(A12,业务数据统计!U:U,业务数据统计!V:V,"") -> 营销三部 | G12: 销售三部 | H12: =SUMIFS(D:D,B:B,G12) -> 503.5
A13: 黄小丽 | B13: =_xlfn.XLOOKUP(E13,部门!A:A,部门!B:B) -> 销售四部 | C13: =$F$1 -> 2026-01 | D13: =SUMIFS(业务数据统计!F:F,业务数据统计!U:U,A13,业务数据统计!H:H,"是") -> 8 | E13: =_xlfn.XLOOKUP(A13,业务数据统计!U:U,业务数据统计!V:V,"") -> 营销四部 | G13: 销售四部 | H13: =SUMIFS(D:D,B:B,G13) -> 765.4
A14: 宋海周 | B14: =_xlfn.XLOOKUP(E14,部门!A:A,部门!B:B) -> 销售二部 | C14: =$F$1 -> 2026-01 | D14: =SUMIFS(业务数据统计!F:F,业务数据统计!U:U,A14,业务数据统计!H:H,"是") -> 26.6 | E14: =_xlfn.XLOOKUP(A14,业务数据统计!U:U,业务数据统计!V:V,"") -> 营销二部 | G14: 销售五部 | H14: =SUMIFS(D:D,B:B,G14) -> 907.85
A15: 陈巧玲 | B15: =_xlfn.XLOOKUP(E15,部门!A:A,部门!B:B) -> 销售三部 | C15: =$F$1 -> 2026-01 | D15: =SUMIFS(业务数据统计!F:F,业务数据统计!U:U,A15,业务数据统计!H:H,"是") -> 4 | E15: =_xlfn.XLOOKUP(A15,业务数据统计!U:U,业务数据统计!V:V,"") -> 营销三部 | G15: 销售一部 | H15: =SUMIFS(D:D,B:B,G15) -> 34.1
A16: 段泽明 | B16: =_xlfn.XLOOKUP(E16,部门!A:A,部门!B:B) -> 销售三部 | C16: =$F$1 -> 2026-01 | D16: =SUMIFS(业务数据统计!F:F,业务数据统计!U:U,A16,业务数据统计!H:H,"是") -> 61.9 | E16: =_xlfn.XLOOKUP(A16,业务数据统计!U:U,业务数据统计!V:V,"") -> 营销三部
A17: 吴丽辉 | B17: =_xlfn.XLOOKUP(E17,部门!A:A,部门!B:B) -> 销售三部 | C17: =$F$1 -> 2026-01 | D17: =SUMIFS(业务数据统计!F:F,业务数据统计!U:U,A17,业务数据统计!H:H,"是") -> 49.1 | E17: =_xlfn.XLOOKUP(A17,业务数据统计!U:U,业务数据统计!V:V,"") -> 营销三部
A18: 李凤 | B18: =_xlfn.XLOOKUP(E18,部门!A:A,部门!B:B) -> 销售四部 | C18: =$F$1 -> 2026-01 | D18: =SUMIFS(业务数据统计!F:F,业务数据统计!U:U,A18,业务数据统计!H:H,"是") -> 22.9 | E18: =_xlfn.XLOOKUP(A18,业务数据统计!U:U,业务数据统计!V:V,"") -> 营销四部
A19: 汪祺 | B19: =_xlfn.XLOOKUP(E19,部门!A:A,部门!B:B) -> 销售二部 | C19: =$F$1 -> 2026-01 | D19: =SUMIFS(业务数据统计!F:F,业务数据统计!U:U,A19,业务数据统计!H:H,"是") -> 8 | E19: =_xlfn.XLOOKUP(A19,业务数据统计!U:U,业务数据统计!V:V,"") -> 营销二部 | H19: =SUM(H8:H17) -> 2341.95
A20: 朱杰 | B20: =_xlfn.XLOOKUP(E20,部门!A:A,部门!B:B) -> 销售四部 | C20: =$F$1 -> 2026-01 | D20: =SUMIFS(业务数据统计!F:F,业务数据统计!U:U,A20,业务数据统计!H:H,"是") -> 80.8 | E20: =_xlfn.XLOOKUP(A20,业务数据统计!U:U,业务数据统计!V:V,"") -> 营销四部
A21: 邓健群 | B21: =_xlfn.XLOOKUP(E21,部门!A:A,部门!B:B) -> 销售三部 | C21: =$F$1 -> 2026-01 | D21: =SUMIFS(业务数据统计!F:F,业务数据统计!U:U,A21,业务数据统计!H:H,"是") -> 15.8 | E21: =_xlfn.XLOOKUP(A21,业务数据统计!U:U,业务数据统计!V:V,"") -> 营销三部
A22: 王岩岩 | B22: =_xlfn.XLOOKUP(E22,部门!A:A,部门!B:B) -> 销售四部 | C22: =$F$1 -> 2026-01 | D22: =SUMIFS(业务数据统计!F:F,业务数据统计!U:U,A22,业务数据统计!H:H,"是") -> 28 | E22: =_xlfn.XLOOKUP(A22,业务数据统计!U:U,业务数据统计!V:V,"") -> 营销四部
A23: 李得胜 | B23: =_xlfn.XLOOKUP(E23,部门!A:A,部门!B:B) -> 销售四部 | C23: =$F$1 -> 2026-01 | D23: =SUMIFS(业务数据统计!F:F,业务数据统计!U:U,A23,业务数据统计!H:H,"是") -> 4 | E23: =_xlfn.XLOOKUP(A23,业务数据统计!U:U,业务数据统计!V:V,"") -> 营销四部
A24: 小飞侠 | B24: =_xlfn.XLOOKUP(E24,部门!A:A,部门!B:B) -> 销售五部 | C24: =$F$1 -> 2026-01 | D24: =SUMIFS(业务数据统计!F:F,业务数据统计!U:U,A24,业务数据统计!H:H,"是") -> 73.45 | E24: =_xlfn.XLOOKUP(A24,业务数据统计!U:U,业务数据统计!V:V,"") -> 营销五部
A25: 许会彦 | B25: =_xlfn.XLOOKUP(E25,部门!A:A,部门!B:B) -> 销售四部 | C25: =$F$1 -> 2026-01 | D25: =SUMIFS(业务数据统计!F:F,业务数据统计!U:U,A25,业务数据统计!H:H,"是") -> 2 | E25: =_xlfn.XLOOKUP(A25,业务数据统计!U:U,业务数据统计!V:V,"") -> 营销四部
A26: 余雨婕 | B26: =_xlfn.XLOOKUP(E26,部门!A:A,部门!B:B) -> 销售四部 | C26: =$F$1 -> 2026-01 | D26: =SUMIFS(业务数据统计!F:F,业务数据统计!U:U,A26,业务数据统计!H:H,"是") -> 14 | E26: =_xlfn.XLOOKUP(A26,业务数据统计!U:U,业务数据统计!V:V,"") -> 营销四部
A27: 左宗伟 | B27: =_xlfn.XLOOKUP(E27,部门!A:A,部门!B:B) -> 销售四部 | C27: =$F$1 -> 2026-01 | D27: =SUMIFS(业务数据统计!F:F,业务数据统计!U:U,A27,业务数据统计!H:H,"是") -> 50.6 | E27: =_xlfn.XLOOKUP(A27,业务数据统计!U:U,业务数据统计!V:V,"") -> 营销四部
A28: 张俊合 | B28: =_xlfn.XLOOKUP(E28,部门!A:A,部门!B:B) -> 销售五部 | C28: =$F$1 -> 2026-01 | D28: =SUMIFS(业务数据统计!F:F,业务数据统计!U:U,A28,业务数据统计!H:H,"是") -> 35.3 | E28: =_xlfn.XLOOKUP(A28,业务数据统计!U:U,业务数据统计!V:V,"") -> 营销五部
A29: 杨胜东 | B29: =_xlfn.XLOOKUP(E29,部门!A:A,部门!B:B) -> 销售四部 | C29: =$F$1 -> 2026-01 | D29: =SUMIFS(业务数据统计!F:F,业务数据统计!U:U,A29,业务数据统计!H:H,"是") -> 11.6 | E29: =_xlfn.XLOOKUP(A29,业务数据统计!U:U,业务数据统计!V:V,"") -> 营销四部
A30: 陈炎 | B30: =_xlfn.XLOOKUP(E30,部门!A:A,部门!B:B) -> 销售二部 | C30: =$F$1 -> 2026-01 | D30: =SUMIFS(业务数据统计!F:F,业务数据统计!U:U,A30,业务数据统计!H:H,"是") -> 12 | E30: =_xlfn.XLOOKUP(A30,业务数据统计!U:U,业务数据统计!V:V,"") -> 营销二部
A31: 付乐航 | B31: =_xlfn.XLOOKUP(E31,部门!A:A,部门!B:B) -> 销售五部 | C31: =$F$1 -> 2026-01 | D31: =SUMIFS(业务数据统计!F:F,业务数据统计!U:U,A31,业务数据统计!H:H,"是") -> 119.9 | E31: =_xlfn.XLOOKUP(A31,业务数据统计!U:U,业务数据统计!V:V,"") -> 营销五部
... A63: 魏心华 | B63: =_xlfn.XLOOKUP(E63,部门!A:A,部门!B:B) -> 销售四部 | C63: =$F$1 -> 2026-01 | D63: =SUMIFS(业务数据统计!F:F,业务数据统计!U:U,A63,业务数据统计!H:H,"是") -> 4 | E63: =_xlfn.XLOOKUP(A63,业务数据统计!U:U,业务数据统计!V:V,"") -> 营销四部
A64: 合计： | D64: =SUM(D3:D63) -> 2341.95

Sheet 部门
A1: 业务员部门 | B1: 部门
A2: KA部-亮剑队 | B2: KA部
A3: KA部-一组长 | B3: KA部
A4: KA部-群英队 | B4: KA部
A5: 北苑-业务员 | B5: 北苑
A6: 北苑-业务员-陈伟 | B6: 北苑
A7: 北苑-业务员-冯玉勋 | B7: 北苑
A8: 广州分公司-业务员 | B8: 广州
A9: 广州分公司-业务员(曹深研) | B9: 广州
A10: 广州分公司-业务员(练思强) | B10: 广州
A11: 广州分公司-业务员(周源伟) | B11: 广州
A12: 广州分公司-业务员-马井贝 | B12: 广州
... A22: 深圳-业务员-刘薇 | B22: 深圳
A23: 深圳-直客-业务员 | B23: 深圳 | E23: 、
A24: 深圳-直客-坂田 | B24: 深圳
A25: 拓展部-飓风队 | B25: 拓展部-直客
A26: 吴慧俊
A27: 下王公司-业务员 | B27: 下王
A28: 下王公司-总经理 | B28: 下王
A29: 下王-业务员 | B29: 下王
A30: 销售二部-第一队 | B30: 销售二部
A31: 销售二部-昊阳队 | B31: 销售二部
A32: 销售二部-烈火队 | B32: 销售二部
A33: 销售二部-野狼队 | B33: 销售二部
A34: 销售三部-战狼队 | B34: 销售三部
A35: 销售三部-主管 | B35: 销售三部
A36: 销售一部-火箭队 | B36: 销售一部
A37: 销售一部-迈凯伦队 | B37: 销售一部
A38: 销售一部-王炸队 | B38: 销售一部
... A90: 四部KA客服 | B90: 销售四部

Sheet 无崖子提成
B4: 渠道客服提成明细表
B5: 客服系统名 | C5: 姓名 | D5: 票数 | E5: 提成系数 | F5: 应发提成 | G5: 特殊事项扣除 | H5: 实发工资
B6: 无崖子 | C6: 江雯 | D6: =COUNTIFS(业务数据统计!B:B,B6,业务数据统计!AA:AA,"正常走货") -> 756 | E6: 1 | F6: =D6*E6 -> 756 | H6: =F6-G6 -> 756
B9: 2025年6月6日起江雯开始有提成
